Workbook
Name Apr: 横カレンダー!DaysAndWeeks+DATE(CalendarYear,4,1)-WEEKDAY(DATE(CalendarYear,4,1),横カレンダー!WeekdayOption)+1
Name Apr: 予算!DaysAndWeeks+DATE(CalendarYear,4,1)-WEEKDAY(DATE(CalendarYear,4,1),予算!WeekdayOption)+1
Name Apr: DaysAndWeeks+DATE(CalendarYear,4,1)-WEEKDAY(DATE(CalendarYear,4,1),WeekdayOption)+1
Name Aug: 横カレンダー!DaysAndWeeks+DATE(CalendarYear,8,1)-WEEKDAY(DATE(CalendarYear,8,1),横カレンダー!WeekdayOption)+1
Name Aug: 予算!DaysAndWeeks+DATE(CalendarYear,8,1)-WEEKDAY(DATE(CalendarYear,8,1),予算!WeekdayOption)+1
Name Aug: DaysAndWeeks+DATE(CalendarYear,8,1)-WEEKDAY(DATE(CalendarYear,8,1),WeekdayOption)+1
Name CalendarYear: #REF!
Name DayHeaders: LEFT(TEXT(#REF!,"aaa"),2)
Name DaysAndWeeks: {0,1,2,3,4,5,6} + {0;1;2;3;4;5}*7
Name DaysAndWeeks: {0,1,2,3,4,5,6} + {0;1;2;3;4;5}*7
Name DaysAndWeeks: {0,1,2,3,4,5,6} + {0;1;2;3;4;5}*7
Name Dec: 横カレンダー!DaysAndWeeks+DATE(CalendarYear,12,1)-WEEKDAY(DATE(CalendarYear,12,1),横カレンダー!WeekdayOption)+1
Name Dec: 予算!DaysAndWeeks+DATE(CalendarYear,12,1)-WEEKDAY(DATE(CalendarYear,12,1),予算!WeekdayOption)+1
Name Dec: DaysAndWeeks+DATE(CalendarYear,12,1)-WEEKDAY(DATE(CalendarYear,12,1),WeekdayOption)+1
Name Feb: 横カレンダー!DaysAndWeeks+DATE(CalendarYear,2,1)-WEEKDAY(DATE(CalendarYear,2,1),横カレンダー!WeekdayOption)+1
Name Feb: 予算!DaysAndWeeks+DATE(CalendarYear,2,1)-WEEKDAY(DATE(CalendarYear,2,1),予算!WeekdayOption)+1
Name Feb: DaysAndWeeks+DATE(CalendarYear,2,1)-WEEKDAY(DATE(CalendarYear,2,1),WeekdayOption)+1
Name Jan: 横カレンダー!DaysAndWeeks+DATE(CalendarYear,1,1)-WEEKDAY(DATE(CalendarYear,1,1),横カレンダー!WeekdayOption)+1
Name Jan: 予算!DaysAndWeeks+DATE(CalendarYear,1,1)-WEEKDAY(DATE(CalendarYear,1,1),予算!WeekdayOption)+1
Name Jan: DaysAndWeeks+DATE(CalendarYear,1,1)-WEEKDAY(DATE(CalendarYear,1,1),WeekdayOption)+1
Name Jul: 横カレンダー!DaysAndWeeks+DATE(CalendarYear,7,1)-WEEKDAY(DATE(CalendarYear,7,1),横カレンダー!WeekdayOption)+1
Name Jul: 予算!DaysAndWeeks+DATE(CalendarYear,7,1)-WEEKDAY(DATE(CalendarYear,7,1),予算!WeekdayOption)+1
Name Jul: DaysAndWeeks+DATE(CalendarYear,7,1)-WEEKDAY(DATE(CalendarYear,7,1),WeekdayOption)+1
Name Jun: 横カレンダー!DaysAndWeeks+DATE(CalendarYear,6,1)-WEEKDAY(DATE(CalendarYear,6,1),横カレンダー!WeekdayOption)+1
Name Jun: 予算!DaysAndWeeks+DATE(CalendarYear,6,1)-WEEKDAY(DATE(CalendarYear,6,1),予算!WeekdayOption)+1
Name Jun: DaysAndWeeks+DATE(CalendarYear,6,1)-WEEKDAY(DATE(CalendarYear,6,1),WeekdayOption)+1
Name Mar: 横カレンダー!DaysAndWeeks+DATE(CalendarYear,3,1)-WEEKDAY(DATE(CalendarYear,3,1),横カレンダー!WeekdayOption)+1
Name Mar: 予算!DaysAndWeeks+DATE(CalendarYear,3,1)-WEEKDAY(DATE(CalendarYear,3,1),予算!WeekdayOption)+1
Name Mar: DaysAndWeeks+DATE(CalendarYear,3,1)-WEEKDAY(DATE(CalendarYear,3,1),WeekdayOption)+1
Name May: 横カレンダー!DaysAndWeeks+DATE(CalendarYear,5,1)-WEEKDAY(DATE(CalendarYear,5,1),横カレンダー!WeekdayOption)+1
Name May: 予算!DaysAndWeeks+DATE(CalendarYear,5,1)-WEEKDAY(DATE(CalendarYear,5,1),予算!WeekdayOption)+1
Name May: DaysAndWeeks+DATE(CalendarYear,5,1)-WEEKDAY(DATE(CalendarYear,5,1),WeekdayOption)+1
Name MonthHeaders: UPPER(TEXT(#REF!,"m月"))
Name Nov: 横カレンダー!DaysAndWeeks+DATE(CalendarYear,11,1)-WEEKDAY(DATE(CalendarYear,11,1),横カレンダー!WeekdayOption)+1
Name Nov: 予算!DaysAndWeeks+DATE(CalendarYear,11,1)-WEEKDAY(DATE(CalendarYear,11,1),予算!WeekdayOption)+1
Name Nov: DaysAndWeeks+DATE(CalendarYear,11,1)-WEEKDAY(DATE(CalendarYear,11,1),WeekdayOption)+1
Name Oct: 横カレンダー!DaysAndWeeks+DATE(CalendarYear,10,1)-WEEKDAY(DATE(CalendarYear,10,1),横カレンダー!WeekdayOption)+1
Name Oct: 予算!DaysAndWeeks+DATE(CalendarYear,10,1)-WEEKDAY(DATE(CalendarYear,10,1),予算!WeekdayOption)+1
Name Oct: DaysAndWeeks+DATE(CalendarYear,10,1)-WEEKDAY(DATE(CalendarYear,10,1),WeekdayOption)+1
Name Sep: 横カレンダー!DaysAndWeeks+DATE(CalendarYear,9,1)-WEEKDAY(DATE(CalendarYear,9,1),横カレンダー!WeekdayOption)+1
Name Sep: 予算!DaysAndWeeks+DATE(CalendarYear,9,1)-WEEKDAY(DATE(CalendarYear,9,1),予算!WeekdayOption)+1
Name Sep: DaysAndWeeks+DATE(CalendarYear,9,1)-WEEKDAY(DATE(CalendarYear,9,1),WeekdayOption)+1
Name WeekdayOption: MATCH(WeekStart,横カレンダー!曜日,0)+10
Name WeekdayOption: MATCH(WeekStart,予算!曜日,0)+10
Name WeekdayOption: MATCH(WeekStart,曜日,0)+10
Name WeekStart: #REF!
Name 修正ランク: #REF!,#REF!,#REF!,#REF!,#REF!,#REF!,#REF!,#REF!,#REF!,#REF!,#REF!,#REF!
Name 修正ランク: #REF!,#REF!,#REF!,#REF!,#REF!,#REF!,#REF!,#REF!,#REF!,#REF!,#REF!,#REF!
Name 修正案: #REF!,#REF!,#REF!,#REF!,#REF!,#REF!
Name 曜日: {"月曜日","火曜日","水曜日","木曜日","金曜日","土曜日","日曜日"}
Name 曜日: {"月曜日","火曜日","水曜日","木曜日","金曜日","土曜日","日曜日"}
Name 曜日: {"月曜日","火曜日","水曜日","木曜日","金曜日","土曜日","日曜日"}

Sheet 横カレンダー
C1: =C3-TODAY() -> -17 | D1: =D3-TODAY() -> -16 | E1: =E3-TODAY() -> -15 | F1: =F3-TODAY() -> -14 | G1: =G3-TODAY() -> -13 | H1: =H3-TODAY() -> -12 | I1: =I3-TODAY() -> -11 | J1: =J3-TODAY() -> -10 | ... KT1: =KT3-TODAY() -> 286
C2: =TEXT(C$3,"yyyy年m月") -> 2025年11月 | D2: =TEXT(D$3,"yyyy年m月") -> 2025年11月 | E2: =TEXT(E$3,"yyyy年m月") -> 2025年11月 | F2: =TEXT(F$3,"yyyy年m月") -> 2025年11月 | G2: =TEXT(G$3,"yyyy年m月") -> 2025年11月 | H2: =TEXT(H$3,"yyyy年m月") -> 2025年11月 | I2: =TEXT(I$3,"yyyy年m月") -> 2025年11月 | J2: =TEXT(J$3,"yyyy年m月") -> 2025年11月 | ... KT2: =TEXT(KT$3,"yyyy年m月") -> 2026年8月
B3: 45962 | C3: =B3 -> 45962 | D3: =C3+1 -> 45963 | E3: =D3+1 -> 45964 | F3: =E3+1 -> 45965 | G3: =F3+1 -> 45966 | H3: =G3+1 -> 45967 | I3: =H3+1 -> 45968 | J3: =I3+1 -> 45969 | K3: =J3+1 -> 45970 | ... KT3: =KS3+1 -> 46265
A4: 1 | B4: =カレンダー!B$16 -> ラグジュアリープールヴィラ(単泊) | H4: =IFERROR(IF(AND(H29="",H16=""),"",IF(H29="",H16,H29)),"") -> H | I4: =IFERROR(IF(AND(I29="",I16=""),"",IF(I29="",I16,I29)),"") -> G | J4: =IFERROR(IF(AND(J29="",J16=""),"",IF(J29="",J16,J29)),"") -> P | K4: =IFERROR(IF(AND(K29="",K16=""),"",IF(K29="",K16,K29)),"") -> I | L4: =IFERROR(IF(AND(L29="",L16=""),"",IF(L29="",L16,L29)),"") -> K | M4: =IFERROR(IF(AND(M29="",M16=""),"",IF(M29="",M16,M29)),"") -> H | N4: =IFERROR(IF(AND(N29="",N16=""),"",IF(N29="",N16,N29)),"") -> E | O4: =IFERROR(IF(AND(O29="",O16=""),"",IF(O29="",O16,O29)),"") -> H | ... KT4: =IFERROR(IF(AND(KT29="",KT16=""),"",IF(KT29="",KT16,KT29)),"")
A5: =A4+1 -> 2 | B5: =カレンダー!B$17 -> ラグジュアリープールヴィラ(連泊) | H5: =IFERROR(IF(AND(H30="",H17=""),"",IF(H30="",H17,H30)),"") -> H | I5: =IFERROR(IF(AND(I30="",I17=""),"",IF(I30="",I17,I30)),"") -> G | J5: =IFERROR(IF(AND(J30="",J17=""),"",IF(J30="",J17,J30)),"") -> P | K5: =IFERROR(IF(AND(K30="",K17=""),"",IF(K30="",K17,K30)),"") -> I | L5: =IFERROR(IF(AND(L30="",L17=""),"",IF(L30="",L17,L30)),"") -> K | M5: =IFERROR(IF(AND(M30="",M17=""),"",IF(M30="",M17,M30)),"") -> H | N5: =IFERROR(IF(AND(N30="",N17=""),"",IF(N30="",N17,N30)),"") -> E | O5: =IFERROR(IF(AND(O30="",O17=""),"",IF(O30="",O17,O30)),"") -> H | ... KT5: =IFERROR(IF(AND(KT30="",KT17=""),"",IF(KT30="",KT17,KT30)),"")
A6: =A5+1 -> 3 | B6: =カレンダー!B$18 -> with SAUNA(単泊) | C6: =IFERROR(IF(AND(C31="",C18=""),"",IF(C31="",C18,C31)),"") -> Q | D6: =IFERROR(IF(AND(D31="",D18=""),"",IF(D31="",D18,D31)),"") -> Q | E6: =IFERROR(IF(AND(E31="",E18=""),"",IF(E31="",E18,E31)),"") -> G | F6: =IFERROR(IF(AND(F31="",F18=""),"",IF(F31="",F18,F31)),"") -> G | G6: =IFERROR(IF(AND(G31="",G18=""),"",IF(G31="",G18,G31)),"") -> G | H6: =IFERROR(IF(AND(H31="",H18=""),"",IF(H31="",H18,H31)),"") -> H | I6: =IFERROR(IF(AND(I31="",I18=""),"",IF(I31="",I18,I31)),"") -> G | J6: =IFERROR(IF(AND(J31="",J18=""),"",IF(J31="",J18,J31)),"") -> P | ... KT6: =IFERROR(IF(AND(KT31="",KT18=""),"",IF(KT31="",KT18,KT31)),"")
A7: =A6+1 -> 4 | B7: =カレンダー!B$19 -> with SAUNA(連泊) | C7: =IFERROR(IF(AND(C32="",C19=""),"",IF(C32="",C19,C32)),"") -> Q | D7: =IFERROR(IF(AND(D32="",D19=""),"",IF(D32="",D19,D32)),"") -> Q | E7: =IFERROR(IF(AND(E32="",E19=""),"",IF(E32="",E19,E32)),"") -> G | F7: =IFERROR(IF(AND(F32="",F19=""),"",IF(F32="",F19,F32)),"") -> G | G7: =IFERROR(IF(AND(G32="",G19=""),"",IF(G32="",G19,G32)),"") -> G | H7: =IFERROR(IF(AND(H32="",H19=""),"",IF(H32="",H19,H32)),"") -> H | I7: =IFERROR(IF(AND(I32="",I19=""),"",IF(I32="",I19,I32)),"") -> G | J7: =IFERROR(IF(AND(J32="",J19=""),"",IF(J32="",J19,J32)),"") -> P | ... KT7: =IFERROR(IF(AND(KT32="",KT19=""),"",IF(KT32="",KT19,KT32)),"")
A8: =A7+1 -> 5 | B8: =カレンダー!B$20 -> 0 | C8: =IFERROR(IF(AND(C33="",C20=""),"",IF(C33="",C20,C33)),"") | D8: =IFERROR(IF(AND(D33="",D20=""),"",IF(D33="",D20,D33)),"") | E8: =IFERROR(IF(AND(E33="",E20=""),"",IF(E33="",E20,E33)),"") | F8: =IFERROR(IF(AND(F33="",F20=""),"",IF(F33="",F20,F33)),"") | G8: =IFERROR(IF(AND(G33="",G20=""),"",IF(G33="",G20,G33)),"") | H8: =IFERROR(IF(AND(H33="",H20=""),"",IF(H33="",H20,H33)),"") | I8: =IFERROR(IF(AND(I33="",I20=""),"",IF(I33="",I20,I33)),"") | J8: =IFERROR(IF(AND(J33="",J20=""),"",IF(J33="",J20,J33)),"") | ... KT8: =IFERROR(IF(AND(KT33="",KT20=""),"",IF(KT33="",KT20,KT33)),"")
A9: =A8+1 -> 6 | B9: =カレンダー!B$21 -> 0 | C9: =IFERROR(IF(AND(C34="",C21=""),"",IF(C34="",C21,C34)),"") | D9: =IFERROR(IF(AND(D34="",D21=""),"",IF(D34="",D21,D34)),"") | E9: =IFERROR(IF(AND(E34="",E21=""),"",IF(E34="",E21,E34)),"") | F9: =IFERROR(IF(AND(F34="",F21=""),"",IF(F34="",F21,F34)),"") | G9: =IFERROR(IF(AND(G34="",G21=""),"",IF(G34="",G21,G34)),"") | H9: =IFERROR(IF(AND(H34="",H21=""),"",IF(H34="",H21,H34)),"") | I9: =IFERROR(IF(AND(I34="",I21=""),"",IF(I34="",I21,I34)),"") | J9: =IFERROR(IF(AND(J34="",J21=""),"",IF(J34="",J21,J34)),"") | ... KT9: =IFERROR(IF(AND(KT34="",KT21=""),"",IF(KT34="",KT21,KT34)),"")
A10: =A9+1 -> 7 | B10: =カレンダー!B$22 -> 0 | C10: =IFERROR(IF(AND(C35="",C22=""),"",IF(C35="",C22,C35)),"") | D10: =IFERROR(IF(AND(D35="",D22=""),"",IF(D35="",D22,D35)),"") | E10: =IFERROR(IF(AND(E35="",E22=""),"",IF(E35="",E22,E35)),"") | F10: =IFERROR(IF(AND(F35="",F22=""),"",IF(F35="",F22,F35)),"") | G10: =IFERROR(IF(AND(G35="",G22=""),"",IF(G35="",G22,G35)),"") | H10: =IFERROR(IF(AND(H35="",H22=""),"",IF(H35="",H22,H35)),"") | I10: =IFERROR(IF(AND(I35="",I22=""),"",IF(I35="",I22,I35)),"") | J10: =IFERROR(IF(AND(J35="",J22=""),"",IF(J35="",J22,J35)),"") | ... KT10: =IFERROR(IF(AND(KT35="",KT22=""),"",IF(KT35="",KT22,KT35)),"")
A11: =A10+1 -> 8 | B11: =カレンダー!B$23 -> 0 | C11: =IFERROR(IF(AND(C36="",C23=""),"",IF(C36="",C23,C36)),"") | D11: =IFERROR(IF(AND(D36="",D23=""),"",IF(D36="",D23,D36)),"") | E11: =IFERROR(IF(AND(E36="",E23=""),"",IF(E36="",E23,E36)),"") | F11: =IFERROR(IF(AND(F36="",F23=""),"",IF(F36="",F23,F36)),"") | G11: =IFERROR(IF(AND(G36="",G23=""),"",IF(G36="",G23,G36)),"") | H11: =IFERROR(IF(AND(H36="",H23=""),"",IF(H36="",H23,H36)),"") | I11: =IFERROR(IF(AND(I36="",I23=""),"",IF(I36="",I23,I36)),"") | J11: =IFERROR(IF(AND(J36="",J23=""),"",IF(J36="",J23,J36)),"") | ... KT11: =IFERROR(IF(AND(KT36="",KT23=""),"",IF(KT36="",KT23,KT36)),"")
A12: =A11+1 -> 9 | B12: =カレンダー!B$24 -> 0 | C12: =IFERROR(IF(AND(C37="",C24=""),"",IF(C37="",C24,C37)),"") | D12: =IFERROR(IF(AND(D37="",D24=""),"",IF(D37="",D24,D37)),"") | E12: =IFERROR(IF(AND(E37="",E24=""),"",IF(E37="",E24,E37)),"") | F12: =IFERROR(IF(AND(F37="",F24=""),"",IF(F37="",F24,F37)),"") | G12: =IFERROR(IF(AND(G37="",G24=""),"",IF(G37="",G24,G37)),"") | H12: =IFERROR(IF(AND(H37="",H24=""),"",IF(H37="",H24,H37)),"") | I12: =IFERROR(IF(AND(I37="",I24=""),"",IF(I37="",I24,I37)),"") | J12: =IFERROR(IF(AND(J37="",J24=""),"",IF(J37="",J24,J37)),"") | ... KT12: =IFERROR(IF(AND(KT37="",KT24=""),"",IF(KT37="",KT24,KT37)),"")
A13: =A12+1 -> 10 | B13: =カレンダー!B$25 -> 0 | C13: =IFERROR(IF(AND(C38="",C25=""),"",IF(C38="",C25,C38)),"") | D13: =IFERROR(IF(AND(D38="",D25=""),"",IF(D38="",D25,D38)),"") | E13: =IFERROR(IF(AND(E38="",E25=""),"",IF(E38="",E25,E38)),"") | F13: =IFERROR(IF(AND(F38="",F25=""),"",IF(F38="",F25,F38)),"") | G13: =IFERROR(IF(AND(G38="",G25=""),"",IF(G38="",G25,G38)),"") | H13: =IFERROR(IF(AND(H38="",H25=""),"",IF(H38="",H25,H38)),"") | I13: =IFERROR(IF(AND(I38="",I25=""),"",IF(I38="",I25,I38)),"") | J13: =IFERROR(IF(AND(J38="",J25=""),"",IF(J38="",J25,J38)),"") | ... KT13: =IFERROR(IF(AND(KT38="",KT25=""),"",IF(KT38="",KT25,KT38)),"")
A16: 1 | B16: =カレンダー!B$16 -> ラグジュアリープールヴィラ(単泊) | C16: =IFERROR(VLOOKUP($B16,INDIRECT(C$2&"!$C$39:$AH$63"),DAY(C$3)+1,FALSE),"") -> Q | D16: =IFERROR(VLOOKUP($B16,INDIRECT(D$2&"!$C$39:$AH$63"),DAY(D$3)+1,FALSE),"") -> Q | E16: =IFERROR(VLOOKUP($B16,INDIRECT(E$2&"!$C$39:$AH$63"),DAY(E$3)+1,FALSE),"") -> G | F16: =IFERROR(VLOOKUP($B16,INDIRECT(F$2&"!$C$39:$AH$63"),DAY(F$3)+1,FALSE),"") -> G | G16: =IFERROR(VLOOKUP($B16,INDIRECT(G$2&"!$C$39:$AH$63"),DAY(G$3)+1,FALSE),"") -> G | H16: =IFERROR(VLOOKUP($B16,INDIRECT(H$2&"!$C$39:$AH$63"),DAY(H$3)+1,FALSE),"") -> H | I16: =IFERROR(VLOOKUP($B16,INDIRECT(I$2&"!$C$39:$AH$63"),DAY(I$3)+1,FALSE),"") -> G | J16: =IFERROR(VLOOKUP($B16,INDIRECT(J$2&"!$C$39:$AH$63"),DAY(J$3)+1,FALSE),"") -> P | ... KT16: =IFERROR(VLOOKUP($B16,INDIRECT(KT$2&"!$C$39:$AH$63"),DAY(KT$3)+1,FALSE),"")
A17: =A16+1 -> 2 | B17: =カレンダー!B$17 -> ラグジュアリープールヴィラ(連泊) | C17: =IFERROR(VLOOKUP($B17,INDIRECT(C$2&"!$C$39:$AH$63"),DAY(C$3)+1,FALSE),"") -> Q | D17: =IFERROR(VLOOKUP($B17,INDIRECT(D$2&"!$C$39:$AH$63"),DAY(D$3)+1,FALSE),"") -> Q | E17: =IFERROR(VLOOKUP($B17,INDIRECT(E$2&"!$C$39:$AH$63"),DAY(E$3)+1,FALSE),"") -> G | F17: =IFERROR(VLOOKUP($B17,INDIRECT(F$2&"!$C$39:$AH$63"),DAY(F$3)+1,FALSE),"") -> G | G17: =IFERROR(VLOOKUP($B17,INDIRECT(G$2&"!$C$39:$AH$63"),DAY(G$3)+1,FALSE),"") -> G | H17: =IFERROR(VLOOKUP($B17,INDIRECT(H$2&"!$C$39:$AH$63"),DAY(H$3)+1,FALSE),"") -> H | I17: =IFERROR(VLOOKUP($B17,INDIRECT(I$2&"!$C$39:$AH$63"),DAY(I$3)+1,FALSE),"") -> G | J17: =IFERROR(VLOOKUP($B17,INDIRECT(J$2&"!$C$39:$AH$63"),DAY(J$3)+1,FALSE),"") -> P | ... KT17: =IFERROR(VLOOKUP($B17,INDIRECT(KT$2&"!$C$39:$AH$63"),DAY(KT$3)+1,FALSE),"")
A18: =A17+1 -> 3 | B18: =カレンダー!B$18 -> with SAUNA(単泊) | C18: =IFERROR(VLOOKUP($B18,INDIRECT(C$2&"!$C$39:$AH$63"),DAY(C$3)+1,FALSE),"") -> Q | D18: =IFERROR(VLOOKUP($B18,INDIRECT(D$2&"!$C$39:$AH$63"),DAY(D$3)+1,FALSE),"") -> Q | E18: =IFERROR(VLOOKUP($B18,INDIRECT(E$2&"!$C$39:$AH$63"),DAY(E$3)+1,FALSE),"") -> G | F18: =IFERROR(VLOOKUP($B18,INDIRECT(F$2&"!$C$39:$AH$63"),DAY(F$3)+1,FALSE),"") -> G | G18: =IFERROR(VLOOKUP($B18,INDIRECT(G$2&"!$C$39:$AH$63"),DAY(G$3)+1,FALSE),"") -> G | H18: =IFERROR(VLOOKUP($B18,INDIRECT(H$2&"!$C$39:$AH$63"),DAY(H$3)+1,FALSE),"") -> H | I18: =IFERROR(VLOOKUP($B18,INDIRECT(I$2&"!$C$39:$AH$63"),DAY(I$3)+1,FALSE),"") -> G | J18: =IFERROR(VLOOKUP($B18,INDIRECT(J$2&"!$C$39:$AH$63"),DAY(J$3)+1,FALSE),"") -> P | ... KT18: =IFERROR(VLOOKUP($B18,INDIRECT(KT$2&"!$C$39:$AH$63"),DAY(KT$3)+1,FALSE),"")
A19: =A18+1 -> 4 | B19: =カレンダー!B$19 -> with SAUNA(連泊) | C19: =IFERROR(VLOOKUP($B19,INDIRECT(C$2&"!$C$39:$AH$63"),DAY(C$3)+1,FALSE),"") -> Q | D19: =IFERROR(VLOOKUP($B19,INDIRECT(D$2&"!$C$39:$AH$63"),DAY(D$3)+1,FALSE),"") -> Q | E19: =IFERROR(VLOOKUP($B19,INDIRECT(E$2&"!$C$39:$AH$63"),DAY(E$3)+1,FALSE),"") -> G | F19: =IFERROR(VLOOKUP($B19,INDIRECT(F$2&"!$C$39:$AH$63"),DAY(F$3)+1,FALSE),"") -> G | G19: =IFERROR(VLOOKUP($B19,INDIRECT(G$2&"!$C$39:$AH$63"),DAY(G$3)+1,FALSE),"") -> G | H19: =IFERROR(VLOOKUP($B19,INDIRECT(H$2&"!$C$39:$AH$63"),DAY(H$3)+1,FALSE),"") -> H | I19: =IFERROR(VLOOKUP($B19,INDIRECT(I$2&"!$C$39:$AH$63"),DAY(I$3)+1,FALSE),"") -> G | J19: =IFERROR(VLOOKUP($B19,INDIRECT(J$2&"!$C$39:$AH$63"),DAY(J$3)+1,FALSE),"") -> P | ... KT19: =IFERROR(VLOOKUP($B19,INDIRECT(KT$2&"!$C$39:$AH$63"),DAY(KT$3)+1,FALSE),"")
A20: =A19+1 -> 5 | B20: =カレンダー!B$20 -> 0 | C20: =IFERROR(VLOOKUP($B20,INDIRECT(C$2&"!$C$39:$AH$63"),DAY(C$3)+1,FALSE),"") | D20: =IFERROR(VLOOKUP($B20,INDIRECT(D$2&"!$C$39:$AH$63"),DAY(D$3)+1,FALSE),"") | E20: =IFERROR(VLOOKUP($B20,INDIRECT(E$2&"!$C$39:$AH$63"),DAY(E$3)+1,FALSE),"") | F20: =IFERROR(VLOOKUP($B20,INDIRECT(F$2&"!$C$39:$AH$63"),DAY(F$3)+1,FALSE),"") | G20: =IFERROR(VLOOKUP($B20,INDIRECT(G$2&"!$C$39:$AH$63"),DAY(G$3)+1,FALSE),"") | H20: =IFERROR(VLOOKUP($B20,INDIRECT(H$2&"!$C$39:$AH$63"),DAY(H$3)+1,FALSE),"") | I20: =IFERROR(VLOOKUP($B20,INDIRECT(I$2&"!$C$39:$AH$63"),DAY(I$3)+1,FALSE),"") | J20: =IFERROR(VLOOKUP($B20,INDIRECT(J$2&"!$C$39:$AH$63"),DAY(J$3)+1,FALSE),"") | ... KT20: =IFERROR(VLOOKUP($B20,INDIRECT(KT$2&"!$C$39:$AH$63"),DAY(KT$3)+1,FALSE),"")
A21: =A20+1 -> 6 | B21: =カレンダー!B$21 -> 0 | C21: =IFERROR(VLOOKUP($B21,INDIRECT(C$2&"!$C$39:$AH$63"),DAY(C$3)+1,FALSE),"") | D21: =IFERROR(VLOOKUP($B21,INDIRECT(D$2&"!$C$39:$AH$63"),DAY(D$3)+1,FALSE),"") | E21: =IFERROR(VLOOKUP($B21,INDIRECT(E$2&"!$C$39:$AH$63"),DAY(E$3)+1,FALSE),"") | F21: =IFERROR(VLOOKUP($B21,INDIRECT(F$2&"!$C$39:$AH$63"),DAY(F$3)+1,FALSE),"") | G21: =IFERROR(VLOOKUP($B21,INDIRECT(G$2&"!$C$39:$AH$63"),DAY(G$3)+1,FALSE),"") | H21: =IFERROR(VLOOKUP($B21,INDIRECT(H$2&"!$C$39:$AH$63"),DAY(H$3)+1,FALSE),"") | I21: =IFERROR(VLOOKUP($B21,INDIRECT(I$2&"!$C$39:$AH$63"),DAY(I$3)+1,FALSE),"") | J21: =IFERROR(VLOOKUP($B21,INDIRECT(J$2&"!$C$39:$AH$63"),DAY(J$3)+1,FALSE),"") | ... KT21: =IFERROR(VLOOKUP($B21,INDIRECT(KT$2&"!$C$39:$AH$63"),DAY(KT$3)+1,FALSE),"")
A22: =A21+1 -> 7 | B22: =カレンダー!B$22 -> 0 | C22: =IFERROR(VLOOKUP($B22,INDIRECT(C$2&"!$C$39:$AH$63"),DAY(C$3)+1,FALSE),"") | D22: =IFERROR(VLOOKUP($B22,INDIRECT(D$2&"!$C$39:$AH$63"),DAY(D$3)+1,FALSE),"") | E22: =IFERROR(VLOOKUP($B22,INDIRECT(E$2&"!$C$39:$AH$63"),DAY(E$3)+1,FALSE),"") | F22: =IFERROR(VLOOKUP($B22,INDIRECT(F$2&"!$C$39:$AH$63"),DAY(F$3)+1,FALSE),"") | G22: =IFERROR(VLOOKUP($B22,INDIRECT(G$2&"!$C$39:$AH$63"),DAY(G$3)+1,FALSE),"") | H22: =IFERROR(VLOOKUP($B22,INDIRECT(H$2&"!$C$39:$AH$63"),DAY(H$3)+1,FALSE),"") | I22: =IFERROR(VLOOKUP($B22,INDIRECT(I$2&"!$C$39:$AH$63"),DAY(I$3)+1,FALSE),"") | J22: =IFERROR(VLOOKUP($B22,INDIRECT(J$2&"!$C$39:$AH$63"),DAY(J$3)+1,FALSE),"") | ... KT22: =IFERROR(VLOOKUP($B22,INDIRECT(KT$2&"!$C$39:$AH$63"),DAY(KT$3)+1,FALSE),"")
A23: =A22+1 -> 8 | B23: =カレンダー!B$23 -> 0 | C23: =IFERROR(VLOOKUP($B23,INDIRECT(C$2&"!$C$39:$AH$63"),DAY(C$3)+1,FALSE),"") | D23: =IFERROR(VLOOKUP($B23,INDIRECT(D$2&"!$C$39:$AH$63"),DAY(D$3)+1,FALSE),"") | E23: =IFERROR(VLOOKUP($B23,INDIRECT(E$2&"!$C$39:$AH$63"),DAY(E$3)+1,FALSE),"") | F23: =IFERROR(VLOOKUP($B23,INDIRECT(F$2&"!$C$39:$AH$63"),DAY(F$3)+1,FALSE),"") | G23: =IFERROR(VLOOKUP($B23,INDIRECT(G$2&"!$C$39:$AH$63"),DAY(G$3)+1,FALSE),"") | H23: =IFERROR(VLOOKUP($B23,INDIRECT(H$2&"!$C$39:$AH$63"),DAY(H$3)+1,FALSE),"") | I23: =IFERROR(VLOOKUP($B23,INDIRECT(I$2&"!$C$39:$AH$63"),DAY(I$3)+1,FALSE),"") | J23: =IFERROR(VLOOKUP($B23,INDIRECT(J$2&"!$C$39:$AH$63"),DAY(J$3)+1,FALSE),"") | ... KT23: =IFERROR(VLOOKUP($B23,INDIRECT(KT$2&"!$C$39:$AH$63"),DAY(KT$3)+1,FALSE),"")
A24: =A23+1 -> 9 | B24: =カレンダー!B$24 -> 0 | C24: =IFERROR(VLOOKUP($B24,INDIRECT(C$2&"!$C$39:$AH$63"),DAY(C$3)+1,FALSE),"") | D24: =IFERROR(VLOOKUP($B24,INDIRECT(D$2&"!$C$39:$AH$63"),DAY(D$3)+1,FALSE),"") | E24: =IFERROR(VLOOKUP($B24,INDIRECT(E$2&"!$C$39:$AH$63"),DAY(E$3)+1,FALSE),"") | F24: =IFERROR(VLOOKUP($B24,INDIRECT(F$2&"!$C$39:$AH$63"),DAY(F$3)+1,FALSE),"") | G24: =IFERROR(VLOOKUP($B24,INDIRECT(G$2&"!$C$39:$AH$63"),DAY(G$3)+1,FALSE),"") | H24: =IFERROR(VLOOKUP($B24,INDIRECT(H$2&"!$C$39:$AH$63"),DAY(H$3)+1,FALSE),"") | I24: =IFERROR(VLOOKUP($B24,INDIRECT(I$2&"!$C$39:$AH$63"),DAY(I$3)+1,FALSE),"") | J24: =IFERROR(VLOOKUP($B24,INDIRECT(J$2&"!$C$39:$AH$63"),DAY(J$3)+1,FALSE),"") | ... KT24: =IFERROR(VLOOKUP($B24,INDIRECT(KT$2&"!$C$39:$AH$63"),DAY(KT$3)+1,FALSE),"")
A25: =A24+1 -> 10 | B25: =カレンダー!B$25 -> 0 | C25: =IFERROR(VLOOKUP($B25,INDIRECT(C$2&"!$C$39:$AH$63"),DAY(C$3)+1,FALSE),"") | D25: =IFERROR(VLOOKUP($B25,INDIRECT(D$2&"!$C$39:$AH$63"),DAY(D$3)+1,FALSE),"") | E25: =IFERROR(VLOOKUP($B25,INDIRECT(E$2&"!$C$39:$AH$63"),DAY(E$3)+1,FALSE),"") | F25: =IFERROR(VLOOKUP($B25,INDIRECT(F$2&"!$C$39:$AH$63"),DAY(F$3)+1,FALSE),"") | G25: =IFERROR(VLOOKUP($B25,INDIRECT(G$2&"!$C$39:$AH$63"),DAY(G$3)+1,FALSE),"") | H25: =IFERROR(VLOOKUP($B25,INDIRECT(H$2&"!$C$39:$AH$63"),DAY(H$3)+1,FALSE),"") | I25: =IFERROR(VLOOKUP($B25,INDIRECT(I$2&"!$C$39:$AH$63"),DAY(I$3)+1,FALSE),"") | J25: =IFERROR(VLOOKUP($B25,INDIRECT(J$2&"!$C$39:$AH$63"),DAY(J$3)+1,FALSE),"") | ... KT25: =IFERROR(VLOOKUP($B25,INDIRECT(KT$2&"!$C$39:$AH$63"),DAY(KT$3)+1,FALSE),"")
A29: 1 | B29: =カレンダー!B$16 -> ラグジュアリープールヴィラ(単泊) | C29: =IFERROR(IF(VLOOKUP($B29,INDIRECT(C$2&"!$C$85:$AH$108"),DAY(C$3)+1,FALSE)="","",VLOOKUP($B29,INDIRECT(C$2&"!$C$85:$AH$108"),DAY(C$3)+1,FALSE)),"") | D29: =IFERROR(IF(VLOOKUP($B29,INDIRECT(D$2&"!$C$85:$AH$108"),DAY(D$3)+1,FALSE)="","",VLOOKUP($B29,INDIRECT(D$2&"!$C$85:$AH$108"),DAY(D$3)+1,FALSE)),"") | E29: =IFERROR(IF(VLOOKUP($B29,INDIRECT(E$2&"!$C$85:$AH$108"),DAY(E$3)+1,FALSE)="","",VLOOKUP($B29,INDIRECT(E$2&"!$C$85:$AH$108"),DAY(E$3)+1,FALSE)),"") | F29: =IFERROR(IF(VLOOKUP($B29,INDIRECT(F$2&"!$C$85:$AH$108"),DAY(F$3)+1,FALSE)="","",VLOOKUP($B29,INDIRECT(F$2&"!$C$85:$AH$108"),DAY(F$3)+1,FALSE)),"") | G29: =IFERROR(IF(VLOOKUP($B29,INDIRECT(G$2&"!$C$85:$AH$108"),DAY(G$3)+1,FALSE)="","",VLOOKUP($B29,INDIRECT(G$2&"!$C$85:$AH$108"),DAY(G$3)+1,FALSE)),"") | H29: =IFERROR(IF(VLOOKUP($B29,INDIRECT(H$2&"!$C$85:$AH$108"),DAY(H$3)+1,FALSE)="","",VLOOKUP($B29,INDIRECT(H$2&"!$C$85:$AH$108"),DAY(H$3)+1,FALSE)),"") | I29: =IFERROR(IF(VLOOKUP($B29,INDIRECT(I$2&"!$C$85:$AH$108"),DAY(I$3)+1,FALSE)="","",VLOOKUP($B29,INDIRECT(I$2&"!$C$85:$AH$108"),DAY(I$3)+1,FALSE)),"") | J29: =IFERROR(IF(VLOOKUP($B29,INDIRECT(J$2&"!$C$85:$AH$108"),DAY(J$3)+1,FALSE)="","",VLOOKUP($B29,INDIRECT(J$2&"!$C$85:$AH$108"),DAY(J$3)+1,FALSE)),"") | ... IV29: =IFERROR(IF(VLOOKUP($B29,INDIRECT(IV$2&"!$C$85:$AH$108"),DAY(IV$3)+1,FALSE)="","",VLOOKUP($B29,INDIRECT(IV$2&"!$C$85:$AH$108"),DAY(IV$3)+1,FALSE)),"")
A30: =A29+1 -> 2 | B30: =カレンダー!B$17 -> ラグジュアリープールヴィラ(連泊) | C30: =IFERROR(IF(VLOOKUP($B30,INDIRECT(C$2&"!$C$85:$AH$108"),DAY(C$3)+1,FALSE)="","",VLOOKUP($B30,INDIRECT(C$2&"!$C$85:$AH$108"),DAY(C$3)+1,FALSE)),"") | D30: =IFERROR(IF(VLOOKUP($B30,INDIRECT(D$2&"!$C$85:$AH$108"),DAY(D$3)+1,FALSE)="","",VLOOKUP($B30,INDIRECT(D$2&"!$C$85:$AH$108"),DAY(D$3)+1,FALSE)),"") | E30: =IFERROR(IF(VLOOKUP($B30,INDIRECT(E$2&"!$C$85:$AH$108"),DAY(E$3)+1,FALSE)="","",VLOOKUP($B30,INDIRECT(E$2&"!$C$85:$AH$108"),DAY(E$3)+1,FALSE)),"") | F30: =IFERROR(IF(VLOOKUP($B30,INDIRECT(F$2&"!$C$85:$AH$108"),DAY(F$3)+1,FALSE)="","",VLOOKUP($B30,INDIRECT(F$2&"!$C$85:$AH$108"),DAY(F$3)+1,FALSE)),"") | G30: =IFERROR(IF(VLOOKUP($B30,INDIRECT(G$2&"!$C$85:$AH$108"),DAY(G$3)+1,FALSE)="","",VLOOKUP($B30,INDIRECT(G$2&"!$C$85:$AH$108"),DAY(G$3)+1,FALSE)),"") | H30: =IFERROR(IF(VLOOKUP($B30,INDIRECT(H$2&"!$C$85:$AH$108"),DAY(H$3)+1,FALSE)="","",VLOOKUP($B30,INDIRECT(H$2&"!$C$85:$AH$108"),DAY(H$3)+1,FALSE)),"") | I30: =IFERROR(IF(VLOOKUP($B30,INDIRECT(I$2&"!$C$85:$AH$108"),DAY(I$3)+1,FALSE)="","",VLOOKUP($B30,INDIRECT(I$2&"!$C$85:$AH$108"),DAY(I$3)+1,FALSE)),"") | J30: =IFERROR(IF(VLOOKUP($B30,INDIRECT(J$2&"!$C$85:$AH$108"),DAY(J$3)+1,FALSE)="","",VLOOKUP($B30,INDIRECT(J$2&"!$C$85:$AH$108"),DAY(J$3)+1,FALSE)),"") | ... IV30: =IFERROR(IF(VLOOKUP($B30,INDIRECT(IV$2&"!$C$85:$AH$108"),DAY(IV$3)+1,FALSE)="","",VLOOKUP($B30,INDIRECT(IV$2&"!$C$85:$AH$108"),DAY(IV$3)+1,FALSE)),"")
A31: =A30+1 -> 3 | B31: =カレンダー!B$18 -> with SAUNA(単泊) | C31: =IFERROR(IF(VLOOKUP($B31,INDIRECT(C$2&"!$C$85:$AH$108"),DAY(C$3)+1,FALSE)="","",VLOOKUP($B31,INDIRECT(C$2&"!$C$85:$AH$108"),DAY(C$3)+1,FALSE)),"") | D31: =IFERROR(IF(VLOOKUP($B31,INDIRECT(D$2&"!$C$85:$AH$108"),DAY(D$3)+1,FALSE)="","",VLOOKUP($B31,INDIRECT(D$2&"!$C$85:$AH$108"),DAY(D$3)+1,FALSE)),"") | E31: =IFERROR(IF(VLOOKUP($B31,INDIRECT(E$2&"!$C$85:$AH$108"),DAY(E$3)+1,FALSE)="","",VLOOKUP($B31,INDIRECT(E$2&"!$C$85:$AH$108"),DAY(E$3)+1,FALSE)),"") | F31: =IFERROR(IF(VLOOKUP($B31,INDIRECT(F$2&"!$C$85:$AH$108"),DAY(F$3)+1,FALSE)="","",VLOOKUP($B31,INDIRECT(F$2&"!$C$85:$AH$108"),DAY(F$3)+1,FALSE)),"") | G31: =IFERROR(IF(VLOOKUP($B31,INDIRECT(G$2&"!$C$85:$AH$108"),DAY(G$3)+1,FALSE)="","",VLOOKUP($B31,INDIRECT(G$2&"!$C$85:$AH$108"),DAY(G$3)+1,FALSE)),"") | H31: =IFERROR(IF(VLOOKUP($B31,INDIRECT(H$2&"!$C$85:$AH$108"),DAY(H$3)+1,FALSE)="","",VLOOKUP($B31,INDIRECT(H$2&"!$C$85:$AH$108"),DAY(H$3)+1,FALSE)),"") | I31: =IFERROR(IF(VLOOKUP($B31,INDIRECT(I$2&"!$C$85:$AH$108"),DAY(I$3)+1,FALSE)="","",VLOOKUP($B31,INDIRECT(I$2&"!$C$85:$AH$108"),DAY(I$3)+1,FALSE)),"") | J31: =IFERROR(IF(VLOOKUP($B31,INDIRECT(J$2&"!$C$85:$AH$108"),DAY(J$3)+1,FALSE)="","",VLOOKUP($B31,INDIRECT(J$2&"!$C$85:$AH$108"),DAY(J$3)+1,FALSE)),"") | ... IV31: =IFERROR(IF(VLOOKUP($B31,INDIRECT(IV$2&"!$C$85:$AH$108"),DAY(IV$3)+1,FALSE)="","",VLOOKUP($B31,INDIRECT(IV$2&"!$C$85:$AH$108"),DAY(IV$3)+1,FALSE)),"")
A32: =A31+1 -> 4 | B32: =カレンダー!B$19 -> with SAUNA(連泊) | C32: =IFERROR(IF(VLOOKUP($B32,INDIRECT(C$2&"!$C$85:$AH$108"),DAY(C$3)+1,FALSE)="","",VLOOKUP($B32,INDIRECT(C$2&"!$C$85:$AH$108"),DAY(C$3)+1,FALSE)),"") | D32: =IFERROR(IF(VLOOKUP($B32,INDIRECT(D$2&"!$C$85:$AH$108"),DAY(D$3)+1,FALSE)="","",VLOOKUP($B32,INDIRECT(D$2&"!$C$85:$AH$108"),DAY(D$3)+1,FALSE)),"") | E32: =IFERROR(IF(VLOOKUP($B32,INDIRECT(E$2&"!$C$85:$AH$108"),DAY(E$3)+1,FALSE)="","",VLOOKUP($B32,INDIRECT(E$2&"!$C$85:$AH$108"),DAY(E$3)+1,FALSE)),"") | F32: =IFERROR(IF(VLOOKUP($B32,INDIRECT(F$2&"!$C$85:$AH$108"),DAY(F$3)+1,FALSE)="","",VLOOKUP($B32,INDIRECT(F$2&"!$C$85:$AH$108"),DAY(F$3)+1,FALSE)),"") | G32: =IFERROR(IF(VLOOKUP($B32,INDIRECT(G$2&"!$C$85:$AH$108"),DAY(G$3)+1,FALSE)="","",VLOOKUP($B32,INDIRECT(G$2&"!$C$85:$AH$108"),DAY(G$3)+1,FALSE)),"") | H32: =IFERROR(IF(VLOOKUP($B32,INDIRECT(H$2&"!$C$85:$AH$108"),DAY(H$3)+1,FALSE)="","",VLOOKUP($B32,INDIRECT(H$2&"!$C$85:$AH$108"),DAY(H$3)+1,FALSE)),"") | I32: =IFERROR(IF(VLOOKUP($B32,INDIRECT(I$2&"!$C$85:$AH$108"),DAY(I$3)+1,FALSE)="","",VLOOKUP($B32,INDIRECT(I$2&"!$C$85:$AH$108"),DAY(I$3)+1,FALSE)),"") | J32: =IFERROR(IF(VLOOKUP($B32,INDIRECT(J$2&"!$C$85:$AH$108"),DAY(J$3)+1,FALSE)="","",VLOOKUP($B32,INDIRECT(J$2&"!$C$85:$AH$108"),DAY(J$3)+1,FALSE)),"") | ... IV32: =IFERROR(IF(VLOOKUP($B32,INDIRECT(IV$2&"!$C$85:$AH$108"),DAY(IV$3)+1,FALSE)="","",VLOOKUP($B32,INDIRECT(IV$2&"!$C$85:$AH$108"),DAY(IV$3)+1,FALSE)),"")
A33: =A32+1 -> 5 | B33: =カレンダー!B$20 -> 0 | C33: =IFERROR(IF(VLOOKUP($B33,INDIRECT(C$2&"!$C$85:$AH$108"),DAY(C$3)+1,FALSE)="","",VLOOKUP($B33,INDIRECT(C$2&"!$C$85:$AH$108"),DAY(C$3)+1,FALSE)),"") | D33: =IFERROR(IF(VLOOKUP($B33,INDIRECT(D$2&"!$C$85:$AH$108"),DAY(D$3)+1,FALSE)="","",VLOOKUP($B33,INDIRECT(D$2&"!$C$85:$AH$108"),DAY(D$3)+1,FALSE)),"") | E33: =IFERROR(IF(VLOOKUP($B33,INDIRECT(E$2&"!$C$85:$AH$108"),DAY(E$3)+1,FALSE)="","",VLOOKUP($B33,INDIRECT(E$2&"!$C$85:$AH$108"),DAY(E$3)+1,FALSE)),"") | F33: =IFERROR(IF(VLOOKUP($B33,INDIRECT(F$2&"!$C$85:$AH$108"),DAY(F$3)+1,FALSE)="","",VLOOKUP($B33,INDIRECT(F$2&"!$C$85:$AH$108"),DAY(F$3)+1,FALSE)),"") | G33: =IFERROR(IF(VLOOKUP($B33,INDIRECT(G$2&"!$C$85:$AH$108"),DAY(G$3)+1,FALSE)="","",VLOOKUP($B33,INDIRECT(G$2&"!$C$85:$AH$108"),DAY(G$3)+1,FALSE)),"") | H33: =IFERROR(IF(VLOOKUP($B33,INDIRECT(H$2&"!$C$85:$AH$108"),DAY(H$3)+1,FALSE)="","",VLOOKUP($B33,INDIRECT(H$2&"!$C$85:$AH$108"),DAY(H$3)+1,FALSE)),"") | I33: =IFERROR(IF(VLOOKUP($B33,INDIRECT(I$2&"!$C$85:$AH$108"),DAY(I$3)+1,FALSE)="","",VLOOKUP($B33,INDIRECT(I$2&"!$C$85:$AH$108"),DAY(I$3)+1,FALSE)),"") | J33: =IFERROR(IF(VLOOKUP($B33,INDIRECT(J$2&"!$C$85:$AH$108"),DAY(J$3)+1,FALSE)="","",VLOOKUP($B33,INDIRECT(J$2&"!$C$85:$AH$108"),DAY(J$3)+1,FALSE)),"") | ... IV33: =IFERROR(IF(VLOOKUP($B33,INDIRECT(IV$2&"!$C$85:$AH$108"),DAY(IV$3)+1,FALSE)="","",VLOOKUP($B33,INDIRECT(IV$2&"!$C$85:$AH$108"),DAY(IV$3)+1,FALSE)),"")
A34: =A33+1 -> 6 | B34: =カレンダー!B$21 -> 0 | C34: =IFERROR(IF(VLOOKUP($B34,INDIRECT(C$2&"!$C$85:$AH$108"),DAY(C$3)+1,FALSE)="","",VLOOKUP($B34,INDIRECT(C$2&"!$C$85:$AH$108"),DAY(C$3)+1,FALSE)),"") | D34: =IFERROR(IF(VLOOKUP($B34,INDIRECT(D$2&"!$C$85:$AH$108"),DAY(D$3)+1,FALSE)="","",VLOOKUP($B34,INDIRECT(D$2&"!$C$85:$AH$108"),DAY(D$3)+1,FALSE)),"") | E34: =IFERROR(IF(VLOOKUP($B34,INDIRECT(E$2&"!$C$85:$AH$108"),DAY(E$3)+1,FALSE)="","",VLOOKUP($B34,INDIRECT(E$2&"!$C$85:$AH$108"),DAY(E$3)+1,FALSE)),"") | F34: =IFERROR(IF(VLOOKUP($B34,INDIRECT(F$2&"!$C$85:$AH$108"),DAY(F$3)+1,FALSE)="","",VLOOKUP($B34,INDIRECT(F$2&"!$C$85:$AH$108"),DAY(F$3)+1,FALSE)),"") | G34: =IFERROR(IF(VLOOKUP($B34,INDIRECT(G$2&"!$C$85:$AH$108"),DAY(G$3)+1,FALSE)="","",VLOOKUP($B34,INDIRECT(G$2&"!$C$85:$AH$108"),DAY(G$3)+1,FALSE)),"") | H34: =IFERROR(IF(VLOOKUP($B34,INDIRECT(H$2&"!$C$85:$AH$108"),DAY(H$3)+1,FALSE)="","",VLOOKUP($B34,INDIRECT(H$2&"!$C$85:$AH$108"),DAY(H$3)+1,FALSE)),"") | I34: =IFERROR(IF(VLOOKUP($B34,INDIRECT(I$2&"!$C$85:$AH$108"),DAY(I$3)+1,FALSE)="","",VLOOKUP($B34,INDIRECT(I$2&"!$C$85:$AH$108"),DAY(I$3)+1,FALSE)),"") | J34: =IFERROR(IF(VLOOKUP($B34,INDIRECT(J$2&"!$C$85:$AH$108"),DAY(J$3)+1,FALSE)="","",VLOOKUP($B34,INDIRECT(J$2&"!$C$85:$AH$108"),DAY(J$3)+1,FALSE)),"") | ... IV34: =IFERROR(IF(VLOOKUP($B34,INDIRECT(IV$2&"!$C$85:$AH$108"),DAY(IV$3)+1,FALSE)="","",VLOOKUP($B34,INDIRECT(IV$2&"!$C$85:$AH$108"),DAY(IV$3)+1,FALSE)),"")
A35: =A34+1 -> 7 | B35: =カレンダー!B$22 -> 0 | C35: =IFERROR(IF(VLOOKUP($B35,INDIRECT(C$2&"!$C$85:$AH$108"),DAY(C$3)+1,FALSE)="","",VLOOKUP($B35,INDIRECT(C$2&"!$C$85:$AH$108"),DAY(C$3)+1,FALSE)),"") | D35: =IFERROR(IF(VLOOKUP($B35,INDIRECT(D$2&"!$C$85:$AH$108"),DAY(D$3)+1,FALSE)="","",VLOOKUP($B35,INDIRECT(D$2&"!$C$85:$AH$108"),DAY(D$3)+1,FALSE)),"") | E35: =IFERROR(IF(VLOOKUP($B35,INDIRECT(E$2&"!$C$85:$AH$108"),DAY(E$3)+1,FALSE)="","",VLOOKUP($B35,INDIRECT(E$2&"!$C$85:$AH$108"),DAY(E$3)+1,FALSE)),"") | F35: =IFERROR(IF(VLOOKUP($B35,INDIRECT(F$2&"!$C$85:$AH$108"),DAY(F$3)+1,FALSE)="","",VLOOKUP($B35,INDIRECT(F$2&"!$C$85:$AH$108"),DAY(F$3)+1,FALSE)),"") | G35: =IFERROR(IF(VLOOKUP($B35,INDIRECT(G$2&"!$C$85:$AH$108"),DAY(G$3)+1,FALSE)="","",VLOOKUP($B35,INDIRECT(G$2&"!$C$85:$AH$108"),DAY(G$3)+1,FALSE)),"") | H35: =IFERROR(IF(VLOOKUP($B35,INDIRECT(H$2&"!$C$85:$AH$108"),DAY(H$3)+1,FALSE)="","",VLOOKUP($B35,INDIRECT(H$2&"!$C$85:$AH$108"),DAY(H$3)+1,FALSE)),"") | I35: =IFERROR(IF(VLOOKUP($B35,INDIRECT(I$2&"!$C$85:$AH$108"),DAY(I$3)+1,FALSE)="","",VLOOKUP($B35,INDIRECT(I$2&"!$C$85:$AH$108"),DAY(I$3)+1,FALSE)),"") | J35: =IFERROR(IF(VLOOKUP($B35,INDIRECT(J$2&"!$C$85:$AH$108"),DAY(J$3)+1,FALSE)="","",VLOOKUP($B35,INDIRECT(J$2&"!$C$85:$AH$108"),DAY(J$3)+1,FALSE)),"") | ... IV35: =IFERROR(IF(VLOOKUP($B35,INDIRECT(IV$2&"!$C$85:$AH$108"),DAY(IV$3)+1,FALSE)="","",VLOOKUP($B35,INDIRECT(IV$2&"!$C$85:$AH$108"),DAY(IV$3)+1,FALSE)),"")
A36: =A35+1 -> 8 | B36: =カレンダー!B$23 -> 0 | C36: =IFERROR(IF(VLOOKUP($B36,INDIRECT(C$2&"!$C$85:$AH$108"),DAY(C$3)+1,FALSE)="","",VLOOKUP($B36,INDIRECT(C$2&"!$C$85:$AH$108"),DAY(C$3)+1,FALSE)),"") | D36: =IFERROR(IF(VLOOKUP($B36,INDIRECT(D$2&"!$C$85:$AH$108"),DAY(D$3)+1,FALSE)="","",VLOOKUP($B36,INDIRECT(D$2&"!$C$85:$AH$108"),DAY(D$3)+1,FALSE)),"") | E36: =IFERROR(IF(VLOOKUP($B36,INDIRECT(E$2&"!$C$85:$AH$108"),DAY(E$3)+1,FALSE)="","",VLOOKUP($B36,INDIRECT(E$2&"!$C$85:$AH$108"),DAY(E$3)+1,FALSE)),"") | F36: =IFERROR(IF(VLOOKUP($B36,INDIRECT(F$2&"!$C$85:$AH$108"),DAY(F$3)+1,FALSE)="","",VLOOKUP($B36,INDIRECT(F$2&"!$C$85:$AH$108"),DAY(F$3)+1,FALSE)),"") | G36: =IFERROR(IF(VLOOKUP($B36,INDIRECT(G$2&"!$C$85:$AH$108"),DAY(G$3)+1,FALSE)="","",VLOOKUP($B36,INDIRECT(G$2&"!$C$85:$AH$108"),DAY(G$3)+1,FALSE)),"") | H36: =IFERROR(IF(VLOOKUP($B36,INDIRECT(H$2&"!$C$85:$AH$108"),DAY(H$3)+1,FALSE)="","",VLOOKUP($B36,INDIRECT(H$2&"!$C$85:$AH$108"),DAY(H$3)+1,FALSE)),"") | I36: =IFERROR(IF(VLOOKUP($B36,INDIRECT(I$2&"!$C$85:$AH$108"),DAY(I$3)+1,FALSE)="","",VLOOKUP($B36,INDIRECT(I$2&"!$C$85:$AH$108"),DAY(I$3)+1,FALSE)),"") | J36: =IFERROR(IF(VLOOKUP($B36,INDIRECT(J$2&"!$C$85:$AH$108"),DAY(J$3)+1,FALSE)="","",VLOOKUP($B36,INDIRECT(J$2&"!$C$85:$AH$108"),DAY(J$3)+1,FALSE)),"") | ... IV36: =IFERROR(IF(VLOOKUP($B36,INDIRECT(IV$2&"!$C$85:$AH$108"),DAY(IV$3)+1,FALSE)="","",VLOOKUP($B36,INDIRECT(IV$2&"!$C$85:$AH$108"),DAY(IV$3)+1,FALSE)),"")
A37: =A36+1 -> 9 | B37: =カレンダー!B$24 -> 0 | C37: =IFERROR(IF(VLOOKUP($B37,INDIRECT(C$2&"!$C$85:$AH$108"),DAY(C$3)+1,FALSE)="","",VLOOKUP($B37,INDIRECT(C$2&"!$C$85:$AH$108"),DAY(C$3)+1,FALSE)),"") | D37: =IFERROR(IF(VLOOKUP($B37,INDIRECT(D$2&"!$C$85:$AH$108"),DAY(D$3)+1,FALSE)="","",VLOOKUP($B37,INDIRECT(D$2&"!$C$85:$AH$108"),DAY(D$3)+1,FALSE)),"") | E37: =IFERROR(IF(VLOOKUP($B37,INDIRECT(E$2&"!$C$85:$AH$108"),DAY(E$3)+1,FALSE)="","",VLOOKUP($B37,INDIRECT(E$2&"!$C$85:$AH$108"),DAY(E$3)+1,FALSE)),"") | F37: =IFERROR(IF(VLOOKUP($B37,INDIRECT(F$2&"!$C$85:$AH$108"),DAY(F$3)+1,FALSE)="","",VLOOKUP($B37,INDIRECT(F$2&"!$C$85:$AH$108"),DAY(F$3)+1,FALSE)),"") | G37: =IFERROR(IF(VLOOKUP($B37,INDIRECT(G$2&"!$C$85:$AH$108"),DAY(G$3)+1,FALSE)="","",VLOOKUP($B37,INDIRECT(G$2&"!$C$85:$AH$108"),DAY(G$3)+1,FALSE)),"") | H37: =IFERROR(IF(VLOOKUP($B37,INDIRECT(H$2&"!$C$85:$AH$108"),DAY(H$3)+1,FALSE)="","",VLOOKUP($B37,INDIRECT(H$2&"!$C$85:$AH$108"),DAY(H$3)+1,FALSE)),"") | I37: =IFERROR(IF(VLOOKUP($B37,INDIRECT(I$2&"!$C$85:$AH$108"),DAY(I$3)+1,FALSE)="","",VLOOKUP($B37,INDIRECT(I$2&"!$C$85:$AH$108"),DAY(I$3)+1,FALSE)),"") | J37: =IFERROR(IF(VLOOKUP($B37,INDIRECT(J$2&"!$C$85:$AH$108"),DAY(J$3)+1,FALSE)="","",VLOOKUP($B37,INDIRECT(J$2&"!$C$85:$AH$108"),DAY(J$3)+1,FALSE)),"") | ... IV37: =IFERROR(IF(VLOOKUP($B37,INDIRECT(IV$2&"!$C$85:$AH$108"),DAY(IV$3)+1,FALSE)="","",VLOOKUP($B37,INDIRECT(IV$2&"!$C$85:$AH$108"),DAY(IV$3)+1,FALSE)),"")
A38: =A37+1 -> 10 | B38: =カレンダー!B$25 -> 0 | C38: =IFERROR(IF(VLOOKUP($B38,INDIRECT(C$2&"!$C$85:$AH$108"),DAY(C$3)+1,FALSE)="","",VLOOKUP($B38,INDIRECT(C$2&"!$C$85:$AH$108"),DAY(C$3)+1,FALSE)),"") | D38: =IFERROR(IF(VLOOKUP($B38,INDIRECT(D$2&"!$C$85:$AH$108"),DAY(D$3)+1,FALSE)="","",VLOOKUP($B38,INDIRECT(D$2&"!$C$85:$AH$108"),DAY(D$3)+1,FALSE)),"") | E38: =IFERROR(IF(VLOOKUP($B38,INDIRECT(E$2&"!$C$85:$AH$108"),DAY(E$3)+1,FALSE)="","",VLOOKUP($B38,INDIRECT(E$2&"!$C$85:$AH$108"),DAY(E$3)+1,FALSE)),"") | F38: =IFERROR(IF(VLOOKUP($B38,INDIRECT(F$2&"!$C$85:$AH$108"),DAY(F$3)+1,FALSE)="","",VLOOKUP($B38,INDIRECT(F$2&"!$C$85:$AH$108"),DAY(F$3)+1,FALSE)),"") | G38: =IFERROR(IF(VLOOKUP($B38,INDIRECT(G$2&"!$C$85:$AH$108"),DAY(G$3)+1,FALSE)="","",VLOOKUP($B38,INDIRECT(G$2&"!$C$85:$AH$108"),DAY(G$3)+1,FALSE)),"") | H38: =IFERROR(IF(VLOOKUP($B38,INDIRECT(H$2&"!$C$85:$AH$108"),DAY(H$3)+1,FALSE)="","",VLOOKUP($B38,INDIRECT(H$2&"!$C$85:$AH$108"),DAY(H$3)+1,FALSE)),"") | I38: =IFERROR(IF(VLOOKUP($B38,INDIRECT(I$2&"!$C$85:$AH$108"),DAY(I$3)+1,FALSE)="","",VLOOKUP($B38,INDIRECT(I$2&"!$C$85:$AH$108"),DAY(I$3)+1,FALSE)),"") | J38: =IFERROR(IF(VLOOKUP($B38,INDIRECT(J$2&"!$C$85:$AH$108"),DAY(J$3)+1,FALSE)="","",VLOOKUP($B38,INDIRECT(J$2&"!$C$85:$AH$108"),DAY(J$3)+1,FALSE)),"") | ... IV38: =IFERROR(IF(VLOOKUP($B38,INDIRECT(IV$2&"!$C$85:$AH$108"),DAY(IV$3)+1,FALSE)="","",VLOOKUP($B38,INDIRECT(IV$2&"!$C$85:$AH$108"),DAY(IV$3)+1,FALSE)),"")
B40: ラグジュアリープールヴィラ(単泊) | AZ40: E | BA40: T | BB40: N | BC40: N | BD40: N | BE40: N | BF40: K | BG40: L | BH40: Q | BI40: O | BJ40: H | BK40: L | BL40: L | BM40: Q | BN40: R | BO40: V | BP40: U | BQ40: O | BR40: Q | BS40: O | BT40: M | BU40: Q | BV40: W | BW40: V | BX40: L | BY40: L | BZ40: H | CA40: I | CB40: M | CC40: M | CD40: J | CE40: K | CF40: J | CG40: K | CH40: G | CI40: U | CJ40: V | CK40: S | CL40: G | CM40: G | CN40: D | CO40: I | CP40: I | CQ40: Q | CR40: Q | CS40: O | CT40: H | CU40: H | CV40: H | CW40: I | CX40: M | CY40: J | CZ40: J | DA40: J | DB40: C | DC40: C | DD40: M | DE40: M | DF40: C | DG40: C | DH40: C | DI40: C | DJ40: C | DK40: K | DL40: N | DM40: L | DN40: N | DO40: C | DP40: C | DQ40: C | DR40: G | DS40: I | DT40: C | DU40: C | DV40: C | DW40: D | DX40: D | DY40: G | DZ40: I | EA40: C | EB40: C | EC40: C | ED40: C | EE40: C | EF40: G | EG40: I | EH40: C | EI40: C | EJ40: C | EK40: C | EL40: C | EM40: G | EN40: I | EO40: G | EP40: G | EQ40: G | ER40: G | ES40: I | ET40: T | EU40: T | EV40: T | EW40: T | EX40: X | EY40: Z | EZ40: Y | FA40: W | FB40: T | FC40: C | FD40: C | FE40: C | FF40: C | FG40: C | FH40: G | FI40: I | FJ40: I | FK40: C | FL40: C | FM40: C | FN40: C | FO40: G | FP40: I | FQ40: C | FR40: C | FS40: C | FT40: C | FU40: C | FV40: G | FW40: I | FX40: C | FY40: C | FZ40: C | GA40: C | GB40: C | GC40: G | GD40: I
B41: ラグジュアリープールヴィラ(連泊) | AZ41: E | BA41: T | BB41: N | BC41: N | BD41: N | BE41: N | BF41: K | BG41: L | BH41: Q | BI41: O | BJ41: H | BK41: L | BL41: L | BM41: Q | BN41: R | BO41: V | BP41: U | BQ41: O | BR41: Q | BS41: O | BT41: M | BU41: Q | BV41: W | BW41: V | BX41: L | BY41: L | BZ41: H | CA41: I | CB41: M | CC41: M | CD41: J | CE41: K | CF41: J | CG41: K | CH41: G | CI41: U | CJ41: V | CK41: S | CL41: G | CM41: G | CN41: D | CO41: I | CP41: I | CQ41: Q | CR41: Q | CS41: O | CT41: H | CU41: H | CV41: H | CW41: I | CX41: M | CY41: J | CZ41: J | DA41: J | DB41: C | DC41: C | DD41: M | DE41: M | DF41: C | DG41: C | DH41: C | DI41: C | DJ41: C | DK41: K | DL41: N | DM41: L | DN41: N | DO41: C | DP41: C | DQ41: C | DR41: G | DS41: I | DT41: C | DU41: C | DV41: C | DW41: D | DX41: D | DY41: G | DZ41: I | EA41: C | EB41: C | EC41: C | ED41: C | EE41: C | EF41: G | EG41: I | EH41: C | EI41: C | EJ41: C | EK41: C | EL41: C | EM41: G | EN41: I | EO41: G | EP41: G | EQ41: G | ER41: G | ES41: I | ET41: T | EU41: T | EV41: T | EW41: T | EX41: X | EY41: Z | EZ41: Y | FA41: W | FB41: T | FC41: C | FD41: C | FE41: C | FF41: C | FG41: C | FH41: G | FI41: I | FJ41: I | FK41: C | FL41: C | FM41: C | FN41: C | FO41: G | FP41: I | FQ41: C | FR41: C | FS41: C | FT41: C | FU41: C | FV41: G | FW41: I | FX41: C | FY41: C | FZ41: C | GA41: C | GB41: C | GC41: G | GD41: I
B42: with SAUNA(単泊) | AZ42: E | BA42: T | BB42: N | BC42: N | BD42: N | BE42: N | BF42: K | BG42: L | BH42: Q | BI42: O | BJ42: H | BK42: L | BL42: L | BM42: Q | BN42: R | BO42: V | BP42: U | BQ42: O | BR42: Q | BS42: O | BT42: M | BU42: Q | BV42: W | BW42: V | BX42: L | BY42: L | BZ42: H | CA42: I | CB42: M | CC42: M | CD42: J | CE42: K | CF42: J | CG42: K | CH42: G | CI42: U | CJ42: V | CK42: S | CL42: G | CM42: G | CN42: D | CO42: I | CP42: I | CQ42: Q | CR42: Q | CS42: O | CT42: H | CU42: H | CV42: H | CW42: I | CX42: M | CY42: J | CZ42: J | DA42: J | DB42: C | DC42: C | DD42: M | DE42: M | DF42: C | DG42: C | DH42: C | DI42: C | DJ42: C | DK42: K | DL42: N | DM42: L | DN42: N | DO42: C | DP42: C | DQ42: C | DR42: G | DS42: I | DT42: C | DU42: C | DV42: C | DW42: D | DX42: D | DY42: G | DZ42: I | EA42: C | EB42: C | EC42: C | ED42: C | EE42: C | EF42: G | EG42: I | EH42: C | EI42: C | EJ42: C | EK42: C | EL42: C | EM42: G | EN42: I | EO42: G | EP42: G | EQ42: G | ER42: G | ES42: I | ET42: T | EU42: T | EV42: T | EW42: T | EX42: X | EY42: Z | EZ42: Y | FA42: W | FB42: T | FC42: C | FD42: C | FE42: C | FF42: C | FG42: C | FH42: G | FI42: I | FJ42: I | FK42: C | FL42: C | FM42: C | FN42: C | FO42: G | FP42: I | FQ42: C | FR42: C | FS42: C | FT42: C | FU42: C | FV42: G | FW42: I | FX42: C | FY42: C | FZ42: C | GA42: C | GB42: C | GC42: G | GD42: I
B43: with SAUNA(連泊) | AZ43: E | BA43: T | BB43: N | BC43: N | BD43: N | BE43: N | BF43: K | BG43: L | BH43: Q | BI43: O | BJ43: H | BK43: L | BL43: L | BM43: Q | BN43: R | BO43: V | BP43: U | BQ43: O | BR43: Q | BS43: O | BT43: M | BU43: Q | BV43: W | BW43: V | BX43: L | BY43: L | BZ43: H | CA43: I | CB43: M | CC43: M | CD43: J | CE43: K | CF43: J | CG43: K | CH43: G | CI43: U | CJ43: V | CK43: S | CL43: G | CM43: G | CN43: D | CO43: I | CP43: I | CQ43: Q | CR43: Q | CS43: O | CT43: H | CU43: H | CV43: H | CW43: I | CX43: M | CY43: J | CZ43: J | DA43: J | DB43: C | DC43: C | DD43: M | DE43: M | DF43: C | DG43: C | DH43: C | DI43: C | DJ43: C | DK43: K | DL43: N | DM43: L | DN43: N | DO43: C | DP43: C | DQ43: C | DR43: G | DS43: I | DT43: C | DU43: C | DV43: C | DW43: D | DX43: D | DY43: G | DZ43: I | EA43: C | EB43: C | EC43: C | ED43: C | EE43: C | EF43: G | EG43: I | EH43: C | EI43: C | EJ43: C | EK43: C | EL43: C | EM43: G | EN43: I | EO43: G | EP43: G | EQ43: G | ER43: G | ES43: I | ET43: T | EU43: T | EV43: T | EW43: T | EX43: X | EY43: Z | EZ43: Y | FA43: W | FB43: T | FC43: C | FD43: C | FE43: C | FF43: C | FG43: C | FH43: G | FI43: I | FJ43: I | FK43: C | FL43: C | FM43: C | FN43: C | FO43: G | FP43: I | FQ43: C | FR43: C | FS43: C | FT43: C | FU43: C | FV43: G | FW43: I | FX43: C | FY43: C | FZ43: C | GA43: C | GB43: C | GC43: G | GD43: I
A45: =SUM(C45:IV45) -> -130 | B45: ラグジュアリープールヴィラ(単泊) | C45: =IF(ISBLANK(C40),"",IF(C40=C4,0,-1)) | D45: =IF(ISBLANK(D40),"",IF(D40=D4,0,-1)) | E45: =IF(ISBLANK(E40),"",IF(E40=E4,0,-1)) | F45: =IF(ISBLANK(F40),"",IF(F40=F4,0,-1)) | G45: =IF(ISBLANK(G40),"",IF(G40=G4,0,-1)) | H45: =IF(ISBLANK(H40),"",IF(H40=H4,0,-1)) | I45: =IF(ISBLANK(I40),"",IF(I40=I4,0,-1)) | J45: =IF(ISBLANK(J40),"",IF(J40=J4,0,-1)) | ... IV45: =IF(ISBLANK(IV40),"",IF(IV40=IV4,0,-1))
A46: =SUM(C46:IV46) -> -130 | B46: ラグジュアリープールヴィラ(連泊) | C46: =IF(ISBLANK(C41),"",IF(C41=C5,0,-1)) | D46: =IF(ISBLANK(D41),"",IF(D41=D5,0,-1)) | E46: =IF(ISBLANK(E41),"",IF(E41=E5,0,-1)) | F46: =IF(ISBLANK(F41),"",IF(F41=F5,0,-1)) | G46: =IF(ISBLANK(G41),"",IF(G41=G5,0,-1)) | H46: =IF(ISBLANK(H41),"",IF(H41=H5,0,-1)) | I46: =IF(ISBLANK(I41),"",IF(I41=I5,0,-1)) | J46: =IF(ISBLANK(J41),"",IF(J41=J5,0,-1)) | ... IV46: =IF(ISBLANK(IV41),"",IF(IV41=IV5,0,-1))
A47: =SUM(C47:IV47) -> -130 | B47: with SAUNA(単泊) | C47: =IF(ISBLANK(C42),"",IF(C42=C6,0,-1)) | D47: =IF(ISBLANK(D42),"",IF(D42=D6,0,-1)) | E47: =IF(ISBLANK(E42),"",IF(E42=E6,0,-1)) | F47: =IF(ISBLANK(F42),"",IF(F42=F6,0,-1)) | G47: =IF(ISBLANK(G42),"",IF(G42=G6,0,-1)) | H47: =IF(ISBLANK(H42),"",IF(H42=H6,0,-1)) | I47: =IF(ISBLANK(I42),"",IF(I42=I6,0,-1)) | J47: =IF(ISBLANK(J42),"",IF(J42=J6,0,-1)) | ... IV47: =IF(ISBLANK(IV42),"",IF(IV42=IV6,0,-1))
A48: =SUM(C48:IV48) -> -130 | B48: with SAUNA(連泊) | C48: =IF(ISBLANK(C43),"",IF(C43=C7,0,-1)) | D48: =IF(ISBLANK(D43),"",IF(D43=D7,0,-1)) | E48: =IF(ISBLANK(E43),"",IF(E43=E7,0,-1)) | F48: =IF(ISBLANK(F43),"",IF(F43=F7,0,-1)) | G48: =IF(ISBLANK(G43),"",IF(G43=G7,0,-1)) | H48: =IF(ISBLANK(H43),"",IF(H43=H7,0,-1)) | I48: =IF(ISBLANK(I43),"",IF(I43=I7,0,-1)) | J48: =IF(ISBLANK(J43),"",IF(J43=J7,0,-1)) | ... IV48: =IF(ISBLANK(IV43),"",IF(IV43=IV7,0,-1))
EZ50: C | FA50: C | FB50: D | FC50: D | FD50: G | FE50: I | FF50: C | FG50: C | FH50: C | FI50: C | FJ50: C | FK50: G | FL50: I | FM50: C | FN50: C | FO50: C | FP50: C | FQ50: C | FR50: G | FS50: I | FT50: G | FU50: G | FV50: G | FW50: G | FX50: I | FY50: T | FZ50: T | GA50: T | GB50: T | GC50: X | GD50: Z
EZ51: C | FA51: C | FB51: D | FC51: D | FD51: G | FE51: I | FF51: C | FG51: C | FH51: C | FI51: C | FJ51: C | FK51: G | FL51: I | FM51: C | FN51: C | FO51: C | FP51: C | FQ51: C | FR51: G | FS51: I | FT51: G | FU51: G | FV51: G | FW51: G | FX51: I | FY51: T | FZ51: T | GA51: T | GB51: T | GC51: X | GD51: Z
EZ52: C | FA52: C | FB52: D | FC52: D | FD52: G | FE52: I | FF52: C | FG52: C | FH52: C | FI52: C | FJ52: C | FK52: G | FL52: I | FM52: C | FN52: C | FO52: C | FP52: C | FQ52: C | FR52: G | FS52: I | FT52: G | FU52: G | FV52: G | FW52: G | FX52: I | FY52: T | FZ52: T | GA52: T | GB52: T | GC52: X | GD52: Z
EZ53: C | FA53: C | FB53: D | FC53: D | FD53: G | FE53: I | FF53: C | FG53: C | FH53: C | FI53: C | FJ53: C | FK53: G | FL53: I | FM53: C | FN53: C | FO53: C | FP53: C | FQ53: C | FR53: G | FS53: I | FT53: G | FU53: G | FV53: G | FW53: G | FX53: I | FY53: T | FZ53: T | GA53: T | GB53: T | GC53: X | GD53: Z

Sheet カレンダー
B1: 45870 | C1: =B1-1 -> 45869 | D1: 料金プラン①⇒ | F1: WEB割 | I1: 割引率⇒
B2: カレンダー名 | C2: 利用人数⇩ | D2: A | E2: B | F2: C | G2: D | H2: E | I2: F | J2: G | K2: H | L2: I | M2: J | N2: K | O2: L | P2: M | Q2: N | R2: O | S2: P | T2: Q | U2: R | V2: S | W2: T | X2: U | Y2: V | Z2: W | AA2: X | AB2: Y | AC2: Z
A3: 1 | B3: ラグジュアリープールヴィラ | C3: 2
A4: 12 | B4: with SAUNA | C4: 2
A5: 6 | C5: 2
A6: 13 | C6: 2
A7: 8 | C7: 1
A8: 14 | C8: 4
C10: =TEXT(EDATE(B1,0),"yyyy年m月") -> 2025年8月 | K10: =TEXT(EDATE(C10,1),"yyyy年m月") -> 2025年9月 | S10: =TEXT(EDATE(K10,1),"yyyy年m月") -> 2025年10月
B11: ⇩対象部屋タイプ⇩ | C11: 日 | D11: 月 | E11: 火 | F11: 水 | G11: 木 | H11: 金 | I11: 土 | K11: 日 | L11: 月 | M11: 火 | N11: 水 | O11: 木 | P11: 金 | Q11: 土 | S11: 日 | T11: 月 | U11: 火 | V11: 水 | W11: 木 | X11: 金 | Y11: 土
C12: =$C$10-WEEKDAY($C$10)+1 -> 45865 | D12: =$C$10-WEEKDAY($C$10)+2 -> 45866 | E12: =$C$10-WEEKDAY($C$10)+3 -> 45867 | F12: =$C$10-WEEKDAY($C$10)+4 -> 45868 | G12: =$C$10-WEEKDAY($C$10)+5 -> 45869 | H12: =$C$10-WEEKDAY($C$10)+6 -> 45870 | I12: =$C$10-WEEKDAY($C$10)+7 -> 45871 | K12: =$K$10-WEEKDAY($K$10)+1 -> 45900 | L12: =$K$10-WEEKDAY($K$10)+2 -> 45901 | M12: =$K$10-WEEKDAY($K$10)+3 -> 45902 | N12: =$K$10-WEEKDAY($K$10)+4 -> 45903 | O12: =$K$10-WEEKDAY($K$10)+5 -> 45904 | P12: =$K$10-WEEKDAY($K$10)+6 -> 45905 | Q12: =$K$10-WEEKDAY($K$10)+7 -> 45906 | S12: =$S$10-WEEKDAY($S$10)+1 -> 45928 | T12: =$S$10-WEEKDAY($S$10)+2 -> 45929 | U12: =$S$10-WEEKDAY($S$10)+3 -> 45930 | V12: =$S$10-WEEKDAY($S$10)+4 -> 45931 | W12: =$S$10-WEEKDAY($S$10)+5 -> 45932 | X12: =$S$10-WEEKDAY($S$10)+6 -> 45933 | Y12: =$S$10-WEEKDAY($S$10)+7 -> 45934
B13: ラグジュアリープールヴィラ(連泊) | C13: =IF(TEXT(カレンダー!C12,"yyyy年m月")=TEXT($C$10,"yyyy年m月"),INDEX(横カレンダー!$C$4:$IV$13,MATCH($B$13,横カレンダー!$B$4:$B$13,0),MATCH(カレンダー!C12,横カレンダー!$C$3:$IV$3,0)),"") | D13: =IF(TEXT(カレンダー!D12,"yyyy年m月")=TEXT($C$10,"yyyy年m月"),INDEX(横カレンダー!$C$4:$IV$13,MATCH($B$13,横カレンダー!$B$4:$B$13,0),MATCH(カレンダー!D12,横カレンダー!$C$3:$IV$3,0)),"") | E13: =IF(TEXT(カレンダー!E12,"yyyy年m月")=TEXT($C$10,"yyyy年m月"),INDEX(横カレンダー!$C$4:$IV$13,MATCH($B$13,横カレンダー!$B$4:$B$13,0),MATCH(カレンダー!E12,横カレンダー!$C$3:$IV$3,0)),"") | F13: =IF(TEXT(カレンダー!F12,"yyyy年m月")=TEXT($C$10,"yyyy年m月"),INDEX(横カレンダー!$C$4:$IV$13,MATCH($B$13,横カレンダー!$B$4:$B$13,0),MATCH(カレンダー!F12,横カレンダー!$C$3:$IV$3,0)),"") | G13: =IF(TEXT(カレンダー!G12,"yyyy年m月")=TEXT($C$10,"yyyy年m月"),INDEX(横カレンダー!$C$4:$IV$13,MATCH($B$13,横カレンダー!$B$4:$B$13,0),MATCH(カレンダー!G12,横カレンダー!$C$3:$IV$3,0)),"") | H13: =IF(TEXT(カレンダー!H12,"yyyy年m月")=TEXT($C$10,"yyyy年m月"),INDEX(横カレンダー!$C$4:$IV$13,MATCH($B$13,横カレンダー!$B$4:$B$13,0),MATCH(カレンダー!H12,横カレンダー!$C$3:$IV$3,0)),"") -> #N/A | I13: =IF(TEXT(カレンダー!I12,"yyyy年m月")=TEXT($C$10,"yyyy年m月"),INDEX(横カレンダー!$C$4:$IV$13,MATCH($B$13,横カレンダー!$B$4:$B$13,0),MATCH(カレンダー!I12,横カレンダー!$C$3:$IV$3,0)),"") -> #N/A | K13: =IF(TEXT(カレンダー!K12,"yyyy年m月")=TEXT($K$10,"yyyy年m月"),INDEX(横カレンダー!$C$4:$IV$13,MATCH($B$13,横カレンダー!$B$4:$B$13,0),MATCH(カレンダー!K12,横カレンダー!$C$3:$IV$3,0)),"") | L13: =IF(TEXT(カレンダー!L12,"yyyy年m月")=TEXT($K$10,"yyyy年m月"),INDEX(横カレンダー!$C$4:$IV$13,MATCH($B$13,横カレンダー!$B$4:$B$13,0),MATCH(カレンダー!L12,横カレンダー!$C$3:$IV$3,0)),"") -> #N/A | M13: =IF(TEXT(カレンダー!M12,"yyyy年m月")=TEXT($K$10,"yyyy年m月"),INDEX(横カレンダー!$C$4:$IV$13,MATCH($B$13,横カレンダー!$B$4:$B$13,0),MATCH(カレンダー!M12,横カレンダー!$C$3:$IV$3,0)),"") -> #N/A | N13: =IF(TEXT(カレンダー!N12,"yyyy年m月")=TEXT($K$10,"yyyy年m月"),INDEX(横カレンダー!$C$4:$IV$13,MATCH($B$13,横カレンダー!$B$4:$B$13,0),MATCH(カレンダー!N12,横カレンダー!$C$3:$IV$3,0)),"") -> #N/A | O13: =IF(TEXT(カレンダー!O12,"yyyy年m月")=TEXT($K$10,"yyyy年m月"),INDEX(横カレンダー!$C$4:$IV$13,MATCH($B$13,横カレンダー!$B$4:$B$13,0),MATCH(カレンダー!O12,横カレンダー!$C$3:$IV$3,0)),"") -> #N/A | P13: =IF(TEXT(カレンダー!P12,"yyyy年m月")=TEXT($K$10,"yyyy年m月"),INDEX(横カレンダー!$C$4:$IV$13,MATCH($B$13,横カレンダー!$B$4:$B$13,0),MATCH(カレンダー!P12,横カレンダー!$C$3:$IV$3,0)),"") -> #N/A | Q13: =IF(TEXT(カレンダー!Q12,"yyyy年m月")=TEXT($K$10,"yyyy年m月"),INDEX(横カレンダー!$C$4:$IV$13,MATCH($B$13,横カレンダー!$B$4:$B$13,0),MATCH(カレンダー!Q12,横カレンダー!$C$3:$IV$3,0)),"") -> #N/A | S13: =IF(TEXT(カレンダー!S12,"yyyy年m月")=TEXT($S$10,"yyyy年m月"),INDEX(横カレンダー!$C$4:$IV$13,MATCH($B$13,横カレンダー!$B$4:$B$13,0),MATCH(カレンダー!S12,横カレンダー!$C$3:$IV$3,0)),"") | T13: =IF(TEXT(カレンダー!T12,"yyyy年m月")=TEXT($S$10,"yyyy年m月"),INDEX(横カレンダー!$C$4:$IV$13,MATCH($B$13,横カレンダー!$B$4:$B$13,0),MATCH(カレンダー!T12,横カレンダー!$C$3:$IV$3,0)),"") | U13: =IF(TEXT(カレンダー!U12,"yyyy年m月")=TEXT($S$10,"yyyy年m月"),INDEX(横カレンダー!$C$4:$IV$13,MATCH($B$13,横カレンダー!$B$4:$B$13,0),MATCH(カレンダー!U12,横カレンダー!$C$3:$IV$3,0)),"") | V13: =IF(TEXT(カレンダー!V12,"yyyy年m月")=TEXT($S$10,"yyyy年m月"),INDEX(横カレンダー!$C$4:$IV$13,MATCH($B$13,横カレンダー!$B$4:$B$13,0),MATCH(カレンダー!V12,横カレンダー!$C$3:$IV$3,0)),"") -> #N/A | W13: =IF(TEXT(カレンダー!W12,"yyyy年m月")=TEXT($S$10,"yyyy年m月"),INDEX(横カレンダー!$C$4:$IV$13,MATCH($B$13,横カレンダー!$B$4:$B$13,0),MATCH(カレンダー!W12,横カレンダー!$C$3:$IV$3,0)),"") -> #N/A | X13: =IF(TEXT(カレンダー!X12,"yyyy年m月")=TEXT($S$10,"yyyy年m月"),INDEX(横カレンダー!$C$4:$IV$13,MATCH($B$13,横カレンダー!$B$4:$B$13,0),MATCH(カレンダー!X12,横カレンダー!$C$3:$IV$3,0)),"") -> #N/A | Y13: =IF(TEXT(カレンダー!Y12,"yyyy年m月")=TEXT($S$10,"yyyy年m月"),INDEX(横カレンダー!$C$4:$IV$13,MATCH($B$13,横カレンダー!$B$4:$B$13,0),MATCH(カレンダー!Y12,横カレンダー!$C$3:$IV$3,0)),"") -> #N/A
B14: =MATCH($B$13,B3:B8,0)+1 -> #N/A | C14: =$C$10-WEEKDAY($C$10)+8 -> 45872 | D14: =$C$10-WEEKDAY($C$10)+9 -> 45873 | E14: =$C$10-WEEKDAY($C$10)+10 -> 45874 | F14: =$C$10-WEEKDAY($C$10)+11 -> 45875 | G14: =$C$10-WEEKDAY($C$10)+12 -> 45876 | H14: =$C$10-WEEKDAY($C$10)+13 -> 45877 | I14: =$C$10-WEEKDAY($C$10)+14 -> 45878 | K14: =$K$10-WEEKDAY($K$10)+8 -> 45907 | L14: =$K$10-WEEKDAY($K$10)+9 -> 45908 | M14: =$K$10-WEEKDAY($K$10)+10 -> 45909 | N14: =$K$10-WEEKDAY($K$10)+11 -> 45910 | O14: =$K$10-WEEKDAY($K$10)+12 -> 45911 | P14: =$K$10-WEEKDAY($K$10)+13 -> 45912 | Q14: =$K$10-WEEKDAY($K$10)+14 -> 45913 | S14: =$S$10-WEEKDAY($S$10)+8 -> 45935 | T14: =$S$10-WEEKDAY($S$10)+9 -> 45936 | U14: =$S$10-WEEKDAY($S$10)+10 -> 45937 | V14: =$S$10-WEEKDAY($S$10)+11 -> 45938 | W14: =$S$10-WEEKDAY($S$10)+12 -> 45939 | X14: =$S$10-WEEKDAY($S$10)+13 -> 45940 | Y14: =$S$10-WEEKDAY($S$10)+14 -> 45941
B15: ↓カレンダーリスト | C15: =IF(TEXT(カレンダー!C14,"yyyy年m月")=TEXT($C$10,"yyyy年m月"),INDEX(横カレンダー!$C$4:$IV$13,MATCH($B$13,横カレンダー!$B$4:$B$13,0),MATCH(カレンダー!C14,横カレンダー!$C$3:$IV$3,0)),"") -> #N/A | D15: =IF(TEXT(カレンダー!D14,"yyyy年m月")=TEXT($C$10,"yyyy年m月"),INDEX(横カレンダー!$C$4:$IV$13,MATCH($B$13,横カレンダー!$B$4:$B$13,0),MATCH(カレンダー!D14,横カレンダー!$C$3:$IV$3,0)),"") -> #N/A | E15: =IF(TEXT(カレンダー!E14,"yyyy年m月")=TEXT($C$10,"yyyy年m月"),INDEX(横カレンダー!$C$4:$IV$13,MATCH($B$13,横カレンダー!$B$4:$B$13,0),MATCH(カレンダー!E14,横カレンダー!$C$3:$IV$3,0)),"") -> #N/A | F15: =IF(TEXT(カレンダー!F14,"yyyy年m月")=TEXT($C$10,"yyyy年m月"),INDEX(横カレンダー!$C$4:$IV$13,MATCH($B$13,横カレンダー!$B$4:$B$13,0),MATCH(カレンダー!F14,横カレンダー!$C$3:$IV$3,0)),"") -> #N/A | G15: =IF(TEXT(カレンダー!G14,"yyyy年m月")=TEXT($C$10,"yyyy年m月"),INDEX(横カレンダー!$C$4:$IV$13,MATCH($B$13,横カレンダー!$B$4:$B$13,0),MATCH(カレンダー!G14,横カレンダー!$C$3:$IV$3,0)),"") -> #N/A | H15: =IF(TEXT(カレンダー!H14,"yyyy年m月")=TEXT($C$10,"yyyy年m月"),INDEX(横カレンダー!$C$4:$IV$13,MATCH($B$13,横カレンダー!$B$4:$B$13,0),MATCH(カレンダー!H14,横カレンダー!$C$3:$IV$3,0)),"") -> #N/A | I15: =IF(TEXT(カレンダー!I14,"yyyy年m月")=TEXT($C$10,"yyyy年m月"),INDEX(横カレンダー!$C$4:$IV$13,MATCH($B$13,横カレンダー!$B$4:$B$13,0),MATCH(カレンダー!I14,横カレンダー!$C$3:$IV$3,0)),"") -> #N/A | K15: =IF(TEXT(カレンダー!K14,"yyyy年m月")=TEXT($K$10,"yyyy年m月"),INDEX(横カレンダー!$C$4:$IV$13,MATCH($B$13,横カレンダー!$B$4:$B$13,0),MATCH(カレンダー!K14,横カレンダー!$C$3:$IV$3,0)),"") -> #N/A | L15: =IF(TEXT(カレンダー!L14,"yyyy年m月")=TEXT($K$10,"yyyy年m月"),INDEX(横カレンダー!$C$4:$IV$13,MATCH($B$13,横カレンダー!$B$4:$B$13,0),MATCH(カレンダー!L14,横カレンダー!$C$3:$IV$3,0)),"") -> #N/A | M15: =IF(TEXT(カレンダー!M14,"yyyy年m月")=TEXT($K$10,"yyyy年m月"),INDEX(横カレンダー!$C$4:$IV$13,MATCH($B$13,横カレンダー!$B$4:$B$13,0),MATCH(カレンダー!M14,横カレンダー!$C$3:$IV$3,0)),"") -> #N/A | N15: =IF(TEXT(カレンダー!N14,"yyyy年m月")=TEXT($K$10,"yyyy年m月"),INDEX(横カレンダー!$C$4:$IV$13,MATCH($B$13,横カレンダー!$B$4:$B$13,0),MATCH(カレンダー!N14,横カレンダー!$C$3:$IV$3,0)),"") -> #N/A | O15: =IF(TEXT(カレンダー!O14,"yyyy年m月")=TEXT($K$10,"yyyy年m月"),INDEX(横カレンダー!$C$4:$IV$13,MATCH($B$13,横カレンダー!$B$4:$B$13,0),MATCH(カレンダー!O14,横カレンダー!$C$3:$IV$3,0)),"") -> #N/A | P15: =IF(TEXT(カレンダー!P14,"yyyy年m月")=TEXT($K$10,"yyyy年m月"),INDEX(横カレンダー!$C$4:$IV$13,MATCH($B$13,横カレンダー!$B$4:$B$13,0),MATCH(カレンダー!P14,横カレンダー!$C$3:$IV$3,0)),"") -> #N/A | Q15: =IF(TEXT(カレンダー!Q14,"yyyy年m月")=TEXT($K$10,"yyyy年m月"),INDEX(横カレンダー!$C$4:$IV$13,MATCH($B$13,横カレンダー!$B$4:$B$13,0),MATCH(カレンダー!Q14,横カレンダー!$C$3:$IV$3,0)),"") -> #N/A | S15: =IF(TEXT(カレンダー!S14,"yyyy年m月")=TEXT($S$10,"yyyy年m月"),INDEX(横カレンダー!$C$4:$IV$13,MATCH($B$13,横カレンダー!$B$4:$B$13,0),MATCH(カレンダー!S14,横カレンダー!$C$3:$IV$3,0)),"") -> #N/A | T15: =IF(TEXT(カレンダー!T14,"yyyy年m月")=TEXT($S$10,"yyyy年m月"),INDEX(横カレンダー!$C$4:$IV$13,MATCH($B$13,横カレンダー!$B$4:$B$13,0),MATCH(カレンダー!T14,横カレンダー!$C$3:$IV$3,0)),"") -> #N/A | U15: =IF(TEXT(カレンダー!U14,"yyyy年m月")=TEXT($S$10,"yyyy年m月"),INDEX(横カレンダー!$C$4:$IV$13,MATCH($B$13,横カレンダー!$B$4:$B$13,0),MATCH(カレンダー!U14,横カレンダー!$C$3:$IV$3,0)),"") -> #N/A | V15: =IF(TEXT(カレンダー!V14,"yyyy年m月")=TEXT($S$10,"yyyy年m月"),INDEX(横カレンダー!$C$4:$IV$13,MATCH($B$13,横カレンダー!$B$4:$B$13,0),MATCH(カレンダー!V14,横カレンダー!$C$3:$IV$3,0)),"") -> #N/A | W15: =IF(TEXT(カレンダー!W14,"yyyy年m月")=TEXT($S$10,"yyyy年m月"),INDEX(横カレンダー!$C$4:$IV$13,MATCH($B$13,横カレンダー!$B$4:$B$13,0),MATCH(カレンダー!W14,横カレンダー!$C$3:$IV$3,0)),"") -> #N/A | X15: =IF(TEXT(カレンダー!X14,"yyyy年m月")=TEXT($S$10,"yyyy年m月"),INDEX(横カレンダー!$C$4:$IV$13,MATCH($B$13,横カレンダー!$B$4:$B$13,0),MATCH(カレンダー!X14,横カレンダー!$C$3:$IV$3,0)),"") -> #N/A | Y15: =IF(TEXT(カレンダー!Y14,"yyyy年m月")=TEXT($S$10,"yyyy年m月"),INDEX(横カレンダー!$C$4:$IV$13,MATCH($B$13,横カレンダー!$B$4:$B$13,0),MATCH(カレンダー!Y14,横カレンダー!$C$3:$IV$3,0)),"") -> #N/A
A16: 1 | B16: ラグジュアリープールヴィラ(単泊) | C16: =$C$10-WEEKDAY($C$10)+15 -> 45879 | D16: =$C$10-WEEKDAY($C$10)+16 -> 45880 | E16: =$C$10-WEEKDAY($C$10)+17 -> 45881 | F16: =$C$10-WEEKDAY($C$10)+18 -> 45882 | G16: =$C$10-WEEKDAY($C$10)+19 -> 45883 | H16: =$C$10-WEEKDAY($C$10)+20 -> 45884 | I16: =$C$10-WEEKDAY($C$10)+21 -> 45885 | K16: =$K$10-WEEKDAY($K$10)+15 -> 45914 | L16: =$K$10-WEEKDAY($K$10)+16 -> 45915 | M16: =$K$10-WEEKDAY($K$10)+17 -> 45916 | N16: =$K$10-WEEKDAY($K$10)+18 -> 45917 | O16: =$K$10-WEEKDAY($K$10)+19 -> 45918 | P16: =$K$10-WEEKDAY($K$10)+20 -> 45919 | Q16: =$K$10-WEEKDAY($K$10)+21 -> 45920 | S16: =$S$10-WEEKDAY($S$10)+15 -> 45942 | T16: =$S$10-WEEKDAY($S$10)+16 -> 45943 | U16: =$S$10-WEEKDAY($S$10)+17 -> 45944 | V16: =$S$10-WEEKDAY($S$10)+18 -> 45945 | W16: =$S$10-WEEKDAY($S$10)+19 -> 45946 | X16: =$S$10-WEEKDAY($S$10)+20 -> 45947 | Y16: =$S$10-WEEKDAY($S$10)+21 -> 45948
A17: 12 | B17: ラグジュアリープールヴィラ(連泊) | C17: =IF(TEXT(カレンダー!C16,"yyyy年m月")=TEXT($C$10,"yyyy年m月"),INDEX(横カレンダー!$C$4:$IV$13,MATCH($B$13,横カレンダー!$B$4:$B$13,0),MATCH(カレンダー!C16,横カレンダー!$C$3:$IV$3,0)),"") -> #N/A | D17: =IF(TEXT(カレンダー!D16,"yyyy年m月")=TEXT($C$10,"yyyy年m月"),INDEX(横カレンダー!$C$4:$IV$13,MATCH($B$13,横カレンダー!$B$4:$B$13,0),MATCH(カレンダー!D16,横カレンダー!$C$3:$IV$3,0)),"") -> #N/A | E17: =IF(TEXT(カレンダー!E16,"yyyy年m月")=TEXT($C$10,"yyyy年m月"),INDEX(横カレンダー!$C$4:$IV$13,MATCH($B$13,横カレンダー!$B$4:$B$13,0),MATCH(カレンダー!E16,横カレンダー!$C$3:$IV$3,0)),"") -> #N/A | F17: =IF(TEXT(カレンダー!F16,"yyyy年m月")=TEXT($C$10,"yyyy年m月"),INDEX(横カレンダー!$C$4:$IV$13,MATCH($B$13,横カレンダー!$B$4:$B$13,0),MATCH(カレンダー!F16,横カレンダー!$C$3:$IV$3,0)),"") -> #N/A | G17: =IF(TEXT(カレンダー!G16,"yyyy年m月")=TEXT($C$10,"yyyy年m月"),INDEX(横カレンダー!$C$4:$IV$13,MATCH($B$13,横カレンダー!$B$4:$B$13,0),MATCH(カレンダー!G16,横カレンダー!$C$3:$IV$3,0)),"") -> #N/A | H17: =IF(TEXT(カレンダー!H16,"yyyy年m月")=TEXT($C$10,"yyyy年m月"),INDEX(横カレンダー!$C$4:$IV$13,MATCH($B$13,横カレンダー!$B$4:$B$13,0),MATCH(カレンダー!H16,横カレンダー!$C$3:$IV$3,0)),"") -> #N/A | I17: =IF(TEXT(カレンダー!I16,"yyyy年m月")=TEXT($C$10,"yyyy年m月"),INDEX(横カレンダー!$C$4:$IV$13,MATCH($B$13,横カレンダー!$B$4:$B$13,0),MATCH(カレンダー!I16,横カレンダー!$C$3:$IV$3,0)),"") -> #N/A | K17: =IF(TEXT(カレンダー!K16,"yyyy年m月")=TEXT($K$10,"yyyy年m月"),INDEX(横カレンダー!$C$4:$IV$13,MATCH($B$13,横カレンダー!$B$4:$B$13,0),MATCH(カレンダー!K16,横カレンダー!$C$3:$IV$3,0)),"") -> #N/A | L17: =IF(TEXT(カレンダー!L16,"yyyy年m月")=TEXT($K$10,"yyyy年m月"),INDEX(横カレンダー!$C$4:$IV$13,MATCH($B$13,横カレンダー!$B$4:$B$13,0),MATCH(カレンダー!L16,横カレンダー!$C$3:$IV$3,0)),"") -> #N/A | M17: =IF(TEXT(カレンダー!M16,"yyyy年m月")=TEXT($K$10,"yyyy年m月"),INDEX(横カレンダー!$C$4:$IV$13,MATCH($B$13,横カレンダー!$B$4:$B$13,0),MATCH(カレンダー!M16,横カレンダー!$C$3:$IV$3,0)),"") -> #N/A | N17: =IF(TEXT(カレンダー!N16,"yyyy年m月")=TEXT($K$10,"yyyy年m月"),INDEX(横カレンダー!$C$4:$IV$13,MATCH($B$13,横カレンダー!$B$4:$B$13,0),MATCH(カレンダー!N16,横カレンダー!$C$3:$IV$3,0)),"") -> #N/A | O17: =IF(TEXT(カレンダー!O16,"yyyy年m月")=TEXT($K$10,"yyyy年m月"),INDEX(横カレンダー!$C$4:$IV$13,MATCH($B$13,横カレンダー!$B$4:$B$13,0),MATCH(カレンダー!O16,横カレンダー!$C$3:$IV$3,0)),"") -> #N/A | P17: =IF(TEXT(カレンダー!P16,"yyyy年m月")=TEXT($K$10,"yyyy年m月"),INDEX(横カレンダー!$C$4:$IV$13,MATCH($B$13,横カレンダー!$B$4:$B$13,0),MATCH(カレンダー!P16,横カレンダー!$C$3:$IV$3,0)),"") -> #N/A | Q17: =IF(TEXT(カレンダー!Q16,"yyyy年m月")=TEXT($K$10,"yyyy年m月"),INDEX(横カレンダー!$C$4:$IV$13,MATCH($B$13,横カレンダー!$B$4:$B$13,0),MATCH(カレンダー!Q16,横カレンダー!$C$3:$IV$3,0)),"") -> #N/A | S17: =IF(TEXT(カレンダー!S16,"yyyy年m月")=TEXT($S$10,"yyyy年m月"),INDEX(横カレンダー!$C$4:$IV$13,MATCH($B$13,横カレンダー!$B$4:$B$13,0),MATCH(カレンダー!S16,横カレンダー!$C$3:$IV$3,0)),"") -> #N/A | T17: =IF(TEXT(カレンダー!T16,"yyyy年m月")=TEXT($S$10,"yyyy年m月"),INDEX(横カレンダー!$C$4:$IV$13,MATCH($B$13,横カレンダー!$B$4:$B$13,0),MATCH(カレンダー!T16,横カレンダー!$C$3:$IV$3,0)),"") -> #N/A | U17: =IF(TEXT(カレンダー!U16,"yyyy年m月")=TEXT($S$10,"yyyy年m月"),INDEX(横カレンダー!$C$4:$IV$13,MATCH($B$13,横カレンダー!$B$4:$B$13,0),MATCH(カレンダー!U16,横カレンダー!$C$3:$IV$3,0)),"") -> #N/A | V17: =IF(TEXT(カレンダー!V16,"yyyy年m月")=TEXT($S$10,"yyyy年m月"),INDEX(横カレンダー!$C$4:$IV$13,MATCH($B$13,横カレンダー!$B$4:$B$13,0),MATCH(カレンダー!V16,横カレンダー!$C$3:$IV$3,0)),"") -> #N/A | W17: =IF(TEXT(カレンダー!W16,"yyyy年m月")=TEXT($S$10,"yyyy年m月"),INDEX(横カレンダー!$C$4:$IV$13,MATCH($B$13,横カレンダー!$B$4:$B$13,0),MATCH(カレンダー!W16,横カレンダー!$C$3:$IV$3,0)),"") -> #N/A | X17: =IF(TEXT(カレンダー!X16,"yyyy年m月")=TEXT($S$10,"yyyy年m月"),INDEX(横カレンダー!$C$4:$IV$13,MATCH($B$13,横カレンダー!$B$4:$B$13,0),MATCH(カレンダー!X16,横カレンダー!$C$3:$IV$3,0)),"") -> #N/A | Y17: =IF(TEXT(カレンダー!Y16,"yyyy年m月")=TEXT($S$10,"yyyy年m月"),INDEX(横カレンダー!$C$4:$IV$13,MATCH($B$13,横カレンダー!$B$4:$B$13,0),MATCH(カレンダー!Y16,横カレンダー!$C$3:$IV$3,0)),"") -> #N/A
A18: 6 | B18: with SAUNA(単泊) | C18: =$C$10-WEEKDAY($C$10)+22 -> 45886 | D18: =$C$10-WEEKDAY($C$10)+23 -> 45887 | E18: =$C$10-WEEKDAY($C$10)+24 -> 45888 | F18: =$C$10-WEEKDAY($C$10)+25 -> 45889 | G18: =$C$10-WEEKDAY($C$10)+26 -> 45890 | H18: =$C$10-WEEKDAY($C$10)+27 -> 45891 | I18: =$C$10-WEEKDAY($C$10)+28 -> 45892 | K18: =$K$10-WEEKDAY($K$10)+22 -> 45921 | L18: =$K$10-WEEKDAY($K$10)+23 -> 45922 | M18: =$K$10-WEEKDAY($K$10)+24 -> 45923 | N18: =$K$10-WEEKDAY($K$10)+25 -> 45924 | O18: =$K$10-WEEKDAY($K$10)+26 -> 45925 | P18: =$K$10-WEEKDAY($K$10)+27 -> 45926 | Q18: =$K$10-WEEKDAY($K$10)+28 -> 45927 | S18: =$S$10-WEEKDAY($S$10)+22 -> 45949 | T18: =$S$10-WEEKDAY($S$10)+23 -> 45950 | U18: =$S$10-WEEKDAY($S$10)+24 -> 45951 | V18: =$S$10-WEEKDAY($S$10)+25 -> 45952 | W18: =$S$10-WEEKDAY($S$10)+26 -> 45953 | X18: =$S$10-WEEKDAY($S$10)+27 -> 45954 | Y18: =$S$10-WEEKDAY($S$10)+28 -> 45955
A19: 13 | B19: with SAUNA(連泊) | C19: =IF(TEXT(カレンダー!C18,"yyyy年m月")=TEXT($C$10,"yyyy年m月"),INDEX(横カレンダー!$C$4:$IV$13,MATCH($B$13,横カレンダー!$B$4:$B$13,0),MATCH(カレンダー!C18,横カレンダー!$C$3:$IV$3,0)),"") -> #N/A | D19: =IF(TEXT(カレンダー!D18,"yyyy年m月")=TEXT($C$10,"yyyy年m月"),INDEX(横カレンダー!$C$4:$IV$13,MATCH($B$13,横カレンダー!$B$4:$B$13,0),MATCH(カレンダー!D18,横カレンダー!$C$3:$IV$3,0)),"") -> #N/A | E19: =IF(TEXT(カレンダー!E18,"yyyy年m月")=TEXT($C$10,"yyyy年m月"),INDEX(横カレンダー!$C$4:$IV$13,MATCH($B$13,横カレンダー!$B$4:$B$13,0),MATCH(カレンダー!E18,横カレンダー!$C$3:$IV$3,0)),"") -> #N/A | F19: =IF(TEXT(カレンダー!F18,"yyyy年m月")=TEXT($C$10,"yyyy年m月"),INDEX(横カレンダー!$C$4:$IV$13,MATCH($B$13,横カレンダー!$B$4:$B$13,0),MATCH(カレンダー!F18,横カレンダー!$C$3:$IV$3,0)),"") -> #N/A | G19: =IF(TEXT(カレンダー!G18,"yyyy年m月")=TEXT($C$10,"yyyy年m月"),INDEX(横カレンダー!$C$4:$IV$13,MATCH($B$13,横カレンダー!$B$4:$B$13,0),MATCH(カレンダー!G18,横カレンダー!$C$3:$IV$3,0)),"") -> #N/A | H19: =IF(TEXT(カレンダー!H18,"yyyy年m月")=TEXT($C$10,"yyyy年m月"),INDEX(横カレンダー!$C$4:$IV$13,MATCH($B$13,横カレンダー!$B$4:$B$13,0),MATCH(カレンダー!H18,横カレンダー!$C$3:$IV$3,0)),"") -> #N/A | I19: =IF(TEXT(カレンダー!I18,"yyyy年m月")=TEXT($C$10,"yyyy年m月"),INDEX(横カレンダー!$C$4:$IV$13,MATCH($B$13,横カレンダー!$B$4:$B$13,0),MATCH(カレンダー!I18,横カレンダー!$C$3:$IV$3,0)),"") -> #N/A | K19: =IF(TEXT(カレンダー!K18,"yyyy年m月")=TEXT($K$10,"yyyy年m月"),INDEX(横カレンダー!$C$4:$IV$13,MATCH($B$13,横カレンダー!$B$4:$B$13,0),MATCH(カレンダー!K18,横カレンダー!$C$3:$IV$3,0)),"") -> #N/A | L19: =IF(TEXT(カレンダー!L18,"yyyy年m月")=TEXT($K$10,"yyyy年m月"),INDEX(横カレンダー!$C$4:$IV$13,MATCH($B$13,横カレンダー!$B$4:$B$13,0),MATCH(カレンダー!L18,横カレンダー!$C$3:$IV$3,0)),"") -> #N/A | M19: =IF(TEXT(カレンダー!M18,"yyyy年m月")=TEXT($K$10,"yyyy年m月"),INDEX(横カレンダー!$C$4:$IV$13,MATCH($B$13,横カレンダー!$B$4:$B$13,0),MATCH(カレンダー!M18,横カレンダー!$C$3:$IV$3,0)),"") -> #N/A | N19: =IF(TEXT(カレンダー!N18,"yyyy年m月")=TEXT($K$10,"yyyy年m月"),INDEX(横カレンダー!$C$4:$IV$13,MATCH($B$13,横カレンダー!$B$4:$B$13,0),MATCH(カレンダー!N18,横カレンダー!$C$3:$IV$3,0)),"") -> #N/A | O19: =IF(TEXT(カレンダー!O18,"yyyy年m月")=TEXT($K$10,"yyyy年m月"),INDEX(横カレンダー!$C$4:$IV$13,MATCH($B$13,横カレンダー!$B$4:$B$13,0),MATCH(カレンダー!O18,横カレンダー!$C$3:$IV$3,0)),"") -> #N/A | P19: =IF(TEXT(カレンダー!P18,"yyyy年m月")=TEXT($K$10,"yyyy年m月"),INDEX(横カレンダー!$C$4:$IV$13,MATCH($B$13,横カレンダー!$B$4:$B$13,0),MATCH(カレンダー!P18,横カレンダー!$C$3:$IV$3,0)),"") -> #N/A | Q19: =IF(TEXT(カレンダー!Q18,"yyyy年m月")=TEXT($K$10,"yyyy年m月"),INDEX(横カレンダー!$C$4:$IV$13,MATCH($B$13,横カレンダー!$B$4:$B$13,0),MATCH(カレンダー!Q18,横カレンダー!$C$3:$IV$3,0)),"") -> #N/A | S19: =IF(TEXT(カレンダー!S18,"yyyy年m月")=TEXT($S$10,"yyyy年m月"),INDEX(横カレンダー!$C$4:$IV$13,MATCH($B$13,横カレンダー!$B$4:$B$13,0),MATCH(カレンダー!S18,横カレンダー!$C$3:$IV$3,0)),"") -> #N/A | T19: =IF(TEXT(カレンダー!T18,"yyyy年m月")=TEXT($S$10,"yyyy年m月"),INDEX(横カレンダー!$C$4:$IV$13,MATCH($B$13,横カレンダー!$B$4:$B$13,0),MATCH(カレンダー!T18,横カレンダー!$C$3:$IV$3,0)),"") -> #N/A | U19: =IF(TEXT(カレンダー!U18,"yyyy年m月")=TEXT($S$10,"yyyy年m月"),INDEX(横カレンダー!$C$4:$IV$13,MATCH($B$13,横カレンダー!$B$4:$B$13,0),MATCH(カレンダー!U18,横カレンダー!$C$3:$IV$3,0)),"") -> #N/A | V19: =IF(TEXT(カレンダー!V18,"yyyy年m月")=TEXT($S$10,"yyyy年m月"),INDEX(横カレンダー!$C$4:$IV$13,MATCH($B$13,横カレンダー!$B$4:$B$13,0),MATCH(カレンダー!V18,横カレンダー!$C$3:$IV$3,0)),"") -> #N/A | W19: =IF(TEXT(カレンダー!W18,"yyyy年m月")=TEXT($S$10,"yyyy年m月"),INDEX(横カレンダー!$C$4:$IV$13,MATCH($B$13,横カレンダー!$B$4:$B$13,0),MATCH(カレンダー!W18,横カレンダー!$C$3:$IV$3,0)),"") -> #N/A | X19: =IF(TEXT(カレンダー!X18,"yyyy年m月")=TEXT($S$10,"yyyy年m月"),INDEX(横カレンダー!$C$4:$IV$13,MATCH($B$13,横カレンダー!$B$4:$B$13,0),MATCH(カレンダー!X18,横カレンダー!$C$3:$IV$3,0)),"") -> #N/A | Y19: =IF(TEXT(カレンダー!Y18,"yyyy年m月")=TEXT($S$10,"yyyy年m月"),INDEX(横カレンダー!$C$4:$IV$13,MATCH($B$13,横カレンダー!$B$4:$B$13,0),MATCH(カレンダー!Y18,横カレンダー!$C$3:$IV$3,0)),"") -> #N/A
A20: 8 | C20: =$C$10-WEEKDAY($C$10)+29 -> 45893 | D20: =$C$10-WEEKDAY($C$10)+30 -> 45894 | E20: =$C$10-WEEKDAY($C$10)+31 -> 45895 | F20: =$C$10-WEEKDAY($C$10)+32 -> 45896 | G20: =$C$10-WEEKDAY($C$10)+33 -> 45897 | H20: =$C$10-WEEKDAY($C$10)+34 -> 45898 | I20: =$C$10-WEEKDAY($C$10)+35 -> 45899 | K20: =$K$10-WEEKDAY($K$10)+29 -> 45928 | L20: =$K$10-WEEKDAY($K$10)+30 -> 45929 | M20: =$K$10-WEEKDAY($K$10)+31 -> 45930 | N20: =$K$10-WEEKDAY($K$10)+32 -> 45931 | O20: =$K$10-WEEKDAY($K$10)+33 -> 45932 | P20: =$K$10-WEEKDAY($K$10)+34 -> 45933 | Q20: =$K$10-WEEKDAY($K$10)+35 -> 45934 | S20: =$S$10-WEEKDAY($S$10)+29 -> 45956 | T20: =$S$10-WEEKDAY($S$10)+30 -> 45957 | U20: =$S$10-WEEKDAY($S$10)+31 -> 45958 | V20: =$S$10-WEEKDAY($S$10)+32 -> 45959 | W20: =$S$10-WEEKDAY($S$10)+33 -> 45960 | X20: =$S$10-WEEKDAY($S$10)+34 -> 45961 | Y20: =$S$10-WEEKDAY($S$10)+35 -> 45962
A21: 14 | C21: =IF(TEXT(カレンダー!C20,"yyyy年m月")=TEXT($C$10,"yyyy年m月"),INDEX(横カレンダー!$C$4:$IV$13,MATCH($B$13,横カレンダー!$B$4:$B$13,0),MATCH(カレンダー!C20,横カレンダー!$C$3:$IV$3,0)),"") -> #N/A | D21: =IF(TEXT(カレンダー!D20,"yyyy年m月")=TEXT($C$10,"yyyy年m月"),INDEX(横カレンダー!$C$4:$IV$13,MATCH($B$13,横カレンダー!$B$4:$B$13,0),MATCH(カレンダー!D20,横カレンダー!$C$3:$IV$3,0)),"") -> #N/A | E21: =IF(TEXT(カレンダー!E20,"yyyy年m月")=TEXT($C$10,"yyyy年m月"),INDEX(横カレンダー!$C$4:$IV$13,MATCH($B$13,横カレンダー!$B$4:$B$13,0),MATCH(カレンダー!E20,横カレンダー!$C$3:$IV$3,0)),"") -> #N/A | F21: =IF(TEXT(カレンダー!F20,"yyyy年m月")=TEXT($C$10,"yyyy年m月"),INDEX(横カレンダー!$C$4:$IV$13,MATCH($B$13,横カレンダー!$B$4:$B$13,0),MATCH(カレンダー!F20,横カレンダー!$C$3:$IV$3,0)),"") -> #N/A | G21: =IF(TEXT(カレンダー!G20,"yyyy年m月")=TEXT($C$10,"yyyy年m月"),INDEX(横カレンダー!$C$4:$IV$13,MATCH($B$13,横カレンダー!$B$4:$B$13,0),MATCH(カレンダー!G20,横カレンダー!$C$3:$IV$3,0)),"") -> #N/A | H21: =IF(TEXT(カレンダー!H20,"yyyy年m月")=TEXT($C$10,"yyyy年m月"),INDEX(横カレンダー!$C$4:$IV$13,MATCH($B$13,横カレンダー!$B$4:$B$13,0),MATCH(カレンダー!H20,横カレンダー!$C$3:$IV$3,0)),"") -> #N/A | I21: =IF(TEXT(カレンダー!I20,"yyyy年m月")=TEXT($C$10,"yyyy年m月"),INDEX(横カレンダー!$C$4:$IV$13,MATCH($B$13,横カレンダー!$B$4:$B$13,0),MATCH(カレンダー!I20,横カレンダー!$C$3:$IV$3,0)),"") -> #N/A | K21: =IF(TEXT(カレンダー!K20,"yyyy年m月")=TEXT($K$10,"yyyy年m月"),INDEX(横カレンダー!$C$4:$IV$13,MATCH($B$13,横カレンダー!$B$4:$B$13,0),MATCH(カレンダー!K20,横カレンダー!$C$3:$IV$3,0)),"") -> #N/A | L21: =IF(TEXT(カレンダー!L20,"yyyy年m月")=TEXT($K$10,"yyyy年m月"),INDEX(横カレンダー!$C$4:$IV$13,MATCH($B$13,横カレンダー!$B$4:$B$13,0),MATCH(カレンダー!L20,横カレンダー!$C$3:$IV$3,0)),"") -> #N/A | M21: =IF(TEXT(カレンダー!M20,"yyyy年m月")=TEXT($K$10,"yyyy年m月"),INDEX(横カレンダー!$C$4:$IV$13,MATCH($B$13,横カレンダー!$B$4:$B$13,0),MATCH(カレンダー!M20,横カレンダー!$C$3:$IV$3,0)),"") -> #N/A | N21: =IF(TEXT(カレンダー!N20,"yyyy年m月")=TEXT($K$10,"yyyy年m月"),INDEX(横カレンダー!$C$4:$IV$13,MATCH($B$13,横カレンダー!$B$4:$B$13,0),MATCH(カレンダー!N20,横カレンダー!$C$3:$IV$3,0)),"") | O21: =IF(TEXT(カレンダー!O20,"yyyy年m月")=TEXT($K$10,"yyyy年m月"),INDEX(横カレンダー!$C$4:$IV$13,MATCH($B$13,横カレンダー!$B$4:$B$13,0),MATCH(カレンダー!O20,横カレンダー!$C$3:$IV$3,0)),"") | P21: =IF(TEXT(カレンダー!P20,"yyyy年m月")=TEXT($K$10,"yyyy年m月"),INDEX(横カレンダー!$C$4:$IV$13,MATCH($B$13,横カレンダー!$B$4:$B$13,0),MATCH(カレンダー!P20,横カレンダー!$C$3:$IV$3,0)),"") | Q21: =IF(TEXT(カレンダー!Q20,"yyyy年m月")=TEXT($K$10,"yyyy年m月"),INDEX(横カレンダー!$C$4:$IV$13,MATCH($B$13,横カレンダー!$B$4:$B$13,0),MATCH(カレンダー!Q20,横カレンダー!$C$3:$IV$3,0)),"") | S21: =IF(TEXT(カレンダー!S20,"yyyy年m月")=TEXT($S$10,"yyyy年m月"),INDEX(横カレンダー!$C$4:$IV$13,MATCH($B$13,横カレンダー!$B$4:$B$13,0),MATCH(カレンダー!S20,横カレンダー!$C$3:$IV$3,0)),"") -> #N/A | T21: =IF(TEXT(カレンダー!T20,"yyyy年m月")=TEXT($S$10,"yyyy年m月"),INDEX(横カレンダー!$C$4:$IV$13,MATCH($B$13,横カレンダー!$B$4:$B$13,0),MATCH(カレンダー!T20,横カレンダー!$C$3:$IV$3,0)),"") -> #N/A | U21: =IF(TEXT(カレンダー!U20,"yyyy年m月")=TEXT($S$10,"yyyy年m月"),INDEX(横カレンダー!$C$4:$IV$13,MATCH($B$13,横カレンダー!$B$4:$B$13,0),MATCH(カレンダー!U20,横カレンダー!$C$3:$IV$3,0)),"") -> #N/A | V21: =IF(TEXT(カレンダー!V20,"yyyy年m月")=TEXT($S$10,"yyyy年m月"),INDEX(横カレンダー!$C$4:$IV$13,MATCH($B$13,横カレンダー!$B$4:$B$13,0),MATCH(カレンダー!V20,横カレンダー!$C$3:$IV$3,0)),"") -> #N/A | W21: =IF(TEXT(カレンダー!W20,"yyyy年m月")=TEXT($S$10,"yyyy年m月"),INDEX(横カレンダー!$C$4:$IV$13,MATCH($B$13,横カレンダー!$B$4:$B$13,0),MATCH(カレンダー!W20,横カレンダー!$C$3:$IV$3,0)),"") -> #N/A | X21: =IF(TEXT(カレンダー!X20,"yyyy年m月")=TEXT($S$10,"yyyy年m月"),INDEX(横カレンダー!$C$4:$IV$13,MATCH($B$13,横カレンダー!$B$4:$B$13,0),MATCH(カレンダー!X20,横カレンダー!$C$3:$IV$3,0)),"") -> #N/A | Y21: =IF(TEXT(カレンダー!Y20,"yyyy年m月")=TEXT($S$10,"yyyy年m月"),INDEX(横カレンダー!$C$4:$IV$13,MATCH($B$13,横カレンダー!$B$4:$B$13,0),MATCH(カレンダー!Y20,横カレンダー!$C$3:$IV$3,0)),"")
C22: =$C$10-WEEKDAY($C$10)+36 -> 45900 | D22: =$C$10-WEEKDAY($C$10)+37 -> 45901 | E22: =$C$10-WEEKDAY($C$10)+38 -> 45902 | F22: =$C$10-WEEKDAY($C$10)+39 -> 45903 | G22: =$C$10-WEEKDAY($C$10)+40 -> 45904 | H22: =$C$10-WEEKDAY($C$10)+41 -> 45905 | I22: =$C$10-WEEKDAY($C$10)+42 -> 45906 | K22: =$K$10-WEEKDAY($K$10)+36 -> 45935 | L22: =$K$10-WEEKDAY($K$10)+37 -> 45936 | M22: =$K$10-WEEKDAY($K$10)+38 -> 45937 | N22: =$K$10-WEEKDAY($K$10)+39 -> 45938 | O22: =$K$10-WEEKDAY($K$10)+40 -> 45939 | P22: =$K$10-WEEKDAY($K$10)+41 -> 45940 | Q22: =$K$10-WEEKDAY($K$10)+42 -> 45941 | S22: =$S$10-WEEKDAY($S$10)+36 -> 45963 | T22: =$S$10-WEEKDAY($S$10)+37 -> 45964 | U22: =$S$10-WEEKDAY($S$10)+38 -> 45965 | V22: =$S$10-WEEKDAY($S$10)+39 -> 45966 | W22: =$S$10-WEEKDAY($S$10)+40 -> 45967 | X22: =$S$10-WEEKDAY($S$10)+41 -> 45968 | Y22: =$S$10-WEEKDAY($S$10)+42 -> 45969
C23: =IF(TEXT(カレンダー!C22,"yyyy年m月")=TEXT($C$10,"yyyy年m月"),INDEX(横カレンダー!$C$4:$IV$13,MATCH($B$13,横カレンダー!$B$4:$B$13,0),MATCH(カレンダー!C22,横カレンダー!$C$3:$IV$3,0)),"") -> #N/A | D23: =IF(TEXT(カレンダー!D22,"yyyy年m月")=TEXT($C$10,"yyyy年m月"),INDEX(横カレンダー!$C$4:$IV$13,MATCH($B$13,横カレンダー!$B$4:$B$13,0),MATCH(カレンダー!D22,横カレンダー!$C$3:$IV$3,0)),"") | E23: =IF(TEXT(カレンダー!E22,"yyyy年m月")=TEXT($C$10,"yyyy年m月"),INDEX(横カレンダー!$C$4:$IV$13,MATCH($B$13,横カレンダー!$B$4:$B$13,0),MATCH(カレンダー!E22,横カレンダー!$C$3:$IV$3,0)),"") | F23: =IF(TEXT(カレンダー!F22,"yyyy年m月")=TEXT($C$10,"yyyy年m月"),INDEX(横カレンダー!$C$4:$IV$13,MATCH($B$13,横カレンダー!$B$4:$B$13,0),MATCH(カレンダー!F22,横カレンダー!$C$3:$IV$3,0)),"") | G23: =IF(TEXT(カレンダー!G22,"yyyy年m月")=TEXT($C$10,"yyyy年m月"),INDEX(横カレンダー!$C$4:$IV$13,MATCH($B$13,横カレンダー!$B$4:$B$13,0),MATCH(カレンダー!G22,横カレンダー!$C$3:$IV$3,0)),"") | H23: =IF(TEXT(カレンダー!H22,"yyyy年m月")=TEXT($C$10,"yyyy年m月"),INDEX(横カレンダー!$C$4:$IV$13,MATCH($B$13,横カレンダー!$B$4:$B$13,0),MATCH(カレンダー!H22,横カレンダー!$C$3:$IV$3,0)),"") | I23: =IF(TEXT(カレンダー!I22,"yyyy年m月")=TEXT($C$10,"yyyy年m月"),INDEX(横カレンダー!$C$4:$IV$13,MATCH($B$13,横カレンダー!$B$4:$B$13,0),MATCH(カレンダー!I22,横カレンダー!$C$3:$IV$3,0)),"") | K23: =IF(TEXT(カレンダー!K22,"yyyy年m月")=TEXT($K$10,"yyyy年m月"),INDEX(横カレンダー!$C$4:$IV$13,MATCH($B$13,横カレンダー!$B$4:$B$13,0),MATCH(カレンダー!K22,横カレンダー!$C$3:$IV$3,0)),"") | L23: =IF(TEXT(カレンダー!L22,"yyyy年m月")=TEXT($K$10,"yyyy年m月"),INDEX(横カレンダー!$C$4:$IV$13,MATCH($B$13,横カレンダー!$B$4:$B$13,0),MATCH(カレンダー!L22,横カレンダー!$C$3:$IV$3,0)),"") | M23: =IF(TEXT(カレンダー!M22,"yyyy年m月")=TEXT($K$10,"yyyy年m月"),INDEX(横カレンダー!$C$4:$IV$13,MATCH($B$13,横カレンダー!$B$4:$B$13,0),MATCH(カレンダー!M22,横カレンダー!$C$3:$IV$3,0)),"") | N23: =IF(TEXT(カレンダー!N22,"yyyy年m月")=TEXT($K$10,"yyyy年m月"),INDEX(横カレンダー!$C$4:$IV$13,MATCH($B$13,横カレンダー!$B$4:$B$13,0),MATCH(カレンダー!N22,横カレンダー!$C$3:$IV$3,0)),"") | O23: =IF(TEXT(カレンダー!O22,"yyyy年m月")=TEXT($K$10,"yyyy年m月"),INDEX(横カレンダー!$C$4:$IV$13,MATCH($B$13,横カレンダー!$B$4:$B$13,0),MATCH(カレンダー!O22,横カレンダー!$C$3:$IV$3,0)),"") | P23: =IF(TEXT(カレンダー!P22,"yyyy年m月")=TEXT($K$10,"yyyy年m月"),INDEX(横カレンダー!$C$4:$IV$13,MATCH($B$13,横カレンダー!$B$4:$B$13,0),MATCH(カレンダー!P22,横カレンダー!$C$3:$IV$3,0)),"") | Q23: =IF(TEXT(カレンダー!Q22,"yyyy年m月")=TEXT($K$10,"yyyy年m月"),INDEX(横カレンダー!$C$4:$IV$13,MATCH($B$13,横カレンダー!$B$4:$B$13,0),MATCH(カレンダー!Q22,横カレンダー!$C$3:$IV$3,0)),"") | S23: =IF(TEXT(カレンダー!S22,"yyyy年m月")=TEXT($S$10,"yyyy年m月"),INDEX(横カレンダー!$C$4:$IV$13,MATCH($B$13,横カレンダー!$B$4:$B$13,0),MATCH(カレンダー!S22,横カレンダー!$C$3:$IV$3,0)),"") | T23: =IF(TEXT(カレンダー!T22,"yyyy年m月")=TEXT($S$10,"yyyy年m月"),INDEX(横カレンダー!$C$4:$IV$13,MATCH($B$13,横カレンダー!$B$4:$B$13,0),MATCH(カレンダー!T22,横カレンダー!$C$3:$IV$3,0)),"") | U23: =IF(TEXT(カレンダー!U22,"yyyy年m月")=TEXT($S$10,"yyyy年m月"),INDEX(横カレンダー!$C$4:$IV$13,MATCH($B$13,横カレンダー!$B$4:$B$13,0),MATCH(カレンダー!U22,横カレンダー!$C$3:$IV$3,0)),"") | V23: =IF(TEXT(カレンダー!V22,"yyyy年m月")=TEXT($S$10,"yyyy年m月"),INDEX(横カレンダー!$C$4:$IV$13,MATCH($B$13,横カレンダー!$B$4:$B$13,0),MATCH(カレンダー!V22,横カレンダー!$C$3:$IV$3,0)),"") | W23: =IF(TEXT(カレンダー!W22,"yyyy年m月")=TEXT($S$10,"yyyy年m月"),INDEX(横カレンダー!$C$4:$IV$13,MATCH($B$13,横カレンダー!$B$4:$B$13,0),MATCH(カレンダー!W22,横カレンダー!$C$3:$IV$3,0)),"") | X23: =IF(TEXT(カレンダー!X22,"yyyy年m月")=TEXT($S$10,"yyyy年m月"),INDEX(横カレンダー!$C$4:$IV$13,MATCH($B$13,横カレンダー!$B$4:$B$13,0),MATCH(カレンダー!X22,横カレンダー!$C$3:$IV$3,0)),"") | Y23: =IF(TEXT(カレンダー!Y22,"yyyy年m月")=TEXT($S$10,"yyyy年m月"),INDEX(横カレンダー!$C$4:$IV$13,MATCH($B$13,横カレンダー!$B$4:$B$13,0),MATCH(カレンダー!Y22,横カレンダー!$C$3:$IV$3,0)),"")
C26: =TEXT(EDATE(C10,3),"yyyy年m月") -> 2025年11月 | K26: =TEXT(EDATE(K10,3),"yyyy年m月") -> 2025年12月 | S26: =TEXT(EDATE(S10,3),"yyyy年m月") -> 2026年1月
C27: 日 | D27: 月 | E27: 火 | F27: 水 | G27: 木 | H27: 金 | I27: 土 | K27: 日 | L27: 月 | M27: 火 | N27: 水 | O27: 木 | P27: 金 | Q27: 土 | S27: 日 | T27: 月 | U27: 火 | V27: 水 | W27: 木 | X27: 金 | Y27: 土
C28: =$C$26-WEEKDAY($C$26)+1 -> 45956 | D28: =$C$26-WEEKDAY($C$26)+2 -> 45957 | E28: =$C$26-WEEKDAY($C$26)+3 -> 45958 | F28: =$C$26-WEEKDAY($C$26)+4 -> 45959 | G28: =$C$26-WEEKDAY($C$26)+5 -> 45960 | H28: =$C$26-WEEKDAY($C$26)+6 -> 45961 | I28: =$C$26-WEEKDAY($C$26)+7 -> 45962 | K28: =$K$26-WEEKDAY($K$26)+1 -> 45991 | L28: =$K$26-WEEKDAY($K$26)+2 -> 45992 | M28: =$K$26-WEEKDAY($K$26)+3 -> 45993 | N28: =$K$26-WEEKDAY($K$26)+4 -> 45994 | O28: =$K$26-WEEKDAY($K$26)+5 -> 45995 | P28: =$K$26-WEEKDAY($K$26)+6 -> 45996 | Q28: =$K$26-WEEKDAY($K$26)+7 -> 45997 | S28: =$S$26-WEEKDAY($S$26)+1 -> 46019 | T28: =$S$26-WEEKDAY($S$26)+2 -> 46020 | U28: =$S$26-WEEKDAY($S$26)+3 -> 46021 | V28: =$S$26-WEEKDAY($S$26)+4 -> 46022 | W28: =$S$26-WEEKDAY($S$26)+5 -> 46023 | X28: =$S$26-WEEKDAY($S$26)+6 -> 46024 | Y28: =$S$26-WEEKDAY($S$26)+7 -> 46025
C29: =IF(TEXT(カレンダー!C28,"yyyy年m月")=TEXT($C$26,"yyyy年m月"),INDEX(横カレンダー!$C$4:$IV$13,MATCH($B$13,横カレンダー!$B$4:$B$13,0),MATCH(カレンダー!C28,横カレンダー!$C$3:$IV$3,0)),"") | D29: =IF(TEXT(カレンダー!D28,"yyyy年m月")=TEXT($C$26,"yyyy年m月"),INDEX(横カレンダー!$C$4:$IV$13,MATCH($B$13,横カレンダー!$B$4:$B$13,0),MATCH(カレンダー!D28,横カレンダー!$C$3:$IV$3,0)),"") | E29: =IF(TEXT(カレンダー!E28,"yyyy年m月")=TEXT($C$26,"yyyy年m月"),INDEX(横カレンダー!$C$4:$IV$13,MATCH($B$13,横カレンダー!$B$4:$B$13,0),MATCH(カレンダー!E28,横カレンダー!$C$3:$IV$3,0)),"") | F29: =IF(TEXT(カレンダー!F28,"yyyy年m月")=TEXT($C$26,"yyyy年m月"),INDEX(横カレンダー!$C$4:$IV$13,MATCH($B$13,横カレンダー!$B$4:$B$13,0),MATCH(カレンダー!F28,横カレンダー!$C$3:$IV$3,0)),"") | G29: =IF(TEXT(カレンダー!G28,"yyyy年m月")=TEXT($C$26,"yyyy年m月"),INDEX(横カレンダー!$C$4:$IV$13,MATCH($B$13,横カレンダー!$B$4:$B$13,0),MATCH(カレンダー!G28,横カレンダー!$C$3:$IV$3,0)),"") | H29: =IF(TEXT(カレンダー!H28,"yyyy年m月")=TEXT($C$26,"yyyy年m月"),INDEX(横カレンダー!$C$4:$IV$13,MATCH($B$13,横カレンダー!$B$4:$B$13,0),MATCH(カレンダー!H28,横カレンダー!$C$3:$IV$3,0)),"") | I29: =IF(TEXT(カレンダー!I28,"yyyy年m月")=TEXT($C$26,"yyyy年m月"),INDEX(横カレンダー!$C$4:$IV$13,MATCH($B$13,横カレンダー!$B$4:$B$13,0),MATCH(カレンダー!I28,横カレンダー!$C$3:$IV$3,0)),"") -> 0 | K29: =IF(TEXT(カレンダー!K28,"yyyy年m月")=TEXT($K$26,"yyyy年m月"),INDEX(横カレンダー!$C$4:$IV$13,MATCH($B$13,横カレンダー!$B$4:$B$13,0),MATCH(カレンダー!K28,横カレンダー!$C$3:$IV$3,0)),"") | L29: =IF(TEXT(カレンダー!L28,"yyyy年m月")=TEXT($K$26,"yyyy年m月"),INDEX(横カレンダー!$C$4:$IV$13,MATCH($B$13,横カレンダー!$B$4:$B$13,0),MATCH(カレンダー!L28,横カレンダー!$C$3:$IV$3,0)),"") -> D | M29: =IF(TEXT(カレンダー!M28,"yyyy年m月")=TEXT($K$26,"yyyy年m月"),INDEX(横カレンダー!$C$4:$IV$13,MATCH($B$13,横カレンダー!$B$4:$B$13,0),MATCH(カレンダー!M28,横カレンダー!$C$3:$IV$3,0)),"") -> D | N29: =IF(TEXT(カレンダー!N28,"yyyy年m月")=TEXT($K$26,"yyyy年m月"),INDEX(横カレンダー!$C$4:$IV$13,MATCH($B$13,横カレンダー!$B$4:$B$13,0),MATCH(カレンダー!N28,横カレンダー!$C$3:$IV$3,0)),"") -> E | O29: =IF(TEXT(カレンダー!O28,"yyyy年m月")=TEXT($K$26,"yyyy年m月"),INDEX(横カレンダー!$C$4:$IV$13,MATCH($B$13,横カレンダー!$B$4:$B$13,0),MATCH(カレンダー!O28,横カレンダー!$C$3:$IV$3,0)),"") -> D | P29: =IF(TEXT(カレンダー!P28,"yyyy年m月")=TEXT($K$26,"yyyy年m月"),INDEX(横カレンダー!$C$4:$IV$13,MATCH($B$13,横カレンダー!$B$4:$B$13,0),MATCH(カレンダー!P28,横カレンダー!$C$3:$IV$3,0)),"") -> F | Q29: =IF(TEXT(カレンダー!Q28,"yyyy年m月")=TEXT($K$26,"yyyy年m月"),INDEX(横カレンダー!$C$4:$IV$13,MATCH($B$13,横カレンダー!$B$4:$B$13,0),MATCH(カレンダー!Q28,横カレンダー!$C$3:$IV$3,0)),"") -> I | S29: =IF(TEXT(カレンダー!S28,"yyyy年m月")=TEXT($S$26,"yyyy年m月"),INDEX(横カレンダー!$C$4:$IV$13,MATCH($B$13,横カレンダー!$B$4:$B$13,0),MATCH(カレンダー!S28,横カレンダー!$C$3:$IV$3,0)),"") | T29: =IF(TEXT(カレンダー!T28,"yyyy年m月")=TEXT($S$26,"yyyy年m月"),INDEX(横カレンダー!$C$4:$IV$13,MATCH($B$13,横カレンダー!$B$4:$B$13,0),MATCH(カレンダー!T28,横カレンダー!$C$3:$IV$3,0)),"") | U29: =IF(TEXT(カレンダー!U28,"yyyy年m月")=TEXT($S$26,"yyyy年m月"),INDEX(横カレンダー!$C$4:$IV$13,MATCH($B$13,横カレンダー!$B$4:$B$13,0),MATCH(カレンダー!U28,横カレンダー!$C$3:$IV$3,0)),"") | V29: =IF(TEXT(カレンダー!V28,"yyyy年m月")=TEXT($S$26,"yyyy年m月"),INDEX(横カレンダー!$C$4:$IV$13,MATCH($B$13,横カレンダー!$B$4:$B$13,0),MATCH(カレンダー!V28,横カレンダー!$C$3:$IV$3,0)),"") | W29: =IF(TEXT(カレンダー!W28,"yyyy年m月")=TEXT($S$26,"yyyy年m月"),INDEX(横カレンダー!$C$4:$IV$13,MATCH($B$13,横カレンダー!$B$4:$B$13,0),MATCH(カレンダー!W28,横カレンダー!$C$3:$IV$3,0)),"") -> Y | X29: =IF(TEXT(カレンダー!X28,"yyyy年m月")=TEXT($S$26,"yyyy年m月"),INDEX(横カレンダー!$C$4:$IV$13,MATCH($B$13,横カレンダー!$B$4:$B$13,0),MATCH(カレンダー!X28,横カレンダー!$C$3:$IV$3,0)),"") -> Y | Y29: =IF(TEXT(カレンダー!Y28,"yyyy年m月")=TEXT($S$26,"yyyy年m月"),INDEX(横カレンダー!$C$4:$IV$13,MATCH($B$13,横カレンダー!$B$4:$B$13,0),MATCH(カレンダー!Y28,横カレンダー!$C$3:$IV$3,0)),"") -> U
C30: =$C$26-WEEKDAY($C$26)+8 -> 45963 | D30: =$C$26-WEEKDAY($C$26)+9 -> 45964 | E30: =$C$26-WEEKDAY($C$26)+10 -> 45965 | F30: =$C$26-WEEKDAY($C$26)+11 -> 45966 | G30: =$C$26-WEEKDAY($C$26)+12 -> 45967 | H30: =$C$26-WEEKDAY($C$26)+13 -> 45968 | I30: =$C$26-WEEKDAY($C$26)+14 -> 45969 | K30: =$K$26-WEEKDAY($K$26)+8 -> 45998 | L30: =$K$26-WEEKDAY($K$26)+9 -> 45999 | M30: =$K$26-WEEKDAY($K$26)+10 -> 46000 | N30: =$K$26-WEEKDAY($K$26)+11 -> 46001 | O30: =$K$26-WEEKDAY($K$26)+12 -> 46002 | P30: =$K$26-WEEKDAY($K$26)+13 -> 46003 | Q30: =$K$26-WEEKDAY($K$26)+14 -> 46004 | S30: =$S$26-WEEKDAY($S$26)+8 -> 46026 | T30: =$S$26-WEEKDAY($S$26)+9 -> 46027 | U30: =$S$26-WEEKDAY($S$26)+10 -> 46028 | V30: =$S$26-WEEKDAY($S$26)+11 -> 46029 | W30: =$S$26-WEEKDAY($S$26)+12 -> 46030 | X30: =$S$26-WEEKDAY($S$26)+13 -> 46031 | Y30: =$S$26-WEEKDAY($S$26)+14 -> 46032
C31: =IF(TEXT(カレンダー!C30,"yyyy年m月")=TEXT($C$26,"yyyy年m月"),INDEX(横カレンダー!$C$4:$IV$13,MATCH($B$13,横カレンダー!$B$4:$B$13,0),MATCH(カレンダー!C30,横カレンダー!$C$3:$IV$3,0)),"") -> 0 | D31: =IF(TEXT(カレンダー!D30,"yyyy年m月")=TEXT($C$26,"yyyy年m月"),INDEX(横カレンダー!$C$4:$IV$13,MATCH($B$13,横カレンダー!$B$4:$B$13,0),MATCH(カレンダー!D30,横カレンダー!$C$3:$IV$3,0)),"") -> 0 | E31: =IF(TEXT(カレンダー!E30,"yyyy年m月")=TEXT($C$26,"yyyy年m月"),INDEX(横カレンダー!$C$4:$IV$13,MATCH($B$13,横カレンダー!$B$4:$B$13,0),MATCH(カレンダー!E30,横カレンダー!$C$3:$IV$3,0)),"") -> 0 | F31: =IF(TEXT(カレンダー!F30,"yyyy年m月")=TEXT($C$26,"yyyy年m月"),INDEX(横カレンダー!$C$4:$IV$13,MATCH($B$13,横カレンダー!$B$4:$B$13,0),MATCH(カレンダー!F30,横カレンダー!$C$3:$IV$3,0)),"") -> 0 | G31: =IF(TEXT(カレンダー!G30,"yyyy年m月")=TEXT($C$26,"yyyy年m月"),INDEX(横カレンダー!$C$4:$IV$13,MATCH($B$13,横カレンダー!$B$4:$B$13,0),MATCH(カレンダー!G30,横カレンダー!$C$3:$IV$3,0)),"") -> H | H31: =IF(TEXT(カレンダー!H30,"yyyy年m月")=TEXT($C$26,"yyyy年m月"),INDEX(横カレンダー!$C$4:$IV$13,MATCH($B$13,横カレンダー!$B$4:$B$13,0),MATCH(カレンダー!H30,横カレンダー!$C$3:$IV$3,0)),"") -> G | I31: =IF(TEXT(カレンダー!I30,"yyyy年m月")=TEXT($C$26,"yyyy年m月"),INDEX(横カレンダー!$C$4:$IV$13,MATCH($B$13,横カレンダー!$B$4:$B$13,0),MATCH(カレンダー!I30,横カレンダー!$C$3:$IV$3,0)),"") -> P | K31: =IF(TEXT(カレンダー!K30,"yyyy年m月")=TEXT($K$26,"yyyy年m月"),INDEX(横カレンダー!$C$4:$IV$13,MATCH($B$13,横カレンダー!$B$4:$B$13,0),MATCH(カレンダー!K30,横カレンダー!$C$3:$IV$3,0)),"") -> E | L31: =IF(TEXT(カレンダー!L30,"yyyy年m月")=TEXT($K$26,"yyyy年m月"),INDEX(横カレンダー!$C$4:$IV$13,MATCH($B$13,横カレンダー!$B$4:$B$13,0),MATCH(カレンダー!L30,横カレンダー!$C$3:$IV$3,0)),"") -> C | M31: =IF(TEXT(カレンダー!M30,"yyyy年m月")=TEXT($K$26,"yyyy年m月"),INDEX(横カレンダー!$C$4:$IV$13,MATCH($B$13,横カレンダー!$B$4:$B$13,0),MATCH(カレンダー!M30,横カレンダー!$C$3:$IV$3,0)),"") -> C | N31: =IF(TEXT(カレンダー!N30,"yyyy年m月")=TEXT($K$26,"yyyy年m月"),INDEX(横カレンダー!$C$4:$IV$13,MATCH($B$13,横カレンダー!$B$4:$B$13,0),MATCH(カレンダー!N30,横カレンダー!$C$3:$IV$3,0)),"") -> D | O31: =IF(TEXT(カレンダー!O30,"yyyy年m月")=TEXT($K$26,"yyyy年m月"),INDEX(横カレンダー!$C$4:$IV$13,MATCH($B$13,横カレンダー!$B$4:$B$13,0),MATCH(カレンダー!O30,横カレンダー!$C$3:$IV$3,0)),"") -> D | P31: =IF(TEXT(カレンダー!P30,"yyyy年m月")=TEXT($K$26,"yyyy年m月"),INDEX(横カレンダー!$C$4:$IV$13,MATCH($B$13,横カレンダー!$B$4:$B$13,0),MATCH(カレンダー!P30,横カレンダー!$C$3:$IV$3,0)),"") -> I | Q31: =IF(TEXT(カレンダー!Q30,"yyyy年m月")=TEXT($K$26,"yyyy年m月"),INDEX(横カレンダー!$C$4:$IV$13,MATCH($B$13,横カレンダー!$B$4:$B$13,0),MATCH(カレンダー!Q30,横カレンダー!$C$3:$IV$3,0)),"") -> K | S31: =IF(TEXT(カレンダー!S30,"yyyy年m月")=TEXT($S$26,"yyyy年m月"),INDEX(横カレンダー!$C$4:$IV$13,MATCH($B$13,横カレンダー!$B$4:$B$13,0),MATCH(カレンダー!S30,横カレンダー!$C$3:$IV$3,0)),"") -> H | T31: =IF(TEXT(カレンダー!T30,"yyyy年m月")=TEXT($S$26,"yyyy年m月"),INDEX(横カレンダー!$C$4:$IV$13,MATCH($B$13,横カレンダー!$B$4:$B$13,0),MATCH(カレンダー!T30,横カレンダー!$C$3:$IV$3,0)),"") -> H | U31: =IF(TEXT(カレンダー!U30,"yyyy年m月")=TEXT($S$26,"yyyy年m月"),INDEX(横カレンダー!$C$4:$IV$13,MATCH($B$13,横カレンダー!$B$4:$B$13,0),MATCH(カレンダー!U30,横カレンダー!$C$3:$IV$3,0)),"") -> E | V31: =IF(TEXT(カレンダー!V30,"yyyy年m月")=TEXT($S$26,"yyyy年m月"),INDEX(横カレンダー!$C$4:$IV$13,MATCH($B$13,横カレンダー!$B$4:$B$13,0),MATCH(カレンダー!V30,横カレンダー!$C$3:$IV$3,0)),"") -> B | W31: =IF(TEXT(カレンダー!W30,"yyyy年m月")=TEXT($S$26,"yyyy年m月"),INDEX(横カレンダー!$C$4:$IV$13,MATCH($B$13,横カレンダー!$B$4:$B$13,0),MATCH(カレンダー!W30,横カレンダー!$C$3:$IV$3,0)),"") -> C | X31: =IF(TEXT(カレンダー!X30,"yyyy年m月")=TEXT($S$26,"yyyy年m月"),INDEX(横カレンダー!$C$4:$IV$13,MATCH($B$13,横カレンダー!$B$4:$B$13,0),MATCH(カレンダー!X30,横カレンダー!$C$3:$IV$3,0)),"") -> G | Y31: =IF(TEXT(カレンダー!Y30,"yyyy年m月")=TEXT($S$26,"yyyy年m月"),INDEX(横カレンダー!$C$4:$IV$13,MATCH($B$13,横カレンダー!$B$4:$B$13,0),MATCH(カレンダー!Y30,横カレンダー!$C$3:$IV$3,0)),"") -> I
C32: =$C$26-WEEKDAY($C$26)+15 -> 45970 | D32: =$C$26-WEEKDAY($C$26)+16 -> 45971 | E32: =$C$26-WEEKDAY($C$26)+17 -> 45972 | F32: =$C$26-WEEKDAY($C$26)+18 -> 45973 | G32: =$C$26-WEEKDAY($C$26)+19 -> 45974 | H32: =$C$26-WEEKDAY($C$26)+20 -> 45975 | I32: =$C$26-WEEKDAY($C$26)+21 -> 45976 | K32: =$K$26-WEEKDAY($K$26)+15 -> 46005 | L32: =$K$26-WEEKDAY($K$26)+16 -> 46006 | M32: =$K$26-WEEKDAY($K$26)+17 -> 46007 | N32: =$K$26-WEEKDAY($K$26)+18 -> 46008 | O32: =$K$26-WEEKDAY($K$26)+19 -> 46009 | P32: =$K$26-WEEKDAY($K$26)+20 -> 46010 | Q32: =$K$26-WEEKDAY($K$26)+21 -> 46011 | S32: =$S$26-WEEKDAY($S$26)+15 -> 46033 | T32: =$S$26-WEEKDAY($S$26)+16 -> 46034 | U32: =$S$26-WEEKDAY($S$26)+17 -> 46035 | V32: =$S$26-WEEKDAY($S$26)+18 -> 46036 | W32: =$S$26-WEEKDAY($S$26)+19 -> 46037 | X32: =$S$26-WEEKDAY($S$26)+20 -> 46038 | Y32: =$S$26-WEEKDAY($S$26)+21 -> 46039
C33: =IF(TEXT(カレンダー!C32,"yyyy年m月")=TEXT($C$26,"yyyy年m月"),INDEX(横カレンダー!$C$4:$IV$13,MATCH($B$13,横カレンダー!$B$4:$B$13,0),MATCH(カレンダー!C32,横カレンダー!$C$3:$IV$3,0)),"") -> I | D33: =IF(TEXT(カレンダー!D32,"yyyy年m月")=TEXT($C$26,"yyyy年m月"),INDEX(横カレンダー!$C$4:$IV$13,MATCH($B$13,横カレンダー!$B$4:$B$13,0),MATCH(カレンダー!D32,横カレンダー!$C$3:$IV$3,0)),"") -> K | E33: =IF(TEXT(カレンダー!E32,"yyyy年m月")=TEXT($C$26,"yyyy年m月"),INDEX(横カレンダー!$C$4:$IV$13,MATCH($B$13,横カレンダー!$B$4:$B$13,0),MATCH(カレンダー!E32,横カレンダー!$C$3:$IV$3,0)),"") -> H | F33: =IF(TEXT(カレンダー!F32,"yyyy年m月")=TEXT($C$26,"yyyy年m月"),INDEX(横カレンダー!$C$4:$IV$13,MATCH($B$13,横カレンダー!$B$4:$B$13,0),MATCH(カレンダー!F32,横カレンダー!$C$3:$IV$3,0)),"") -> E | G33: =IF(TEXT(カレンダー!G32,"yyyy年m月")=TEXT($C$26,"yyyy年m月"),INDEX(横カレンダー!$C$4:$IV$13,MATCH($B$13,横カレンダー!$B$4:$B$13,0),MATCH(カレンダー!G32,横カレンダー!$C$3:$IV$3,0)),"") -> H | H33: =IF(TEXT(カレンダー!H32,"yyyy年m月")=TEXT($C$26,"yyyy年m月"),INDEX(横カレンダー!$C$4:$IV$13,MATCH($B$13,横カレンダー!$B$4:$B$13,0),MATCH(カレンダー!H32,横カレンダー!$C$3:$IV$3,0)),"") -> M | I33: =IF(TEXT(カレンダー!I32,"yyyy年m月")=TEXT($C$26,"yyyy年m月"),INDEX(横カレンダー!$C$4:$IV$13,MATCH($B$13,横カレンダー!$B$4:$B$13,0),MATCH(カレンダー!I32,横カレンダー!$C$3:$IV$3,0)),"") -> L | K33: =IF(TEXT(カレンダー!K32,"yyyy年m月")=TEXT($K$26,"yyyy年m月"),INDEX(横カレンダー!$C$4:$IV$13,MATCH($B$13,横カレンダー!$B$4:$B$13,0),MATCH(カレンダー!K32,横カレンダー!$C$3:$IV$3,0)),"") -> B | L33: =IF(TEXT(カレンダー!L32,"yyyy年m月")=TEXT($K$26,"yyyy年m月"),INDEX(横カレンダー!$C$4:$IV$13,MATCH($B$13,横カレンダー!$B$4:$B$13,0),MATCH(カレンダー!L32,横カレンダー!$C$3:$IV$3,0)),"") -> B | M33: =IF(TEXT(カレンダー!M32,"yyyy年m月")=TEXT($K$26,"yyyy年m月"),INDEX(横カレンダー!$C$4:$IV$13,MATCH($B$13,横カレンダー!$B$4:$B$13,0),MATCH(カレンダー!M32,横カレンダー!$C$3:$IV$3,0)),"") -> B | N33: =IF(TEXT(カレンダー!N32,"yyyy年m月")=TEXT($K$26,"yyyy年m月"),INDEX(横カレンダー!$C$4:$IV$13,MATCH($B$13,横カレンダー!$B$4:$B$13,0),MATCH(カレンダー!N32,横カレンダー!$C$3:$IV$3,0)),"") -> E | O33: =IF(TEXT(カレンダー!O32,"yyyy年m月")=TEXT($K$26,"yyyy年m月"),INDEX(横カレンダー!$C$4:$IV$13,MATCH($B$13,横カレンダー!$B$4:$B$13,0),MATCH(カレンダー!O32,横カレンダー!$C$3:$IV$3,0)),"") -> G | P33: =IF(TEXT(カレンダー!P32,"yyyy年m月")=TEXT($K$26,"yyyy年m月"),INDEX(横カレンダー!$C$4:$IV$13,MATCH($B$13,横カレンダー!$B$4:$B$13,0),MATCH(カレンダー!P32,横カレンダー!$C$3:$IV$3,0)),"") -> E | Q33: =IF(TEXT(カレンダー!Q32,"yyyy年m月")=TEXT($K$26,"yyyy年m月"),INDEX(横カレンダー!$C$4:$IV$13,MATCH($B$13,横カレンダー!$B$4:$B$13,0),MATCH(カレンダー!Q32,横カレンダー!$C$3:$IV$3,0)),"") -> I | S33: =IF(TEXT(カレンダー!S32,"yyyy年m月")=TEXT($S$26,"yyyy年m月"),INDEX(横カレンダー!$C$4:$IV$13,MATCH($B$13,横カレンダー!$B$4:$B$13,0),MATCH(カレンダー!S32,横カレンダー!$C$3:$IV$3,0)),"") -> I | T33: =IF(TEXT(カレンダー!T32,"yyyy年m月")=TEXT($S$26,"yyyy年m月"),INDEX(横カレンダー!$C$4:$IV$13,MATCH($B$13,横カレンダー!$B$4:$B$13,0),MATCH(カレンダー!T32,横カレンダー!$C$3:$IV$3,0)),"") -> C | U33: =IF(TEXT(カレンダー!U32,"yyyy年m月")=TEXT($S$26,"yyyy年m月"),INDEX(横カレンダー!$C$4:$IV$13,MATCH($B$13,横カレンダー!$B$4:$B$13,0),MATCH(カレンダー!U32,横カレンダー!$C$3:$IV$3,0)),"") -> C | V33: =IF(TEXT(カレンダー!V32,"yyyy年m月")=TEXT($S$26,"yyyy年m月"),INDEX(横カレンダー!$C$4:$IV$13,MATCH($B$13,横カレンダー!$B$4:$B$13,0),MATCH(カレンダー!V32,横カレンダー!$C$3:$IV$3,0)),"") -> C | W33: =IF(TEXT(カレンダー!W32,"yyyy年m月")=TEXT($S$26,"yyyy年m月"),INDEX(横カレンダー!$C$4:$IV$13,MATCH($B$13,横カレンダー!$B$4:$B$13,0),MATCH(カレンダー!W32,横カレンダー!$C$3:$IV$3,0)),"") -> C | X33: =IF(TEXT(カレンダー!X32,"yyyy年m月")=TEXT($S$26,"yyyy年m月"),INDEX(横カレンダー!$C$4:$IV$13,MATCH($B$13,横カレンダー!$B$4:$B$13,0),MATCH(カレンダー!X32,横カレンダー!$C$3:$IV$3,0)),"") -> G | Y33: =IF(TEXT(カレンダー!Y32,"yyyy年m月")=TEXT($S$26,"yyyy年m月"),INDEX(横カレンダー!$C$4:$IV$13,MATCH($B$13,横カレンダー!$B$4:$B$13,0),MATCH(カレンダー!Y32,横カレンダー!$C$3:$IV$3,0)),"") -> I
C34: =$C$26-WEEKDAY($C$26)+22 -> 45977 | D34: =$C$26-WEEKDAY($C$26)+23 -> 45978 | E34: =$C$26-WEEKDAY($C$26)+24 -> 45979 | F34: =$C$26-WEEKDAY($C$26)+25 -> 45980 | G34: =$C$26-WEEKDAY($C$26)+26 -> 45981 | H34: =$C$26-WEEKDAY($C$26)+27 -> 45982 | I34: =$C$26-WEEKDAY($C$26)+28 -> 45983 | K34: =$K$26-WEEKDAY($K$26)+22 -> 46012 | L34: =$K$26-WEEKDAY($K$26)+23 -> 46013 | M34: =$K$26-WEEKDAY($K$26)+24 -> 46014 | N34: =$K$26-WEEKDAY($K$26)+25 -> 46015 | O34: =$K$26-WEEKDAY($K$26)+26 -> 46016 | P34: =$K$26-WEEKDAY($K$26)+27 -> 46017 | Q34: =$K$26-WEEKDAY($K$26)+28 -> 46018 | S34: =$S$26-WEEKDAY($S$26)+22 -> 46040 | T34: =$S$26-WEEKDAY($S$26)+23 -> 46041 | U34: =$S$26-WEEKDAY($S$26)+24 -> 46042 | V34: =$S$26-WEEKDAY($S$26)+25 -> 46043 | W34: =$S$26-WEEKDAY($S$26)+26 -> 46044 | X34: =$S$26-WEEKDAY($S$26)+27 -> 46045 | Y34: =$S$26-WEEKDAY($S$26)+28 -> 46046
C35: =IF(TEXT(カレンダー!C34,"yyyy年m月")=TEXT($C$26,"yyyy年m月"),INDEX(横カレンダー!$C$4:$IV$13,MATCH($B$13,横カレンダー!$B$4:$B$13,0),MATCH(カレンダー!C34,横カレンダー!$C$3:$IV$3,0)),"") -> I | D35: =IF(TEXT(カレンダー!D34,"yyyy年m月")=TEXT($C$26,"yyyy年m月"),INDEX(横カレンダー!$C$4:$IV$13,MATCH($B$13,横カレンダー!$B$4:$B$13,0),MATCH(カレンダー!D34,横カレンダー!$C$3:$IV$3,0)),"") -> E | E35: =IF(TEXT(カレンダー!E34,"yyyy年m月")=TEXT($C$26,"yyyy年m月"),INDEX(横カレンダー!$C$4:$IV$13,MATCH($B$13,横カレンダー!$B$4:$B$13,0),MATCH(カレンダー!E34,横カレンダー!$C$3:$IV$3,0)),"") -> E | F35: =IF(TEXT(カレンダー!F34,"yyyy年m月")=TEXT($C$26,"yyyy年m月"),INDEX(横カレンダー!$C$4:$IV$13,MATCH($B$13,横カレンダー!$B$4:$B$13,0),MATCH(カレンダー!F34,横カレンダー!$C$3:$IV$3,0)),"") -> E | G35: =IF(TEXT(カレンダー!G34,"yyyy年m月")=TEXT($C$26,"yyyy年m月"),INDEX(横カレンダー!$C$4:$IV$13,MATCH($B$13,横カレンダー!$B$4:$B$13,0),MATCH(カレンダー!G34,横カレンダー!$C$3:$IV$3,0)),"") -> F | H35: =IF(TEXT(カレンダー!H34,"yyyy年m月")=TEXT($C$26,"yyyy年m月"),INDEX(横カレンダー!$C$4:$IV$13,MATCH($B$13,横カレンダー!$B$4:$B$13,0),MATCH(カレンダー!H34,横カレンダー!$C$3:$IV$3,0)),"") -> N | I35: =IF(TEXT(カレンダー!I34,"yyyy年m月")=TEXT($C$26,"yyyy年m月"),INDEX(横カレンダー!$C$4:$IV$13,MATCH($B$13,横カレンダー!$B$4:$B$13,0),MATCH(カレンダー!I34,横カレンダー!$C$3:$IV$3,0)),"") -> Q | K35: =IF(TEXT(カレンダー!K34,"yyyy年m月")=TEXT($K$26,"yyyy年m月"),INDEX(横カレンダー!$C$4:$IV$13,MATCH($B$13,横カレンダー!$B$4:$B$13,0),MATCH(カレンダー!K34,横カレンダー!$C$3:$IV$3,0)),"") -> H | L35: =IF(TEXT(カレンダー!L34,"yyyy年m月")=TEXT($K$26,"yyyy年m月"),INDEX(横カレンダー!$C$4:$IV$13,MATCH($B$13,横カレンダー!$B$4:$B$13,0),MATCH(カレンダー!L34,横カレンダー!$C$3:$IV$3,0)),"") -> H | M35: =IF(TEXT(カレンダー!M34,"yyyy年m月")=TEXT($K$26,"yyyy年m月"),INDEX(横カレンダー!$C$4:$IV$13,MATCH($B$13,横カレンダー!$B$4:$B$13,0),MATCH(カレンダー!M34,横カレンダー!$C$3:$IV$3,0)),"") -> G | N35: =IF(TEXT(カレンダー!N34,"yyyy年m月")=TEXT($K$26,"yyyy年m月"),INDEX(横カレンダー!$C$4:$IV$13,MATCH($B$13,横カレンダー!$B$4:$B$13,0),MATCH(カレンダー!N34,横カレンダー!$C$3:$IV$3,0)),"") -> I | O35: =IF(TEXT(カレンダー!O34,"yyyy年m月")=TEXT($K$26,"yyyy年m月"),INDEX(横カレンダー!$C$4:$IV$13,MATCH($B$13,横カレンダー!$B$4:$B$13,0),MATCH(カレンダー!O34,横カレンダー!$C$3:$IV$3,0)),"") -> M | P35: =IF(TEXT(カレンダー!P34,"yyyy年m月")=TEXT($K$26,"yyyy年m月"),INDEX(横カレンダー!$C$4:$IV$13,MATCH($B$13,横カレンダー!$B$4:$B$13,0),MATCH(カレンダー!P34,横カレンダー!$C$3:$IV$3,0)),"") -> T | Q35: =IF(TEXT(カレンダー!Q34,"yyyy年m月")=TEXT($K$26,"yyyy年m月"),INDEX(横カレンダー!$C$4:$IV$13,MATCH($B$13,横カレンダー!$B$4:$B$13,0),MATCH(カレンダー!Q34,横カレンダー!$C$3:$IV$3,0)),"") -> T | S35: =IF(TEXT(カレンダー!S34,"yyyy年m月")=TEXT($S$26,"yyyy年m月"),INDEX(横カレンダー!$C$4:$IV$13,MATCH($B$13,横カレンダー!$B$4:$B$13,0),MATCH(カレンダー!S34,横カレンダー!$C$3:$IV$3,0)),"") -> B | T35: =IF(TEXT(カレンダー!T34,"yyyy年m月")=TEXT($S$26,"yyyy年m月"),INDEX(横カレンダー!$C$4:$IV$13,MATCH($B$13,横カレンダー!$B$4:$B$13,0),MATCH(カレンダー!T34,横カレンダー!$C$3:$IV$3,0)),"") -> C | U35: =IF(TEXT(カレンダー!U34,"yyyy年m月")=TEXT($S$26,"yyyy年m月"),INDEX(横カレンダー!$C$4:$IV$13,MATCH($B$13,横カレンダー!$B$4:$B$13,0),MATCH(カレンダー!U34,横カレンダー!$C$3:$IV$3,0)),"") -> B | V35: =IF(TEXT(カレンダー!V34,"yyyy年m月")=TEXT($S$26,"yyyy年m月"),INDEX(横カレンダー!$C$4:$IV$13,MATCH($B$13,横カレンダー!$B$4:$B$13,0),MATCH(カレンダー!V34,横カレンダー!$C$3:$IV$3,0)),"") -> B | W35: =IF(TEXT(カレンダー!W34,"yyyy年m月")=TEXT($S$26,"yyyy年m月"),INDEX(横カレンダー!$C$4:$IV$13,MATCH($B$13,横カレンダー!$B$4:$B$13,0),MATCH(カレンダー!W34,横カレンダー!$C$3:$IV$3,0)),"") -> C | X35: =IF(TEXT(カレンダー!X34,"yyyy年m月")=TEXT($S$26,"yyyy年m月"),INDEX(横カレンダー!$C$4:$IV$13,MATCH($B$13,横カレンダー!$B$4:$B$13,0),MATCH(カレンダー!X34,横カレンダー!$C$3:$IV$3,0)),"") -> G | Y35: =IF(TEXT(カレンダー!Y34,"yyyy年m月")=TEXT($S$26,"yyyy年m月"),INDEX(横カレンダー!$C$4:$IV$13,MATCH($B$13,横カレンダー!$B$4:$B$13,0),MATCH(カレンダー!Y34,横カレンダー!$C$3:$IV$3,0)),"") -> I
C36: =$C$26-WEEKDAY($C$26)+29 -> 45984 | D36: =$C$26-WEEKDAY($C$26)+30 -> 45985 | E36: =$C$26-WEEKDAY($C$26)+31 -> 45986 | F36: =$C$26-WEEKDAY($C$26)+32 -> 45987 | G36: =$C$26-WEEKDAY($C$26)+33 -> 45988 | H36: =$C$26-WEEKDAY($C$26)+34 -> 45989 | I36: =$C$26-WEEKDAY($C$26)+35 -> 45990 | K36: =$K$26-WEEKDAY($K$26)+29 -> 46019 | L36: =$K$26-WEEKDAY($K$26)+30 -> 46020 | M36: =$K$26-WEEKDAY($K$26)+31 -> 46021 | N36: =$K$26-WEEKDAY($K$26)+32 -> 46022 | O36: =$K$26-WEEKDAY($K$26)+33 -> 46023 | P36: =$K$26-WEEKDAY($K$26)+34 -> 46024 | Q36: =$K$26-WEEKDAY($K$26)+35 -> 46025 | S36: =$S$26-WEEKDAY($S$26)+29 -> 46047 | T36: =$S$26-WEEKDAY($S$26)+30 -> 46048 | U36: =$S$26-WEEKDAY($S$26)+31 -> 46049 | V36: =$S$26-WEEKDAY($S$26)+32 -> 46050 | W36: =$S$26-WEEKDAY($S$26)+33 -> 46051 | X36: =$S$26-WEEKDAY($S$26)+34 -> 46052 | Y36: =$S$26-WEEKDAY($S$26)+35 -> 46053
C37: =IF(TEXT(カレンダー!C36,"yyyy年m月")=TEXT($C$26,"yyyy年m月"),INDEX(横カレンダー!$C$4:$IV$13,MATCH($B$13,横カレンダー!$B$4:$B$13,0),MATCH(カレンダー!C36,横カレンダー!$C$3:$IV$3,0)),"") -> H | D37: =IF(TEXT(カレンダー!D36,"yyyy年m月")=TEXT($C$26,"yyyy年m月"),INDEX(横カレンダー!$C$4:$IV$13,MATCH($B$13,横カレンダー!$B$4:$B$13,0),MATCH(カレンダー!D36,横カレンダー!$C$3:$IV$3,0)),"") -> H | E37: =IF(TEXT(カレンダー!E36,"yyyy年m月")=TEXT($C$26,"yyyy年m月"),INDEX(横カレンダー!$C$4:$IV$13,MATCH($B$13,横カレンダー!$B$4:$B$13,0),MATCH(カレンダー!E36,横カレンダー!$C$3:$IV$3,0)),"") -> G | F37: =IF(TEXT(カレンダー!F36,"yyyy年m月")=TEXT($C$26,"yyyy年m月"),INDEX(横カレンダー!$C$4:$IV$13,MATCH($B$13,横カレンダー!$B$4:$B$13,0),MATCH(カレンダー!F36,横カレンダー!$C$3:$IV$3,0)),"") -> C | G37: =IF(TEXT(カレンダー!G36,"yyyy年m月")=TEXT($C$26,"yyyy年m月"),INDEX(横カレンダー!$C$4:$IV$13,MATCH($B$13,横カレンダー!$B$4:$B$13,0),MATCH(カレンダー!G36,横カレンダー!$C$3:$IV$3,0)),"") -> C | H37: =IF(TEXT(カレンダー!H36,"yyyy年m月")=TEXT($C$26,"yyyy年m月"),INDEX(横カレンダー!$C$4:$IV$13,MATCH($B$13,横カレンダー!$B$4:$B$13,0),MATCH(カレンダー!H36,横カレンダー!$C$3:$IV$3,0)),"") -> I | I37: =IF(TEXT(カレンダー!I36,"yyyy年m月")=TEXT($C$26,"yyyy年m月"),INDEX(横カレンダー!$C$4:$IV$13,MATCH($B$13,横カレンダー!$B$4:$B$13,0),MATCH(カレンダー!I36,横カレンダー!$C$3:$IV$3,0)),"") -> J | K37: =IF(TEXT(カレンダー!K36,"yyyy年m月")=TEXT($K$26,"yyyy年m月"),INDEX(横カレンダー!$C$4:$IV$13,MATCH($B$13,横カレンダー!$B$4:$B$13,0),MATCH(カレンダー!K36,横カレンダー!$C$3:$IV$3,0)),"") -> W | L37: =IF(TEXT(カレンダー!L36,"yyyy年m月")=TEXT($K$26,"yyyy年m月"),INDEX(横カレンダー!$C$4:$IV$13,MATCH($B$13,横カレンダー!$B$4:$B$13,0),MATCH(カレンダー!L36,横カレンダー!$C$3:$IV$3,0)),"") -> W | M37: =IF(TEXT(カレンダー!M36,"yyyy年m月")=TEXT($K$26,"yyyy年m月"),INDEX(横カレンダー!$C$4:$IV$13,MATCH($B$13,横カレンダー!$B$4:$B$13,0),MATCH(カレンダー!M36,横カレンダー!$C$3:$IV$3,0)),"") -> X | N37: =IF(TEXT(カレンダー!N36,"yyyy年m月")=TEXT($K$26,"yyyy年m月"),INDEX(横カレンダー!$C$4:$IV$13,MATCH($B$13,横カレンダー!$B$4:$B$13,0),MATCH(カレンダー!N36,横カレンダー!$C$3:$IV$3,0)),"") -> X | O37: =IF(TEXT(カレンダー!O36,"yyyy年m月")=TEXT($K$26,"yyyy年m月"),INDEX(横カレンダー!$C$4:$IV$13,MATCH($B$13,横カレンダー!$B$4:$B$13,0),MATCH(カレンダー!O36,横カレンダー!$C$3:$IV$3,0)),"") | P37: =IF(TEXT(カレンダー!P36,"yyyy年m月")=TEXT($K$26,"yyyy年m月"),INDEX(横カレンダー!$C$4:$IV$13,MATCH($B$13,横カレンダー!$B$4:$B$13,0),MATCH(カレンダー!P36,横カレンダー!$C$3:$IV$3,0)),"") | Q37: =IF(TEXT(カレンダー!Q36,"yyyy年m月")=TEXT($K$26,"yyyy年m月"),INDEX(横カレンダー!$C$4:$IV$13,MATCH($B$13,横カレンダー!$B$4:$B$13,0),MATCH(カレンダー!Q36,横カレンダー!$C$3:$IV$3,0)),"") | S37: =IF(TEXT(カレンダー!S36,"yyyy年m月")=TEXT($S$26,"yyyy年m月"),INDEX(横カレンダー!$C$4:$IV$13,MATCH($B$13,横カレンダー!$B$4:$B$13,0),MATCH(カレンダー!S36,横カレンダー!$C$3:$IV$3,0)),"") -> C | T37: =IF(TEXT(カレンダー!T36,"yyyy年m月")=TEXT($S$26,"yyyy年m月"),INDEX(横カレンダー!$C$4:$IV$13,MATCH($B$13,横カレンダー!$B$4:$B$13,0),MATCH(カレンダー!T36,横カレンダー!$C$3:$IV$3,0)),"") -> C | U37: =IF(TEXT(カレンダー!U36,"yyyy年m月")=TEXT($S$26,"yyyy年m月"),INDEX(横カレンダー!$C$4:$IV$13,MATCH($B$13,横カレンダー!$B$4:$B$13,0),MATCH(カレンダー!U36,横カレンダー!$C$3:$IV$3,0)),"") -> C | V37: =IF(TEXT(カレンダー!V36,"yyyy年m月")=TEXT($S$26,"yyyy年m月"),INDEX(横カレンダー!$C$4:$IV$13,MATCH($B$13,横カレンダー!$B$4:$B$13,0),MATCH(カレンダー!V36,横カレンダー!$C$3:$IV$3,0)),"") -> C | W37: =IF(TEXT(カレンダー!W36,"yyyy年m月")=TEXT($S$26,"yyyy年m月"),INDEX(横カレンダー!$C$4:$IV$13,MATCH($B$13,横カレンダー!$B$4:$B$13,0),MATCH(カレンダー!W36,横カレンダー!$C$3:$IV$3,0)),"") -> C | X37: =IF(TEXT(カレンダー!X36,"yyyy年m月")=TEXT($S$26,"yyyy年m月"),INDEX(横カレンダー!$C$4:$IV$13,MATCH($B$13,横カレンダー!$B$4:$B$13,0),MATCH(カレンダー!X36,横カレンダー!$C$3:$IV$3,0)),"") -> G | Y37: =IF(TEXT(カレンダー!Y36,"yyyy年m月")=TEXT($S$26,"yyyy年m月"),INDEX(横カレンダー!$C$4:$IV$13,MATCH($B$13,横カレンダー!$B$4:$B$13,0),MATCH(カレンダー!Y36,横カレンダー!$C$3:$IV$3,0)),"") -> I
C38: =$C$26-WEEKDAY($C$26)+36 -> 45991 | D38: =$C$26-WEEKDAY($C$26)+37 -> 45992 | E38: =$C$26-WEEKDAY($C$26)+38 -> 45993 | F38: =$C$26-WEEKDAY($C$26)+39 -> 45994 | G38: =$C$26-WEEKDAY($C$26)+40 -> 45995 | H38: =$C$26-WEEKDAY($C$26)+41 -> 45996 | I38: =$C$26-WEEKDAY($C$26)+42 -> 45997 | K38: =$K$26-WEEKDAY($K$26)+36 -> 46026 | L38: =$K$26-WEEKDAY($K$26)+37 -> 46027 | M38: =$K$26-WEEKDAY($K$26)+38 -> 46028 | N38: =$K$26-WEEKDAY($K$26)+39 -> 46029 | O38: =$K$26-WEEKDAY($K$26)+40 -> 46030 | P38: =$K$26-WEEKDAY($K$26)+41 -> 46031 | Q38: =$K$26-WEEKDAY($K$26)+42 -> 46032 | S38: =$S$26-WEEKDAY($S$26)+36 -> 46054 | T38: =$S$26-WEEKDAY($S$26)+37 -> 46055 | U38: =$S$26-WEEKDAY($S$26)+38 -> 46056 | V38: =$S$26-WEEKDAY($S$26)+39 -> 46057 | W38: =$S$26-WEEKDAY($S$26)+40 -> 46058 | X38: =$S$26-WEEKDAY($S$26)+41 -> 46059 | Y38: =$S$26-WEEKDAY($S$26)+42 -> 46060
C39: =IF(TEXT(カレンダー!C38,"yyyy年m月")=TEXT($C$26,"yyyy年m月"),INDEX(横カレンダー!$C$4:$IV$13,MATCH($B$13,横カレンダー!$B$4:$B$13,0),MATCH(カレンダー!C38,横カレンダー!$C$3:$IV$3,0)),"") -> D | D39: =IF(TEXT(カレンダー!D38,"yyyy年m月")=TEXT($C$26,"yyyy年m月"),INDEX(横カレンダー!$C$4:$IV$13,MATCH($B$13,横カレンダー!$B$4:$B$13,0),MATCH(カレンダー!D38,横カレンダー!$C$3:$IV$3,0)),"") | E39: =IF(TEXT(カレンダー!E38,"yyyy年m月")=TEXT($C$26,"yyyy年m月"),INDEX(横カレンダー!$C$4:$IV$13,MATCH($B$13,横カレンダー!$B$4:$B$13,0),MATCH(カレンダー!E38,横カレンダー!$C$3:$IV$3,0)),"") | F39: =IF(TEXT(カレンダー!F38,"yyyy年m月")=TEXT($C$26,"yyyy年m月"),INDEX(横カレンダー!$C$4:$IV$13,MATCH($B$13,横カレンダー!$B$4:$B$13,0),MATCH(カレンダー!F38,横カレンダー!$C$3:$IV$3,0)),"") | G39: =IF(TEXT(カレンダー!G38,"yyyy年m月")=TEXT($C$26,"yyyy年m月"),INDEX(横カレンダー!$C$4:$IV$13,MATCH($B$13,横カレンダー!$B$4:$B$13,0),MATCH(カレンダー!G38,横カレンダー!$C$3:$IV$3,0)),"") | H39: =IF(TEXT(カレンダー!H38,"yyyy年m月")=TEXT($C$26,"yyyy年m月"),INDEX(横カレンダー!$C$4:$IV$13,MATCH($B$13,横カレンダー!$B$4:$B$13,0),MATCH(カレンダー!H38,横カレンダー!$C$3:$IV$3,0)),"") | I39: =IF(TEXT(カレンダー!I38,"yyyy年m月")=TEXT($C$26,"yyyy年m月"),INDEX(横カレンダー!$C$4:$IV$13,MATCH($B$13,横カレンダー!$B$4:$B$13,0),MATCH(カレンダー!I38,横カレンダー!$C$3:$IV$3,0)),"") | K39: =IF(TEXT(カレンダー!K38,"yyyy年m月")=TEXT($K$26,"yyyy年m月"),INDEX(横カレンダー!$C$4:$IV$13,MATCH($B$13,横カレンダー!$B$4:$B$13,0),MATCH(カレンダー!K38,横カレンダー!$C$3:$IV$3,0)),"") | L39: =IF(TEXT(カレンダー!L38,"yyyy年m月")=TEXT($K$26,"yyyy年m月"),INDEX(横カレンダー!$C$4:$IV$13,MATCH($B$13,横カレンダー!$B$4:$B$13,0),MATCH(カレンダー!L38,横カレンダー!$C$3:$IV$3,0)),"") | M39: =IF(TEXT(カレンダー!M38,"yyyy年m月")=TEXT($K$26,"yyyy年m月"),INDEX(横カレンダー!$C$4:$IV$13,MATCH($B$13,横カレンダー!$B$4:$B$13,0),MATCH(カレンダー!M38,横カレンダー!$C$3:$IV$3,0)),"") | N39: =IF(TEXT(カレンダー!N38,"yyyy年m月")=TEXT($K$26,"yyyy年m月"),INDEX(横カレンダー!$C$4:$IV$13,MATCH($B$13,横カレンダー!$B$4:$B$13,0),MATCH(カレンダー!N38,横カレンダー!$C$3:$IV$3,0)),"") | O39: =IF(TEXT(カレンダー!O38,"yyyy年m月")=TEXT($K$26,"yyyy年m月"),INDEX(横カレンダー!$C$4:$IV$13,MATCH($B$13,横カレンダー!$B$4:$B$13,0),MATCH(カレンダー!O38,横カレンダー!$C$3:$IV$3,0)),"") | P39: =IF(TEXT(カレンダー!P38,"yyyy年m月")=TEXT($K$26,"yyyy年m月"),INDEX(横カレンダー!$C$4:$IV$13,MATCH($B$13,横カレンダー!$B$4:$B$13,0),MATCH(カレンダー!P38,横カレンダー!$C$3:$IV$3,0)),"") | Q39: =IF(TEXT(カレンダー!Q38,"yyyy年m月")=TEXT($K$26,"yyyy年m月"),INDEX(横カレンダー!$C$4:$IV$13,MATCH($B$13,横カレンダー!$B$4:$B$13,0),MATCH(カレンダー!Q38,横カレンダー!$C$3:$IV$3,0)),"") | S39: =IF(TEXT(カレンダー!S38,"yyyy年m月")=TEXT($S$26,"yyyy年m月"),INDEX(横カレンダー!$C$4:$IV$13,MATCH($B$13,横カレンダー!$B$4:$B$13,0),MATCH(カレンダー!S38,横カレンダー!$C$3:$IV$3,0)),"") | T39: =IF(TEXT(カレンダー!T38,"yyyy年m月")=TEXT($S$26,"yyyy年m月"),INDEX(横カレンダー!$C$4:$IV$13,MATCH($B$13,横カレンダー!$B$4:$B$13,0),MATCH(カレンダー!T38,横カレンダー!$C$3:$IV$3,0)),"") | U39: =IF(TEXT(カレンダー!U38,"yyyy年m月")=TEXT($S$26,"yyyy年m月"),INDEX(横カレンダー!$C$4:$IV$13,MATCH($B$13,横カレンダー!$B$4:$B$13,0),MATCH(カレンダー!U38,横カレンダー!$C$3:$IV$3,0)),"") | V39: =IF(TEXT(カレンダー!V38,"yyyy年m月")=TEXT($S$26,"yyyy年m月"),INDEX(横カレンダー!$C$4:$IV$13,MATCH($B$13,横カレンダー!$B$4:$B$13,0),MATCH(カレンダー!V38,横カレンダー!$C$3:$IV$3,0)),"") | W39: =IF(TEXT(カレンダー!W38,"yyyy年m月")=TEXT($S$26,"yyyy年m月"),INDEX(横カレンダー!$C$4:$IV$13,MATCH($B$13,横カレンダー!$B$4:$B$13,0),MATCH(カレンダー!W38,横カレンダー!$C$3:$IV$3,0)),"") | X39: =IF(TEXT(カレンダー!X38,"yyyy年m月")=TEXT($S$26,"yyyy年m月"),INDEX(横カレンダー!$C$4:$IV$13,MATCH($B$13,横カレンダー!$B$4:$B$13,0),MATCH(カレンダー!X38,横カレンダー!$C$3:$IV$3,0)),"") | Y39: =IF(TEXT(カレンダー!Y38,"yyyy年m月")=TEXT($S$26,"yyyy年m月"),INDEX(横カレンダー!$C$4:$IV$13,MATCH($B$13,横カレンダー!$B$4:$B$13,0),MATCH(カレンダー!Y38,横カレンダー!$C$3:$IV$3,0)),"")
C42: =TEXT(EDATE(C26,3),"yyyy年m月") -> 2026年2月 | K42: =TEXT(EDATE(K26,3),"yyyy年m月") -> 2026年3月 | S42: =TEXT(EDATE(S26,3),"yyyy年m月") -> 2026年4月
C43: 日 | D43: 月 | E43: 火 | F43: 水 | G43: 木 | H43: 金 | I43: 土 | K43: 日 | L43: 月 | M43: 火 | N43: 水 | O43: 木 | P43: 金 | Q43: 土 | S43: 日 | T43: 月 | U43: 火 | V43: 水 | W43: 木 | X43: 金 | Y43: 土
C44: =$C$42-WEEKDAY($C$42)+1 -> 46054 | D44: =$C$42-WEEKDAY($C$42)+2 -> 46055 | E44: =$C$42-WEEKDAY($C$42)+3 -> 46056 | F44: =$C$42-WEEKDAY($C$42)+4 -> 46057 | G44: =$C$42-WEEKDAY($C$42)+5 -> 46058 | H44: =$C$42-WEEKDAY($C$42)+6 -> 46059 | I44: =$C$42-WEEKDAY($C$42)+7 -> 46060 | K44: =$K$42-WEEKDAY($K$42)+1 -> 46082 | L44: =$K$42-WEEKDAY($K$42)+2 -> 46083 | M44: =$K$42-WEEKDAY($K$42)+3 -> 46084 | N44: =$K$42-WEEKDAY($K$42)+4 -> 46085 | O44: =$K$42-WEEKDAY($K$42)+5 -> 46086 | P44: =$K$42-WEEKDAY($K$42)+6 -> 46087 | Q44: =$K$42-WEEKDAY($K$42)+7 -> 46088 | S44: =$S$42-WEEKDAY($S$42)+1 -> 46110 | T44: =$S$42-WEEKDAY($S$42)+2 -> 46111 | U44: =$S$42-WEEKDAY($S$42)+3 -> 46112 | V44: =$S$42-WEEKDAY($S$42)+4 -> 46113 | W44: =$S$42-WEEKDAY($S$42)+5 -> 46114 | X44: =$S$42-WEEKDAY($S$42)+6 -> 46115 | Y44: =$S$42-WEEKDAY($S$42)+7 -> 46116
C45: =IF(TEXT(カレンダー!C44,"yyyy年m月")=TEXT($C$42,"yyyy年m月"),INDEX(横カレンダー!$C$4:$IV$13,MATCH($B$13,横カレンダー!$B$4:$B$13,0),MATCH(カレンダー!C44,横カレンダー!$C$3:$IV$3,0)),"") -> H | D45: =IF(TEXT(カレンダー!D44,"yyyy年m月")=TEXT($C$42,"yyyy年m月"),INDEX(横カレンダー!$C$4:$IV$13,MATCH($B$13,横カレンダー!$B$4:$B$13,0),MATCH(カレンダー!D44,横カレンダー!$C$3:$IV$3,0)),"") -> H | E45: =IF(TEXT(カレンダー!E44,"yyyy年m月")=TEXT($C$42,"yyyy年m月"),INDEX(横カレンダー!$C$4:$IV$13,MATCH($B$13,横カレンダー!$B$4:$B$13,0),MATCH(カレンダー!E44,横カレンダー!$C$3:$IV$3,0)),"") -> H | F45: =IF(TEXT(カレンダー!F44,"yyyy年m月")=TEXT($C$42,"yyyy年m月"),INDEX(横カレンダー!$C$4:$IV$13,MATCH($B$13,横カレンダー!$B$4:$B$13,0),MATCH(カレンダー!F44,横カレンダー!$C$3:$IV$3,0)),"") -> H | G45: =IF(TEXT(カレンダー!G44,"yyyy年m月")=TEXT($C$42,"yyyy年m月"),INDEX(横カレンダー!$C$4:$IV$13,MATCH($B$13,横カレンダー!$B$4:$B$13,0),MATCH(カレンダー!G44,横カレンダー!$C$3:$IV$3,0)),"") -> H | H45: =IF(TEXT(カレンダー!H44,"yyyy年m月")=TEXT($C$42,"yyyy年m月"),INDEX(横カレンダー!$C$4:$IV$13,MATCH($B$13,横カレンダー!$B$4:$B$13,0),MATCH(カレンダー!H44,横カレンダー!$C$3:$IV$3,0)),"") -> L | I45: =IF(TEXT(カレンダー!I44,"yyyy年m月")=TEXT($C$42,"yyyy年m月"),INDEX(横カレンダー!$C$4:$IV$13,MATCH($B$13,横カレンダー!$B$4:$B$13,0),MATCH(カレンダー!I44,横カレンダー!$C$3:$IV$3,0)),"") -> N | K45: =IF(TEXT(カレンダー!K44,"yyyy年m月")=TEXT($K$42,"yyyy年m月"),INDEX(横カレンダー!$C$4:$IV$13,MATCH($B$13,横カレンダー!$B$4:$B$13,0),MATCH(カレンダー!K44,横カレンダー!$C$3:$IV$3,0)),"") -> L | L45: =IF(TEXT(カレンダー!L44,"yyyy年m月")=TEXT($K$42,"yyyy年m月"),INDEX(横カレンダー!$C$4:$IV$13,MATCH($B$13,横カレンダー!$B$4:$B$13,0),MATCH(カレンダー!L44,横カレンダー!$C$3:$IV$3,0)),"") -> L | M45: =IF(TEXT(カレンダー!M44,"yyyy年m月")=TEXT($K$42,"yyyy年m月"),INDEX(横カレンダー!$C$4:$IV$13,MATCH($B$13,横カレンダー!$B$4:$B$13,0),MATCH(カレンダー!M44,横カレンダー!$C$3:$IV$3,0)),"") -> L | N45: =IF(TEXT(カレンダー!N44,"yyyy年m月")=TEXT($K$42,"yyyy年m月"),INDEX(横カレンダー!$C$4:$IV$13,MATCH($B$13,横カレンダー!$B$4:$B$13,0),MATCH(カレンダー!N44,横カレンダー!$C$3:$IV$3,0)),"") -> L | O45: =IF(TEXT(カレンダー!O44,"yyyy年m月")=TEXT($K$42,"yyyy年m月"),INDEX(横カレンダー!$C$4:$IV$13,MATCH($B$13,横カレンダー!$B$4:$B$13,0),MATCH(カレンダー!O44,横カレンダー!$C$3:$IV$3,0)),"") -> L | P45: =IF(TEXT(カレンダー!P44,"yyyy年m月")=TEXT($K$42,"yyyy年m月"),INDEX(横カレンダー!$C$4:$IV$13,MATCH($B$13,横カレンダー!$B$4:$B$13,0),MATCH(カレンダー!P44,横カレンダー!$C$3:$IV$3,0)),"") -> P | Q45: =IF(TEXT(カレンダー!Q44,"yyyy年m月")=TEXT($K$42,"yyyy年m月"),INDEX(横カレンダー!$C$4:$IV$13,MATCH($B$13,横カレンダー!$B$4:$B$13,0),MATCH(カレンダー!Q44,横カレンダー!$C$3:$IV$3,0)),"") -> Q | S45: =IF(TEXT(カレンダー!S44,"yyyy年m月")=TEXT($S$42,"yyyy年m月"),INDEX(横カレンダー!$C$4:$IV$13,MATCH($B$13,横カレンダー!$B$4:$B$13,0),MATCH(カレンダー!S44,横カレンダー!$C$3:$IV$3,0)),"") | T45: =IF(TEXT(カレンダー!T44,"yyyy年m月")=TEXT($S$42,"yyyy年m月"),INDEX(横カレンダー!$C$4:$IV$13,MATCH($B$13,横カレンダー!$B$4:$B$13,0),MATCH(カレンダー!T44,横カレンダー!$C$3:$IV$3,0)),"") | U45: =IF(TEXT(カレンダー!U44,"yyyy年m月")=TEXT($S$42,"yyyy年m月"),INDEX(横カレンダー!$C$4:$IV$13,MATCH($B$13,横カレンダー!$B$4:$B$13,0),MATCH(カレンダー!U44,横カレンダー!$C$3:$IV$3,0)),"") | V45: =IF(TEXT(カレンダー!V44,"yyyy年m月")=TEXT($S$42,"yyyy年m月"),INDEX(横カレンダー!$C$4:$IV$13,MATCH($B$13,横カレンダー!$B$4:$B$13,0),MATCH(カレンダー!V44,横カレンダー!$C$3:$IV$3,0)),"") -> K | W45: =IF(TEXT(カレンダー!W44,"yyyy年m月")=TEXT($S$42,"yyyy年m月"),INDEX(横カレンダー!$C$4:$IV$13,MATCH($B$13,横カレンダー!$B$4:$B$13,0),MATCH(カレンダー!W44,横カレンダー!$C$3:$IV$3,0)),"") -> K | X45: =IF(TEXT(カレンダー!X44,"yyyy年m月")=TEXT($S$42,"yyyy年m月"),INDEX(横カレンダー!$C$4:$IV$13,MATCH($B$13,横カレンダー!$B$4:$B$13,0),MATCH(カレンダー!X44,横カレンダー!$C$3:$IV$3,0)),"") -> O | Y45: =IF(TEXT(カレンダー!Y44,"yyyy年m月")=TEXT($S$42,"yyyy年m月"),INDEX(横カレンダー!$C$4:$IV$13,MATCH($B$13,横カレンダー!$B$4:$B$13,0),MATCH(カレンダー!Y44,横カレンダー!$C$3:$IV$3,0)),"") -> Q
C46: =$C$42-WEEKDAY($C$42)+8 -> 46061 | D46: =$C$42-WEEKDAY($C$42)+9 -> 46062 | E46: =$C$42-WEEKDAY($C$42)+10 -> 46063 | F46: =$C$42-WEEKDAY($C$42)+11 -> 46064 | G46: =$C$42-WEEKDAY($C$42)+12 -> 46065 | H46: =$C$42-WEEKDAY($C$42)+13 -> 46066 | I46: =$C$42-WEEKDAY($C$42)+14 -> 46067 | K46: =$K$42-WEEKDAY($K$42)+8 -> 46089 | L46: =$K$42-WEEKDAY($K$42)+9 -> 46090 | M46: =$K$42-WEEKDAY($K$42)+10 -> 46091 | N46: =$K$42-WEEKDAY($K$42)+11 -> 46092 | O46: =$K$42-WEEKDAY($K$42)+12 -> 46093 | P46: =$K$42-WEEKDAY($K$42)+13 -> 46094 | Q46: =$K$42-WEEKDAY($K$42)+14 -> 46095 | S46: =$S$42-WEEKDAY($S$42)+8 -> 46117 | T46: =$S$42-WEEKDAY($S$42)+9 -> 46118 | U46: =$S$42-WEEKDAY($S$42)+10 -> 46119 | V46: =$S$42-WEEKDAY($S$42)+11 -> 46120 | W46: =$S$42-WEEKDAY($S$42)+12 -> 46121 | X46: =$S$42-WEEKDAY($S$42)+13 -> 46122 | Y46: =$S$42-WEEKDAY($S$42)+14 -> 46123
C47: =IF(TEXT(カレンダー!C46,"yyyy年m月")=TEXT($C$42,"yyyy年m月"),INDEX(横カレンダー!$C$4:$IV$13,MATCH($B$13,横カレンダー!$B$4:$B$13,0),MATCH(カレンダー!C46,横カレンダー!$C$3:$IV$3,0)),"") -> H | D47: =IF(TEXT(カレンダー!D46,"yyyy年m月")=TEXT($C$42,"yyyy年m月"),INDEX(横カレンダー!$C$4:$IV$13,MATCH($B$13,横カレンダー!$B$4:$B$13,0),MATCH(カレンダー!D46,横カレンダー!$C$3:$IV$3,0)),"") -> H | E47: =IF(TEXT(カレンダー!E46,"yyyy年m月")=TEXT($C$42,"yyyy年m月"),INDEX(横カレンダー!$C$4:$IV$13,MATCH($B$13,横カレンダー!$B$4:$B$13,0),MATCH(カレンダー!E46,横カレンダー!$C$3:$IV$3,0)),"") -> L | F47: =IF(TEXT(カレンダー!F46,"yyyy年m月")=TEXT($C$42,"yyyy年m月"),INDEX(横カレンダー!$C$4:$IV$13,MATCH($B$13,横カレンダー!$B$4:$B$13,0),MATCH(カレンダー!F46,横カレンダー!$C$3:$IV$3,0)),"") -> L | G47: =IF(TEXT(カレンダー!G46,"yyyy年m月")=TEXT($C$42,"yyyy年m月"),INDEX(横カレンダー!$C$4:$IV$13,MATCH($B$13,横カレンダー!$B$4:$B$13,0),MATCH(カレンダー!G46,横カレンダー!$C$3:$IV$3,0)),"") -> H | H47: =IF(TEXT(カレンダー!H46,"yyyy年m月")=TEXT($C$42,"yyyy年m月"),INDEX(横カレンダー!$C$4:$IV$13,MATCH($B$13,横カレンダー!$B$4:$B$13,0),MATCH(カレンダー!H46,横カレンダー!$C$3:$IV$3,0)),"") -> L | I47: =IF(TEXT(カレンダー!I46,"yyyy年m月")=TEXT($C$42,"yyyy年m月"),INDEX(横カレンダー!$C$4:$IV$13,MATCH($B$13,横カレンダー!$B$4:$B$13,0),MATCH(カレンダー!I46,横カレンダー!$C$3:$IV$3,0)),"") -> N | K47: =IF(TEXT(カレンダー!K46,"yyyy年m月")=TEXT($K$42,"yyyy年m月"),INDEX(横カレンダー!$C$4:$IV$13,MATCH($B$13,横カレンダー!$B$4:$B$13,0),MATCH(カレンダー!K46,横カレンダー!$C$3:$IV$3,0)),"") -> L | L47: =IF(TEXT(カレンダー!L46,"yyyy年m月")=TEXT($K$42,"yyyy年m月"),INDEX(横カレンダー!$C$4:$IV$13,MATCH($B$13,横カレンダー!$B$4:$B$13,0),MATCH(カレンダー!L46,横カレンダー!$C$3:$IV$3,0)),"") -> L | M47: =IF(TEXT(カレンダー!M46,"yyyy年m月")=TEXT($K$42,"yyyy年m月"),INDEX(横カレンダー!$C$4:$IV$13,MATCH($B$13,横カレンダー!$B$4:$B$13,0),MATCH(カレンダー!M46,横カレンダー!$C$3:$IV$3,0)),"") -> L | N47: =IF(TEXT(カレンダー!N46,"yyyy年m月")=TEXT($K$42,"yyyy年m月"),INDEX(横カレンダー!$C$4:$IV$13,MATCH($B$13,横カレンダー!$B$4:$B$13,0),MATCH(カレンダー!N46,横カレンダー!$C$3:$IV$3,0)),"") -> L | O47: =IF(TEXT(カレンダー!O46,"yyyy年m月")=TEXT($K$42,"yyyy年m月"),INDEX(横カレンダー!$C$4:$IV$13,MATCH($B$13,横カレンダー!$B$4:$B$13,0),MATCH(カレンダー!O46,横カレンダー!$C$3:$IV$3,0)),"") -> L | P47: =IF(TEXT(カレンダー!P46,"yyyy年m月")=TEXT($K$42,"yyyy年m月"),INDEX(横カレンダー!$C$4:$IV$13,MATCH($B$13,横カレンダー!$B$4:$B$13,0),MATCH(カレンダー!P46,横カレンダー!$C$3:$IV$3,0)),"") -> P | Q47: =IF(TEXT(カレンダー!Q46,"yyyy年m月")=TEXT($K$42,"yyyy年m月"),INDEX(横カレンダー!$C$4:$IV$13,MATCH($B$13,横カレンダー!$B$4:$B$13,0),MATCH(カレンダー!Q46,横カレンダー!$C$3:$IV$3,0)),"") -> Q | S47: =IF(TEXT(カレンダー!S46,"yyyy年m月")=TEXT($S$42,"yyyy年m月"),INDEX(横カレンダー!$C$4:$IV$13,MATCH($B$13,横カレンダー!$B$4:$B$13,0),MATCH(カレンダー!S46,横カレンダー!$C$3:$IV$3,0)),"") -> K | T47: =IF(TEXT(カレンダー!T46,"yyyy年m月")=TEXT($S$42,"yyyy年m月"),INDEX(横カレンダー!$C$4:$IV$13,MATCH($B$13,横カレンダー!$B$4:$B$13,0),MATCH(カレンダー!T46,横カレンダー!$C$3:$IV$3,0)),"") -> K | U47: =IF(TEXT(カレンダー!U46,"yyyy年m月")=TEXT($S$42,"yyyy年m月"),INDEX(横カレンダー!$C$4:$IV$13,MATCH($B$13,横カレンダー!$B$4:$B$13,0),MATCH(カレンダー!U46,横カレンダー!$C$3:$IV$3,0)),"") -> K | V47: =IF(TEXT(カレンダー!V46,"yyyy年m月")=TEXT($S$42,"yyyy年m月"),INDEX(横カレンダー!$C$4:$IV$13,MATCH($B$13,横カレンダー!$B$4:$B$13,0),MATCH(カレンダー!V46,横カレンダー!$C$3:$IV$3,0)),"") -> K | W47: =IF(TEXT(カレンダー!W46,"yyyy年m月")=TEXT($S$42,"yyyy年m月"),INDEX(横カレンダー!$C$4:$IV$13,MATCH($B$13,横カレンダー!$B$4:$B$13,0),MATCH(カレンダー!W46,横カレンダー!$C$3:$IV$3,0)),"") -> K | X47: =IF(TEXT(カレンダー!X46,"yyyy年m月")=TEXT($S$42,"yyyy年m月"),INDEX(横カレンダー!$C$4:$IV$13,MATCH($B$13,横カレンダー!$B$4:$B$13,0),MATCH(カレンダー!X46,横カレンダー!$C$3:$IV$3,0)),"") -> O | Y47: =IF(TEXT(カレンダー!Y46,"yyyy年m月")=TEXT($S$42,"yyyy年m月"),INDEX(横カレンダー!$C$4:$IV$13,MATCH($B$13,横カレンダー!$B$4:$B$13,0),MATCH(カレンダー!Y46,横カレンダー!$C$3:$IV$3,0)),"") -> Q
C48: =$C$42-WEEKDAY($C$42)+15 -> 46068 | D48: =$C$42-WEEKDAY($C$42)+16 -> 46069 | E48: =$C$42-WEEKDAY($C$42)+17 -> 46070 | F48: =$C$42-WEEKDAY($C$42)+18 -> 46071 | G48: =$C$42-WEEKDAY($C$42)+19 -> 46072 | H48: =$C$42-WEEKDAY($C$42)+20 -> 46073 | I48: =$C$42-WEEKDAY($C$42)+21 -> 46074 | K48: =$K$42-WEEKDAY($K$42)+15 -> 46096 | L48: =$K$42-WEEKDAY($K$42)+16 -> 46097 | M48: =$K$42-WEEKDAY($K$42)+17 -> 46098 | N48: =$K$42-WEEKDAY($K$42)+18 -> 46099 | O48: =$K$42-WEEKDAY($K$42)+19 -> 46100 | P48: =$K$42-WEEKDAY($K$42)+20 -> 46101 | Q48: =$K$42-WEEKDAY($K$42)+21 -> 46102 | S48: =$S$42-WEEKDAY($S$42)+15 -> 46124 | T48: =$S$42-WEEKDAY($S$42)+16 -> 46125 | U48: =$S$42-WEEKDAY($S$42)+17 -> 46126 | V48: =$S$42-WEEKDAY($S$42)+18 -> 46127 | W48: =$S$42-WEEKDAY($S$42)+19 -> 46128 | X48: =$S$42-WEEKDAY($S$42)+20 -> 46129 | Y48: =$S$42-WEEKDAY($S$42)+21 -> 46130
C49: =IF(TEXT(カレンダー!C48,"yyyy年m月")=TEXT($C$42,"yyyy年m月"),INDEX(横カレンダー!$C$4:$IV$13,MATCH($B$13,横カレンダー!$B$4:$B$13,0),MATCH(カレンダー!C48,横カレンダー!$C$3:$IV$3,0)),"") -> I | D49: =IF(TEXT(カレンダー!D48,"yyyy年m月")=TEXT($C$42,"yyyy年m月"),INDEX(横カレンダー!$C$4:$IV$13,MATCH($B$13,横カレンダー!$B$4:$B$13,0),MATCH(カレンダー!D48,横カレンダー!$C$3:$IV$3,0)),"") -> I | E49: =IF(TEXT(カレンダー!E48,"yyyy年m月")=TEXT($C$42,"yyyy年m月"),INDEX(横カレンダー!$C$4:$IV$13,MATCH($B$13,横カレンダー!$B$4:$B$13,0),MATCH(カレンダー!E48,横カレンダー!$C$3:$IV$3,0)),"") -> I | F49: =IF(TEXT(カレンダー!F48,"yyyy年m月")=TEXT($C$42,"yyyy年m月"),INDEX(横カレンダー!$C$4:$IV$13,MATCH($B$13,横カレンダー!$B$4:$B$13,0),MATCH(カレンダー!F48,横カレンダー!$C$3:$IV$3,0)),"") -> H | G49: =IF(TEXT(カレンダー!G48,"yyyy年m月")=TEXT($C$42,"yyyy年m月"),INDEX(横カレンダー!$C$4:$IV$13,MATCH($B$13,横カレンダー!$B$4:$B$13,0),MATCH(カレンダー!G48,横カレンダー!$C$3:$IV$3,0)),"") -> H | H49: =IF(TEXT(カレンダー!H48,"yyyy年m月")=TEXT($C$42,"yyyy年m月"),INDEX(横カレンダー!$C$4:$IV$13,MATCH($B$13,横カレンダー!$B$4:$B$13,0),MATCH(カレンダー!H48,横カレンダー!$C$3:$IV$3,0)),"") -> L | I49: =IF(TEXT(カレンダー!I48,"yyyy年m月")=TEXT($C$42,"yyyy年m月"),INDEX(横カレンダー!$C$4:$IV$13,MATCH($B$13,横カレンダー!$B$4:$B$13,0),MATCH(カレンダー!I48,横カレンダー!$C$3:$IV$3,0)),"") -> N | K49: =IF(TEXT(カレンダー!K48,"yyyy年m月")=TEXT($K$42,"yyyy年m月"),INDEX(横カレンダー!$C$4:$IV$13,MATCH($B$13,横カレンダー!$B$4:$B$13,0),MATCH(カレンダー!K48,横カレンダー!$C$3:$IV$3,0)),"") -> L | L49: =IF(TEXT(カレンダー!L48,"yyyy年m月")=TEXT($K$42,"yyyy年m月"),INDEX(横カレンダー!$C$4:$IV$13,MATCH($B$13,横カレンダー!$B$4:$B$13,0),MATCH(カレンダー!L48,横カレンダー!$C$3:$IV$3,0)),"") -> L | M49: =IF(TEXT(カレンダー!M48,"yyyy年m月")=TEXT($K$42,"yyyy年m月"),INDEX(横カレンダー!$C$4:$IV$13,MATCH($B$13,横カレンダー!$B$4:$B$13,0),MATCH(カレンダー!M48,横カレンダー!$C$3:$IV$3,0)),"") -> L | N49: =IF(TEXT(カレンダー!N48,"yyyy年m月")=TEXT($K$42,"yyyy年m月"),INDEX(横カレンダー!$C$4:$IV$13,MATCH($B$13,横カレンダー!$B$4:$B$13,0),MATCH(カレンダー!N48,横カレンダー!$C$3:$IV$3,0)),"") -> L | O49: =IF(TEXT(カレンダー!O48,"yyyy年m月")=TEXT($K$42,"yyyy年m月"),INDEX(横カレンダー!$C$4:$IV$13,MATCH($B$13,横カレンダー!$B$4:$B$13,0),MATCH(カレンダー!O48,横カレンダー!$C$3:$IV$3,0)),"") -> P | P49: =IF(TEXT(カレンダー!P48,"yyyy年m月")=TEXT($K$42,"yyyy年m月"),INDEX(横カレンダー!$C$4:$IV$13,MATCH($B$13,横カレンダー!$B$4:$B$13,0),MATCH(カレンダー!P48,横カレンダー!$C$3:$IV$3,0)),"") -> P | Q49: =IF(TEXT(カレンダー!Q48,"yyyy年m月")=TEXT($K$42,"yyyy年m月"),INDEX(横カレンダー!$C$4:$IV$13,MATCH($B$13,横カレンダー!$B$4:$B$13,0),MATCH(カレンダー!Q48,横カレンダー!$C$3:$IV$3,0)),"") -> Q | S49: =IF(TEXT(カレンダー!S48,"yyyy年m月")=TEXT($S$42,"yyyy年m月"),INDEX(横カレンダー!$C$4:$IV$13,MATCH($B$13,横カレンダー!$B$4:$B$13,0),MATCH(カレンダー!S48,横カレンダー!$C$3:$IV$3,0)),"") -> K | T49: =IF(TEXT(カレンダー!T48,"yyyy年m月")=TEXT($S$42,"yyyy年m月"),INDEX(横カレンダー!$C$4:$IV$13,MATCH($B$13,横カレンダー!$B$4:$B$13,0),MATCH(カレンダー!T48,横カレンダー!$C$3:$IV$3,0)),"") -> K | U49: =IF(TEXT(カレンダー!U48,"yyyy年m月")=TEXT($S$42,"yyyy年m月"),INDEX(横カレンダー!$C$4:$IV$13,MATCH($B$13,横カレンダー!$B$4:$B$13,0),MATCH(カレンダー!U48,横カレンダー!$C$3:$IV$3,0)),"") -> K | V49: =IF(TEXT(カレンダー!V48,"yyyy年m月")=TEXT($S$42,"yyyy年m月"),INDEX(横カレンダー!$C$4:$IV$13,MATCH($B$13,横カレンダー!$B$4:$B$13,0),MATCH(カレンダー!V48,横カレンダー!$C$3:$IV$3,0)),"") -> K | W49: =IF(TEXT(カレンダー!W48,"yyyy年m月")=TEXT($S$42,"yyyy年m月"),INDEX(横カレンダー!$C$4:$IV$13,MATCH($B$13,横カレンダー!$B$4:$B$13,0),MATCH(カレンダー!W48,横カレンダー!$C$3:$IV$3,0)),"") -> K | X49: =IF(TEXT(カレンダー!X48,"yyyy年m月")=TEXT($S$42,"yyyy年m月"),INDEX(横カレンダー!$C$4:$IV$13,MATCH($B$13,横カレンダー!$B$4:$B$13,0),MATCH(カレンダー!X48,横カレンダー!$C$3:$IV$3,0)),"") -> O | Y49: =IF(TEXT(カレンダー!Y48,"yyyy年m月")=TEXT($S$42,"yyyy年m月"),INDEX(横カレンダー!$C$4:$IV$13,MATCH($B$13,横カレンダー!$B$4:$B$13,0),MATCH(カレンダー!Y48,横カレンダー!$C$3:$IV$3,0)),"") -> Q
C50: =$C$42-WEEKDAY($C$42)+22 -> 46075 | D50: =$C$42-WEEKDAY($C$42)+23 -> 46076 | E50: =$C$42-WEEKDAY($C$42)+24 -> 46077 | F50: =$C$42-WEEKDAY($C$42)+25 -> 46078 | G50: =$C$42-WEEKDAY($C$42)+26 -> 46079 | H50: =$C$42-WEEKDAY($C$42)+27 -> 46080 | I50: =$C$42-WEEKDAY($C$42)+28 -> 46081 | K50: =$K$42-WEEKDAY($K$42)+22 -> 46103 | L50: =$K$42-WEEKDAY($K$42)+23 -> 46104 | M50: =$K$42-WEEKDAY($K$42)+24 -> 46105 | N50: =$K$42-WEEKDAY($K$42)+25 -> 46106 | O50: =$K$42-WEEKDAY($K$42)+26 -> 46107 | P50: =$K$42-WEEKDAY($K$42)+27 -> 46108 | Q50: =$K$42-WEEKDAY($K$42)+28 -> 46109 | S50: =$S$42-WEEKDAY($S$42)+22 -> 46131 | T50: =$S$42-WEEKDAY($S$42)+23 -> 46132 | U50: =$S$42-WEEKDAY($S$42)+24 -> 46133 | V50: =$S$42-WEEKDAY($S$42)+25 -> 46134 | W50: =$S$42-WEEKDAY($S$42)+26 -> 46135 | X50: =$S$42-WEEKDAY($S$42)+27 -> 46136 | Y50: =$S$42-WEEKDAY($S$42)+28 -> 46137
C51: =IF(TEXT(カレンダー!C50,"yyyy年m月")=TEXT($C$42,"yyyy年m月"),INDEX(横カレンダー!$C$4:$IV$13,MATCH($B$13,横カレンダー!$B$4:$B$13,0),MATCH(カレンダー!C50,横カレンダー!$C$3:$IV$3,0)),"") -> L | D51: =IF(TEXT(カレンダー!D50,"yyyy年m月")=TEXT($C$42,"yyyy年m月"),INDEX(横カレンダー!$C$4:$IV$13,MATCH($B$13,横カレンダー!$B$4:$B$13,0),MATCH(カレンダー!D50,横カレンダー!$C$3:$IV$3,0)),"") -> L | E51: =IF(TEXT(カレンダー!E50,"yyyy年m月")=TEXT($C$42,"yyyy年m月"),INDEX(横カレンダー!$C$4:$IV$13,MATCH($B$13,横カレンダー!$B$4:$B$13,0),MATCH(カレンダー!E50,横カレンダー!$C$3:$IV$3,0)),"") -> H | F51: =IF(TEXT(カレンダー!F50,"yyyy年m月")=TEXT($C$42,"yyyy年m月"),INDEX(横カレンダー!$C$4:$IV$13,MATCH($B$13,横カレンダー!$B$4:$B$13,0),MATCH(カレンダー!F50,横カレンダー!$C$3:$IV$3,0)),"") -> H | G51: =IF(TEXT(カレンダー!G50,"yyyy年m月")=TEXT($C$42,"yyyy年m月"),INDEX(横カレンダー!$C$4:$IV$13,MATCH($B$13,横カレンダー!$B$4:$B$13,0),MATCH(カレンダー!G50,横カレンダー!$C$3:$IV$3,0)),"") -> H | H51: =IF(TEXT(カレンダー!H50,"yyyy年m月")=TEXT($C$42,"yyyy年m月"),INDEX(横カレンダー!$C$4:$IV$13,MATCH($B$13,横カレンダー!$B$4:$B$13,0),MATCH(カレンダー!H50,横カレンダー!$C$3:$IV$3,0)),"") -> L | I51: =IF(TEXT(カレンダー!I50,"yyyy年m月")=TEXT($C$42,"yyyy年m月"),INDEX(横カレンダー!$C$4:$IV$13,MATCH($B$13,横カレンダー!$B$4:$B$13,0),MATCH(カレンダー!I50,横カレンダー!$C$3:$IV$3,0)),"") -> N | K51: =IF(TEXT(カレンダー!K50,"yyyy年m月")=TEXT($K$42,"yyyy年m月"),INDEX(横カレンダー!$C$4:$IV$13,MATCH($B$13,横カレンダー!$B$4:$B$13,0),MATCH(カレンダー!K50,横カレンダー!$C$3:$IV$3,0)),"") -> L | L51: =IF(TEXT(カレンダー!L50,"yyyy年m月")=TEXT($K$42,"yyyy年m月"),INDEX(横カレンダー!$C$4:$IV$13,MATCH($B$13,横カレンダー!$B$4:$B$13,0),MATCH(カレンダー!L50,横カレンダー!$C$3:$IV$3,0)),"") -> L | M51: =IF(TEXT(カレンダー!M50,"yyyy年m月")=TEXT($K$42,"yyyy年m月"),INDEX(横カレンダー!$C$4:$IV$13,MATCH($B$13,横カレンダー!$B$4:$B$13,0),MATCH(カレンダー!M50,横カレンダー!$C$3:$IV$3,0)),"") -> L | N51: =IF(TEXT(カレンダー!N50,"yyyy年m月")=TEXT($K$42,"yyyy年m月"),INDEX(横カレンダー!$C$4:$IV$13,MATCH($B$13,横カレンダー!$B$4:$B$13,0),MATCH(カレンダー!N50,横カレンダー!$C$3:$IV$3,0)),"") -> L | O51: =IF(TEXT(カレンダー!O50,"yyyy年m月")=TEXT($K$42,"yyyy年m月"),INDEX(横カレンダー!$C$4:$IV$13,MATCH($B$13,横カレンダー!$B$4:$B$13,0),MATCH(カレンダー!O50,横カレンダー!$C$3:$IV$3,0)),"") -> L | P51: =IF(TEXT(カレンダー!P50,"yyyy年m月")=TEXT($K$42,"yyyy年m月"),INDEX(横カレンダー!$C$4:$IV$13,MATCH($B$13,横カレンダー!$B$4:$B$13,0),MATCH(カレンダー!P50,横カレンダー!$C$3:$IV$3,0)),"") -> P | Q51: =IF(TEXT(カレンダー!Q50,"yyyy年m月")=TEXT($K$42,"yyyy年m月"),INDEX(横カレンダー!$C$4:$IV$13,MATCH($B$13,横カレンダー!$B$4:$B$13,0),MATCH(カレンダー!Q50,横カレンダー!$C$3:$IV$3,0)),"") -> Q | S51: =IF(TEXT(カレンダー!S50,"yyyy年m月")=TEXT($S$42,"yyyy年m月"),INDEX(横カレンダー!$C$4:$IV$13,MATCH($B$13,横カレンダー!$B$4:$B$13,0),MATCH(カレンダー!S50,横カレンダー!$C$3:$IV$3,0)),"") -> K | T51: =IF(TEXT(カレンダー!T50,"yyyy年m月")=TEXT($S$42,"yyyy年m月"),INDEX(横カレンダー!$C$4:$IV$13,MATCH($B$13,横カレンダー!$B$4:$B$13,0),MATCH(カレンダー!T50,横カレンダー!$C$3:$IV$3,0)),"") -> K | U51: =IF(TEXT(カレンダー!U50,"yyyy年m月")=TEXT($S$42,"yyyy年m月"),INDEX(横カレンダー!$C$4:$IV$13,MATCH($B$13,横カレンダー!$B$4:$B$13,0),MATCH(カレンダー!U50,横カレンダー!$C$3:$IV$3,0)),"") -> K | V51: =IF(TEXT(カレンダー!V50,"yyyy年m月")=TEXT($S$42,"yyyy年m月"),INDEX(横カレンダー!$C$4:$IV$13,MATCH($B$13,横カレンダー!$B$4:$B$13,0),MATCH(カレンダー!V50,横カレンダー!$C$3:$IV$3,0)),"") -> K | W51: =IF(TEXT(カレンダー!W50,"yyyy年m月")=TEXT($S$42,"yyyy年m月"),INDEX(横カレンダー!$C$4:$IV$13,MATCH($B$13,横カレンダー!$B$4:$B$13,0),MATCH(カレンダー!W50,横カレンダー!$C$3:$IV$3,0)),"") -> K | X51: =IF(TEXT(カレンダー!X50,"yyyy年m月")=TEXT($S$42,"yyyy年m月"),INDEX(横カレンダー!$C$4:$IV$13,MATCH($B$13,横カレンダー!$B$4:$B$13,0),MATCH(カレンダー!X50,横カレンダー!$C$3:$IV$3,0)),"") -> O | Y51: =IF(TEXT(カレンダー!Y50,"yyyy年m月")=TEXT($S$42,"yyyy年m月"),INDEX(横カレンダー!$C$4:$IV$13,MATCH($B$13,横カレンダー!$B$4:$B$13,0),MATCH(カレンダー!Y50,横カレンダー!$C$3:$IV$3,0)),"") -> U
C52: =$C$42-WEEKDAY($C$42)+29 -> 46082 | D52: =$C$42-WEEKDAY($C$42)+30 -> 46083 | E52: =$C$42-WEEKDAY($C$42)+31 -> 46084 | F52: =$C$42-WEEKDAY($C$42)+32 -> 46085 | G52: =$C$42-WEEKDAY($C$42)+33 -> 46086 | H52: =$C$42-WEEKDAY($C$42)+34 -> 46087 | I52: =$C$42-WEEKDAY($C$42)+35 -> 46088 | K52: =$K$42-WEEKDAY($K$42)+29 -> 46110 | L52: =$K$42-WEEKDAY($K$42)+30 -> 46111 | M52: =$K$42-WEEKDAY($K$42)+31 -> 46112 | N52: =$K$42-WEEKDAY($K$42)+32 -> 46113 | O52: =$K$42-WEEKDAY($K$42)+33 -> 46114 | P52: =$K$42-WEEKDAY($K$42)+34 -> 46115 | Q52: =$K$42-WEEKDAY($K$42)+35 -> 46116 | S52: =$S$42-WEEKDAY($S$42)+29 -> 46138 | T52: =$S$42-WEEKDAY($S$42)+30 -> 46139 | U52: =$S$42-WEEKDAY($S$42)+31 -> 46140 | V52: =$S$42-WEEKDAY($S$42)+32 -> 46141 | W52: =$S$42-WEEKDAY($S$42)+33 -> 46142 | X52: =$S$42-WEEKDAY($S$42)+34 -> 46143 | Y52: =$S$42-WEEKDAY($S$42)+35 -> 46144
C53: =IF(TEXT(カレンダー!C52,"yyyy年m月")=TEXT($C$42,"yyyy年m月"),INDEX(横カレンダー!$C$4:$IV$13,MATCH($B$13,横カレンダー!$B$4:$B$13,0),MATCH(カレンダー!C52,横カレンダー!$C$3:$IV$3,0)),"") | D53: =IF(TEXT(カレンダー!D52,"yyyy年m月")=TEXT($C$42,"yyyy年m月"),INDEX(横カレンダー!$C$4:$IV$13,MATCH($B$13,横カレンダー!$B$4:$B$13,0),MATCH(カレンダー!D52,横カレンダー!$C$3:$IV$3,0)),"") | E53: =IF(TEXT(カレンダー!E52,"yyyy年m月")=TEXT($C$42,"yyyy年m月"),INDEX(横カレンダー!$C$4:$IV$13,MATCH($B$13,横カレンダー!$B$4:$B$13,0),MATCH(カレンダー!E52,横カレンダー!$C$3:$IV$3,0)),"") | F53: =IF(TEXT(カレンダー!F52,"yyyy年m月")=TEXT($C$42,"yyyy年m月"),INDEX(横カレンダー!$C$4:$IV$13,MATCH($B$13,横カレンダー!$B$4:$B$13,0),MATCH(カレンダー!F52,横カレンダー!$C$3:$IV$3,0)),"") | G53: =IF(TEXT(カレンダー!G52,"yyyy年m月")=TEXT($C$42,"yyyy年m月"),INDEX(横カレンダー!$C$4:$IV$13,MATCH($B$13,横カレンダー!$B$4:$B$13,0),MATCH(カレンダー!G52,横カレンダー!$C$3:$IV$3,0)),"") | H53: =IF(TEXT(カレンダー!H52,"yyyy年m月")=TEXT($C$42,"yyyy年m月"),INDEX(横カレンダー!$C$4:$IV$13,MATCH($B$13,横カレンダー!$B$4:$B$13,0),MATCH(カレンダー!H52,横カレンダー!$C$3:$IV$3,0)),"") | I53: =IF(TEXT(カレンダー!I52,"yyyy年m月")=TEXT($C$42,"yyyy年m月"),INDEX(横カレンダー!$C$4:$IV$13,MATCH($B$13,横カレンダー!$B$4:$B$13,0),MATCH(カレンダー!I52,横カレンダー!$C$3:$IV$3,0)),"") | K53: =IF(TEXT(カレンダー!K52,"yyyy年m月")=TEXT($K$42,"yyyy年m月"),INDEX(横カレンダー!$C$4:$IV$13,MATCH($B$13,横カレンダー!$B$4:$B$13,0),MATCH(カレンダー!K52,横カレンダー!$C$3:$IV$3,0)),"") -> M | L53: =IF(TEXT(カレンダー!L52,"yyyy年m月")=TEXT($K$42,"yyyy年m月"),INDEX(横カレンダー!$C$4:$IV$13,MATCH($B$13,横カレンダー!$B$4:$B$13,0),MATCH(カレンダー!L52,横カレンダー!$C$3:$IV$3,0)),"") -> M | M53: =IF(TEXT(カレンダー!M52,"yyyy年m月")=TEXT($K$42,"yyyy年m月"),INDEX(横カレンダー!$C$4:$IV$13,MATCH($B$13,横カレンダー!$B$4:$B$13,0),MATCH(カレンダー!M52,横カレンダー!$C$3:$IV$3,0)),"") -> M | N53: =IF(TEXT(カレンダー!N52,"yyyy年m月")=TEXT($K$42,"yyyy年m月"),INDEX(横カレンダー!$C$4:$IV$13,MATCH($B$13,横カレンダー!$B$4:$B$13,0),MATCH(カレンダー!N52,横カレンダー!$C$3:$IV$3,0)),"") | O53: =IF(TEXT(カレンダー!O52,"yyyy年m月")=TEXT($K$42,"yyyy年m月"),INDEX(横カレンダー!$C$4:$IV$13,MATCH($B$13,横カレンダー!$B$4:$B$13,0),MATCH(カレンダー!O52,横カレンダー!$C$3:$IV$3,0)),"") | P53: =IF(TEXT(カレンダー!P52,"yyyy年m月")=TEXT($K$42,"yyyy年m月"),INDEX(横カレンダー!$C$4:$IV$13,MATCH($B$13,横カレンダー!$B$4:$B$13,0),MATCH(カレンダー!P52,横カレンダー!$C$3:$IV$3,0)),"") | Q53: =IF(TEXT(カレンダー!Q52,"yyyy年m月")=TEXT($K$42,"yyyy年m月"),INDEX(横カレンダー!$C$4:$IV$13,MATCH($B$13,横カレンダー!$B$4:$B$13,0),MATCH(カレンダー!Q52,横カレンダー!$C$3:$IV$3,0)),"") | S53: =IF(TEXT(カレンダー!S52,"yyyy年m月")=TEXT($S$42,"yyyy年m月"),INDEX(横カレンダー!$C$4:$IV$13,MATCH($B$13,横カレンダー!$B$4:$B$13,0),MATCH(カレンダー!S52,横カレンダー!$C$3:$IV$3,0)),"") -> U | T53: =IF(TEXT(カレンダー!T52,"yyyy年m月")=TEXT($S$42,"yyyy年m月"),INDEX(横カレンダー!$C$4:$IV$13,MATCH($B$13,横カレンダー!$B$4:$B$13,0),MATCH(カレンダー!T52,横カレンダー!$C$3:$IV$3,0)),"") -> U | U53: =IF(TEXT(カレンダー!U52,"yyyy年m月")=TEXT($S$42,"yyyy年m月"),INDEX(横カレンダー!$C$4:$IV$13,MATCH($B$13,横カレンダー!$B$4:$B$13,0),MATCH(カレンダー!U52,横カレンダー!$C$3:$IV$3,0)),"") -> U | V53: =IF(TEXT(カレンダー!V52,"yyyy年m月")=TEXT($S$42,"yyyy年m月"),INDEX(横カレンダー!$C$4:$IV$13,MATCH($B$13,横カレンダー!$B$4:$B$13,0),MATCH(カレンダー!V52,横カレンダー!$C$3:$IV$3,0)),"") -> U | W53: =IF(TEXT(カレンダー!W52,"yyyy年m月")=TEXT($S$42,"yyyy年m月"),INDEX(横カレンダー!$C$4:$IV$13,MATCH($B$13,横カレンダー!$B$4:$B$13,0),MATCH(カレンダー!W52,横カレンダー!$C$3:$IV$3,0)),"") -> U | X53: =IF(TEXT(カレンダー!X52,"yyyy年m月")=TEXT($S$42,"yyyy年m月"),INDEX(横カレンダー!$C$4:$IV$13,MATCH($B$13,横カレンダー!$B$4:$B$13,0),MATCH(カレンダー!X52,横カレンダー!$C$3:$IV$3,0)),"") | Y53: =IF(TEXT(カレンダー!Y52,"yyyy年m月")=TEXT($S$42,"yyyy年m月"),INDEX(横カレンダー!$C$4:$IV$13,MATCH($B$13,横カレンダー!$B$4:$B$13,0),MATCH(カレンダー!Y52,横カレンダー!$C$3:$IV$3,0)),"")
C54: =$C$42-WEEKDAY($C$42)+36 -> 46089 | D54: =$C$42-WEEKDAY($C$42)+37 -> 46090 | E54: =$C$42-WEEKDAY($C$42)+38 -> 46091 | F54: =$C$42-WEEKDAY($C$42)+39 -> 46092 | G54: =$C$42-WEEKDAY($C$42)+40 -> 46093 | H54: =$C$42-WEEKDAY($C$42)+41 -> 46094 | I54: =$C$42-WEEKDAY($C$42)+42 -> 46095 | K54: =$K$42-WEEKDAY($K$42)+36 -> 46117 | L54: =$K$42-WEEKDAY($K$42)+37 -> 46118 | M54: =$K$42-WEEKDAY($K$42)+38 -> 46119 | N54: =$K$42-WEEKDAY($K$42)+39 -> 46120 | O54: =$K$42-WEEKDAY($K$42)+40 -> 46121 | P54: =$K$42-WEEKDAY($K$42)+41 -> 46122 | Q54: =$K$42-WEEKDAY($K$42)+42 -> 46123 | S54: =$S$42-WEEKDAY($S$42)+36 -> 46145 | T54: =$S$42-WEEKDAY($S$42)+37 -> 46146 | U54: =$S$42-WEEKDAY($S$42)+38 -> 46147 | V54: =$S$42-WEEKDAY($S$42)+39 -> 46148 | W54: =$S$42-WEEKDAY($S$42)+40 -> 46149 | X54: =$S$42-WEEKDAY($S$42)+41 -> 46150 | Y54: =$S$42-WEEKDAY($S$42)+42 -> 46151
C55: =IF(TEXT(カレンダー!C54,"yyyy年m月")=TEXT($C$42,"yyyy年m月"),INDEX(横カレンダー!$C$4:$IV$13,MATCH($B$13,横カレンダー!$B$4:$B$13,0),MATCH(カレンダー!C54,横カレンダー!$C$3:$IV$3,0)),"") | D55: =IF(TEXT(カレンダー!D54,"yyyy年m月")=TEXT($C$42,"yyyy年m月"),INDEX(横カレンダー!$C$4:$IV$13,MATCH($B$13,横カレンダー!$B$4:$B$13,0),MATCH(カレンダー!D54,横カレンダー!$C$3:$IV$3,0)),"") | E55: =IF(TEXT(カレンダー!E54,"yyyy年m月")=TEXT($C$42,"yyyy年m月"),INDEX(横カレンダー!$C$4:$IV$13,MATCH($B$13,横カレンダー!$B$4:$B$13,0),MATCH(カレンダー!E54,横カレンダー!$C$3:$IV$3,0)),"") | F55: =IF(TEXT(カレンダー!F54,"yyyy年m月")=TEXT($C$42,"yyyy年m月"),INDEX(横カレンダー!$C$4:$IV$13,MATCH($B$13,横カレンダー!$B$4:$B$13,0),MATCH(カレンダー!F54,横カレンダー!$C$3:$IV$3,0)),"") | G55: =IF(TEXT(カレンダー!G54,"yyyy年m月")=TEXT($C$42,"yyyy年m月"),INDEX(横カレンダー!$C$4:$IV$13,MATCH($B$13,横カレンダー!$B$4:$B$13,0),MATCH(カレンダー!G54,横カレンダー!$C$3:$IV$3,0)),"") | H55: =IF(TEXT(カレンダー!H54,"yyyy年m月")=TEXT($C$42,"yyyy年m月"),INDEX(横カレンダー!$C$4:$IV$13,MATCH($B$13,横カレンダー!$B$4:$B$13,0),MATCH(カレンダー!H54,横カレンダー!$C$3:$IV$3,0)),"") | I55: =IF(TEXT(カレンダー!I54,"yyyy年m月")=TEXT($C$42,"yyyy年m月"),INDEX(横カレンダー!$C$4:$IV$13,MATCH($B$13,横カレンダー!$B$4:$B$13,0),MATCH(カレンダー!I54,横カレンダー!$C$3:$IV$3,0)),"") | K55: =IF(TEXT(カレンダー!K54,"yyyy年m月")=TEXT($K$42,"yyyy年m月"),INDEX(横カレンダー!$C$4:$IV$13,MATCH($B$13,横カレンダー!$B$4:$B$13,0),MATCH(カレンダー!K54,横カレンダー!$C$3:$IV$3,0)),"") | L55: =IF(TEXT(カレンダー!L54,"yyyy年m月")=TEXT($K$42,"yyyy年m月"),INDEX(横カレンダー!$C$4:$IV$13,MATCH($B$13,横カレンダー!$B$4:$B$13,0),MATCH(カレンダー!L54,横カレンダー!$C$3:$IV$3,0)),"") | M55: =IF(TEXT(カレンダー!M54,"yyyy年m月")=TEXT($K$42,"yyyy年m月"),INDEX(横カレンダー!$C$4:$IV$13,MATCH($B$13,横カレンダー!$B$4:$B$13,0),MATCH(カレンダー!M54,横カレンダー!$C$3:$IV$3,0)),"") | N55: =IF(TEXT(カレンダー!N54,"yyyy年m月")=TEXT($K$42,"yyyy年m月"),INDEX(横カレンダー!$C$4:$IV$13,MATCH($B$13,横カレンダー!$B$4:$B$13,0),MATCH(カレンダー!N54,横カレンダー!$C$3:$IV$3,0)),"") | O55: =IF(TEXT(カレンダー!O54,"yyyy年m月")=TEXT($K$42,"yyyy年m月"),INDEX(横カレンダー!$C$4:$IV$13,MATCH($B$13,横カレンダー!$B$4:$B$13,0),MATCH(カレンダー!O54,横カレンダー!$C$3:$IV$3,0)),"") | P55: =IF(TEXT(カレンダー!P54,"yyyy年m月")=TEXT($K$42,"yyyy年m月"),INDEX(横カレンダー!$C$4:$IV$13,MATCH($B$13,横カレンダー!$B$4:$B$13,0),MATCH(カレンダー!P54,横カレンダー!$C$3:$IV$3,0)),"") | Q55: =IF(TEXT(カレンダー!Q54,"yyyy年m月")=TEXT($K$42,"yyyy年m月"),INDEX(横カレンダー!$C$4:$IV$13,MATCH($B$13,横カレンダー!$B$4:$B$13,0),MATCH(カレンダー!Q54,横カレンダー!$C$3:$IV$3,0)),"") | S55: =IF(TEXT(カレンダー!S54,"yyyy年m月")=TEXT($S$42,"yyyy年m月"),INDEX(横カレンダー!$C$4:$IV$13,MATCH($B$13,横カレンダー!$B$4:$B$13,0),MATCH(カレンダー!S54,横カレンダー!$C$3:$IV$3,0)),"") | T55: =IF(TEXT(カレンダー!T54,"yyyy年m月")=TEXT($S$42,"yyyy年m月"),INDEX(横カレンダー!$C$4:$IV$13,MATCH($B$13,横カレンダー!$B$4:$B$13,0),MATCH(カレンダー!T54,横カレンダー!$C$3:$IV$3,0)),"") | U55: =IF(TEXT(カレンダー!U54,"yyyy年m月")=TEXT($S$42,"yyyy年m月"),INDEX(横カレンダー!$C$4:$IV$13,MATCH($B$13,横カレンダー!$B$4:$B$13,0),MATCH(カレンダー!U54,横カレンダー!$C$3:$IV$3,0)),"") | V55: =IF(TEXT(カレンダー!V54,"yyyy年m月")=TEXT($S$42,"yyyy年m月"),INDEX(横カレンダー!$C$4:$IV$13,MATCH($B$13,横カレンダー!$B$4:$B$13,0),MATCH(カレンダー!V54,横カレンダー!$C$3:$IV$3,0)),"") | W55: =IF(TEXT(カレンダー!W54,"yyyy年m月")=TEXT($S$42,"yyyy年m月"),INDEX(横カレンダー!$C$4:$IV$13,MATCH($B$13,横カレンダー!$B$4:$B$13,0),MATCH(カレンダー!W54,横カレンダー!$C$3:$IV$3,0)),"") | X55: =IF(TEXT(カレンダー!X54,"yyyy年m月")=TEXT($S$42,"yyyy年m月"),INDEX(横カレンダー!$C$4:$IV$13,MATCH($B$13,横カレンダー!$B$4:$B$13,0),MATCH(カレンダー!X54,横カレンダー!$C$3:$IV$3,0)),"") | Y55: =IF(TEXT(カレンダー!Y54,"yyyy年m月")=TEXT($S$42,"yyyy年m月"),INDEX(横カレンダー!$C$4:$IV$13,MATCH($B$13,横カレンダー!$B$4:$B$13,0),MATCH(カレンダー!Y54,横カレンダー!$C$3:$IV$3,0)),"")

Sheet 2025年8月
B1: =RIGHT(CELL("filename",A1),LEN(CELL("filename",A1))-FIND("]",CELL("filename",A1))) -> 2025年8月 | C1: =B1-1 -> 45869 | D1: 料金プラン①⇒ | F1: WEB割 | I1: 割引率⇒ | J1: =VLOOKUP(F1,料金元データ!$B$2:$C$17,2,FALSE) -> 0
B2: 部屋タイプ名 | C2: 利用人数⇩ | D2: A | E2: B | F2: C | G2: D | H2: E | I2: F | J2: G | K2: H | L2: I | M2: J | N2: K | O2: L | P2: M | Q2: N | R2: O | S2: P | T2: Q | U2: R | V2: S | W2: T | X2: U | Y2: V | Z2: W | AA2: X | AB2: Y | AC2: Z | AD2: Z1 | AE2: Z2 | AF2: Z3
B3: =カレンダー!B3 -> ラグジュアリープールヴィラ | C3: 2 | D3: =ROUNDDOWN(IF($C3=1,料金元データ!D19,IF($C3=2,料金元データ!D26,IF($C3=3,料金元データ!D33,IF($C3=4,料金元データ!D40,IF($C3=5,料金元データ!D47,IF($C3=6,料金元データ!D54))))))*(1-$J$1),-1) -> 30500 | E3: =ROUNDDOWN(IF($C3=1,料金元データ!E19,IF($C3=2,料金元データ!E26,IF($C3=3,料金元データ!E33,IF($C3=4,料金元データ!E40,IF($C3=5,料金元データ!E47,IF($C3=6,料金元データ!E54))))))*(1-$J$1),-1) -> 39500 | F3: =ROUNDDOWN(IF($C3=1,料金元データ!F19,IF($C3=2,料金元データ!F26,IF($C3=3,料金元データ!F33,IF($C3=4,料金元データ!F40,IF($C3=5,料金元データ!F47,IF($C3=6,料金元データ!F54))))))*(1-$J$1),-1) -> 42000 | G3: =ROUNDDOWN(IF($C3=1,料金元データ!G19,IF($C3=2,料金元データ!G26,IF($C3=3,料金元データ!G33,IF($C3=4,料金元データ!G40,IF($C3=5,料金元データ!G47,IF($C3=6,料金元データ!G54))))))*(1-$J$1),-1) -> 44800 | H3: =ROUNDDOWN(IF($C3=1,料金元データ!H19,IF($C3=2,料金元データ!H26,IF($C3=3,料金元データ!H33,IF($C3=4,料金元データ!H40,IF($C3=5,料金元データ!H47,IF($C3=6,料金元データ!H54))))))*(1-$J$1),-1) -> 48000 | I3: =ROUNDDOWN(IF($C3=1,料金元データ!I19,IF($C3=2,料金元データ!I26,IF($C3=3,料金元データ!I33,IF($C3=4,料金元データ!I40,IF($C3=5,料金元データ!I47,IF($C3=6,料金元データ!I54))))))*(1-$J$1),-1) -> 52500 | J3: =ROUNDDOWN(IF($C3=1,料金元データ!J19,IF($C3=2,料金元データ!J26,IF($C3=3,料金元データ!J33,IF($C3=4,料金元データ!J40,IF($C3=5,料金元データ!J47,IF($C3=6,料金元データ!J54))))))*(1-$J$1),-1) -> 54000 | K3: =ROUNDDOWN(IF($C3=1,料金元データ!K19,IF($C3=2,料金元データ!K26,IF($C3=3,料金元データ!K33,IF($C3=4,料金元データ!K40,IF($C3=5,料金元データ!K47,IF($C3=6,料金元データ!K54))))))*(1-$J$1),-1) -> 56500 | ... AF3: =ROUNDDOWN(IF($C3=1,料金元データ!AF19,IF($C3=2,料金元データ!AF26,IF($C3=3,料金元データ!AF33,IF($C3=4,料金元データ!AF40,IF($C3=5,料金元データ!AF47,IF($C3=6,料金元データ!AF54))))))*(1-$J$1),-1) -> 0
B4: =カレンダー!B4 -> with SAUNA | C4: 2 | D4: =ROUNDDOWN(IF($C4=1,料金元データ!D20,IF($C4=2,料金元データ!D27,IF($C4=3,料金元データ!D34,IF($C4=4,料金元データ!D41,IF($C4=5,料金元データ!D48,IF($C4=6,料金元データ!D55))))))*(1-$J$1),-1) -> 40500 | E4: =ROUNDDOWN(IF($C4=1,料金元データ!E20,IF($C4=2,料金元データ!E27,IF($C4=3,料金元データ!E34,IF($C4=4,料金元データ!E41,IF($C4=5,料金元データ!E48,IF($C4=6,料金元データ!E55))))))*(1-$J$1),-1) -> 49500 | F4: =ROUNDDOWN(IF($C4=1,料金元データ!F20,IF($C4=2,料金元データ!F27,IF($C4=3,料金元データ!F34,IF($C4=4,料金元データ!F41,IF($C4=5,料金元データ!F48,IF($C4=6,料金元データ!F55))))))*(1-$J$1),-1) -> 52000 | G4: =ROUNDDOWN(IF($C4=1,料金元データ!G20,IF($C4=2,料金元データ!G27,IF($C4=3,料金元データ!G34,IF($C4=4,料金元データ!G41,IF($C4=5,料金元データ!G48,IF($C4=6,料金元データ!G55))))))*(1-$J$1),-1) -> 54800 | H4: =ROUNDDOWN(IF($C4=1,料金元データ!H20,IF($C4=2,料金元データ!H27,IF($C4=3,料金元データ!H34,IF($C4=4,料金元データ!H41,IF($C4=5,料金元データ!H48,IF($C4=6,料金元データ!H55))))))*(1-$J$1),-1) -> 58000 | I4: =ROUNDDOWN(IF($C4=1,料金元データ!I20,IF($C4=2,料金元データ!I27,IF($C4=3,料金元データ!I34,IF($C4=4,料金元データ!I41,IF($C4=5,料金元データ!I48,IF($C4=6,料金元データ!I55))))))*(1-$J$1),-1) -> 62500 | J4: =ROUNDDOWN(IF($C4=1,料金元データ!J20,IF($C4=2,料金元データ!J27,IF($C4=3,料金元データ!J34,IF($C4=4,料金元データ!J41,IF($C4=5,料金元データ!J48,IF($C4=6,料金元データ!J55))))))*(1-$J$1),-1) -> 64000 | K4: =ROUNDDOWN(IF($C4=1,料金元データ!K20,IF($C4=2,料金元データ!K27,IF($C4=3,料金元データ!K34,IF($C4=4,料金元データ!K41,IF($C4=5,料金元データ!K48,IF($C4=6,料金元データ!K55))))))*(1-$J$1),-1) -> 66500 | ... AF4: =ROUNDDOWN(IF($C4=1,料金元データ!AF20,IF($C4=2,料金元データ!AF27,IF($C4=3,料金元データ!AF34,IF($C4=4,料金元データ!AF41,IF($C4=5,料金元データ!AF48,IF($C4=6,料金元データ!AF55))))))*(1-$J$1),-1) -> 0
B5: =カレンダー!B5 -> 0 | C5: 2 | D5: =ROUNDDOWN(IF($C5=1,料金元データ!D21,IF($C5=2,料金元データ!D28,IF($C5=3,料金元データ!D35,IF($C5=4,料金元データ!D42,IF($C5=5,料金元データ!D49,IF($C5=6,料金元データ!D56))))))*(1-$J$1),-1) -> 0 | F5: 2 | K5: 7 | L5: 14 | M5: 9 | R5: 14 | S5: 15 | T5: 9 | Y5: 14
B6: =カレンダー!B6 -> 0 | C6: 2 | D6: =ROUNDDOWN(IF($C6=1,料金元データ!D22,IF($C6=2,料金元データ!D29,IF($C6=3,料金元データ!D36,IF($C6=4,料金元データ!D43,IF($C6=5,料金元データ!D50,IF($C6=6,料金元データ!D57))))))*(1-$J$1),-1) -> 0
B7: =カレンダー!B7 -> 0 | C7: 3 | D7: =ROUNDDOWN(IF($C7=1,料金元データ!D23,IF($C7=2,料金元データ!D30,IF($C7=3,料金元データ!D37,IF($C7=4,料金元データ!D44,IF($C7=5,料金元データ!D51,IF($C7=6,料金元データ!D58))))))*(1-$J$1),-1) -> 0 | E7: =ROUNDDOWN(IF($C7=1,料金元データ!E23,IF($C7=2,料金元データ!E30,IF($C7=3,料金元データ!E37,IF($C7=4,料金元データ!E44,IF($C7=5,料金元データ!E51,IF($C7=6,料金元データ!E58))))))*(1-$J$1),-1) -> 0 | F7: =ROUNDDOWN(IF($C7=1,料金元データ!F23,IF($C7=2,料金元データ!F30,IF($C7=3,料金元データ!F37,IF($C7=4,料金元データ!F44,IF($C7=5,料金元データ!F51,IF($C7=6,料金元データ!F58))))))*(1-$J$1),-1) -> 0 | G7: =ROUNDDOWN(IF($C7=1,料金元データ!G23,IF($C7=2,料金元データ!G30,IF($C7=3,料金元データ!G37,IF($C7=4,料金元データ!G44,IF($C7=5,料金元データ!G51,IF($C7=6,料金元データ!G58))))))*(1-$J$1),-1) -> 0 | H7: =ROUNDDOWN(IF($C7=1,料金元データ!H23,IF($C7=2,料金元データ!H30,IF($C7=3,料金元データ!H37,IF($C7=4,料金元データ!H44,IF($C7=5,料金元データ!H51,IF($C7=6,料金元データ!H58))))))*(1-$J$1),-1) -> 0 | I7: =ROUNDDOWN(IF($C7=1,料金元データ!I23,IF($C7=2,料金元データ!I30,IF($C7=3,料金元データ!I37,IF($C7=4,料金元データ!I44,IF($C7=5,料金元データ!I51,IF($C7=6,料金元データ!I58))))))*(1-$J$1),-1) -> 0 | J7: =ROUNDDOWN(IF($C7=1,料金元データ!J23,IF($C7=2,料金元データ!J30,IF($C7=3,料金元データ!J37,IF($C7=4,料金元データ!J44,IF($C7=5,料金元データ!J51,IF($C7=6,料金元データ!J58))))))*(1-$J$1),-1) -> 0 | K7: =ROUNDDOWN(IF($C7=1,料金元データ!K23,IF($C7=2,料金元データ!K30,IF($C7=3,料金元データ!K37,IF($C7=4,料金元データ!K44,IF($C7=5,料金元データ!K51,IF($C7=6,料金元データ!K58))))))*(1-$J$1),-1) -> 0 | ... AF7: =ROUNDDOWN(IF($C7=1,料金元データ!AF23,IF($C7=2,料金元データ!AF30,IF($C7=3,料金元データ!AF37,IF($C7=4,料金元データ!AF44,IF($C7=5,料金元データ!AF51,IF($C7=6,料金元データ!AF58))))))*(1-$J$1),-1) -> 0
B8: =カレンダー!B8 -> 0 | C8: 4 | D8: =ROUNDDOWN(IF($C8=1,料金元データ!D24,IF($C8=2,料金元データ!D31,IF($C8=3,料金元データ!D38,IF($C8=4,料金元データ!D45,IF($C8=5,料金元データ!D52,IF($C8=6,料金元データ!D59))))))*(1-$J$1),-1) -> 0 | E8: =ROUNDDOWN(IF($C8=1,料金元データ!E24,IF($C8=2,料金元データ!E31,IF($C8=3,料金元データ!E38,IF($C8=4,料金元データ!E45,IF($C8=5,料金元データ!E52,IF($C8=6,料金元データ!E59))))))*(1-$J$1),-1) -> 0 | F8: =ROUNDDOWN(IF($C8=1,料金元データ!F24,IF($C8=2,料金元データ!F31,IF($C8=3,料金元データ!F38,IF($C8=4,料金元データ!F45,IF($C8=5,料金元データ!F52,IF($C8=6,料金元データ!F59))))))*(1-$J$1),-1) -> 0 | G8: =ROUNDDOWN(IF($C8=1,料金元データ!G24,IF($C8=2,料金元データ!G31,IF($C8=3,料金元データ!G38,IF($C8=4,料金元データ!G45,IF($C8=5,料金元データ!G52,IF($C8=6,料金元データ!G59))))))*(1-$J$1),-1) -> 0 | H8: =ROUNDDOWN(IF($C8=1,料金元データ!H24,IF($C8=2,料金元データ!H31,IF($C8=3,料金元データ!H38,IF($C8=4,料金元データ!H45,IF($C8=5,料金元データ!H52,IF($C8=6,料金元データ!H59))))))*(1-$J$1),-1) -> 0 | I8: =ROUNDDOWN(IF($C8=1,料金元データ!I24,IF($C8=2,料金元データ!I31,IF($C8=3,料金元データ!I38,IF($C8=4,料金元データ!I45,IF($C8=5,料金元データ!I52,IF($C8=6,料金元データ!I59))))))*(1-$J$1),-1) -> 0 | J8: =ROUNDDOWN(IF($C8=1,料金元データ!J24,IF($C8=2,料金元データ!J31,IF($C8=3,料金元データ!J38,IF($C8=4,料金元データ!J45,IF($C8=5,料金元データ!J52,IF($C8=6,料金元データ!J59))))))*(1-$J$1),-1) -> 0 | K8: =ROUNDDOWN(IF($C8=1,料金元データ!K24,IF($C8=2,料金元データ!K31,IF($C8=3,料金元データ!K38,IF($C8=4,料金元データ!K45,IF($C8=5,料金元データ!K52,IF($C8=6,料金元データ!K59))))))*(1-$J$1),-1) -> 0 | ... AF8: =ROUNDDOWN(IF($C8=1,料金元データ!AF24,IF($C8=2,料金元データ!AF31,IF($C8=3,料金元データ!AF38,IF($C8=4,料金元データ!AF45,IF($C8=5,料金元データ!AF52,IF($C8=6,料金元データ!AF59))))))*(1-$J$1),-1) -> 0
C10: =B10-1 -> -1 | D10: 料金プラン②⇒ | F10: 連泊 | I10: 割引率⇒ | J10: =VLOOKUP(F10,料金元データ!$B$2:$C$17,2,FALSE) -> 0.1
B11: 部屋タイプ名 | C11: 利用人数⇩ | D11: A | E11: B | F11: C | G11: D | H11: E | I11: F | J11: G | K11: H | L11: I | M11: J | N11: K | O11: L | P11: M | Q11: N | R11: O | S11: P | T11: Q | U11: R | V11: S | W11: T | X11: U | Y11: V | Z11: W | AA11: X | AB11: Y | AC11: Z | AD11: Z1 | AE11: Z2 | AF11: Z3
B12: =カレンダー!B3 -> ラグジュアリープールヴィラ | C12: 2 | D12: =ROUNDDOWN(IF($C12=1,料金元データ!D19,IF($C12=2,料金元データ!D26,IF($C12=3,料金元データ!D33,IF($C12=4,料金元データ!D40,IF($C12=5,料金元データ!D47,IF($C12=6,料金元データ!D54))))))*(1-$J$10),-1) -> 27450 | E12: =ROUNDDOWN(IF($C12=1,料金元データ!E19,IF($C12=2,料金元データ!E26,IF($C12=3,料金元データ!E33,IF($C12=4,料金元データ!E40,IF($C12=5,料金元データ!E47,IF($C12=6,料金元データ!E54))))))*(1-$J$10),-1) -> 35550 | F12: =ROUNDDOWN(IF($C12=1,料金元データ!F19,IF($C12=2,料金元データ!F26,IF($C12=3,料金元データ!F33,IF($C12=4,料金元データ!F40,IF($C12=5,料金元データ!F47,IF($C12=6,料金元データ!F54))))))*(1-$J$10),-1) -> 37800 | G12: =ROUNDDOWN(IF($C12=1,料金元データ!G19,IF($C12=2,料金元データ!G26,IF($C12=3,料金元データ!G33,IF($C12=4,料金元データ!G40,IF($C12=5,料金元データ!G47,IF($C12=6,料金元データ!G54))))))*(1-$J$10),-1) -> 40320 | H12: =ROUNDDOWN(IF($C12=1,料金元データ!H19,IF($C12=2,料金元データ!H26,IF($C12=3,料金元データ!H33,IF($C12=4,料金元データ!H40,IF($C12=5,料金元データ!H47,IF($C12=6,料金元データ!H54))))))*(1-$J$10),-1) -> 43200 | I12: =ROUNDDOWN(IF($C12=1,料金元データ!I19,IF($C12=2,料金元データ!I26,IF($C12=3,料金元データ!I33,IF($C12=4,料金元データ!I40,IF($C12=5,料金元データ!I47,IF($C12=6,料金元データ!I54))))))*(1-$J$10),-1) -> 47250 | J12: =ROUNDDOWN(IF($C12=1,料金元データ!J19,IF($C12=2,料金元データ!J26,IF($C12=3,料金元データ!J33,IF($C12=4,料金元データ!J40,IF($C12=5,料金元データ!J47,IF($C12=6,料金元データ!J54))))))*(1-$J$10),-1) -> 48600 | K12: =ROUNDDOWN(IF($C12=1,料金元データ!K19,IF($C12=2,料金元データ!K26,IF($C12=3,料金元データ!K33,IF($C12=4,料金元データ!K40,IF($C12=5,料金元データ!K47,IF($C12=6,料金元データ!K54))))))*(1-$J$10),-1) -> 50850 | ... AF12: =ROUNDDOWN(IF($C12=1,料金元データ!AF19,IF($C12=2,料金元データ!AF26,IF($C12=3,料金元データ!AF33,IF($C12=4,料金元データ!AF40,IF($C12=5,料金元データ!AF47,IF($C12=6,料金元データ!AF54))))))*(1-$J$10),-1) -> 0
B13: =カレンダー!B4 -> with SAUNA | C13: 2 | D13: =ROUNDDOWN(IF($C13=1,料金元データ!D20,IF($C13=2,料金元データ!D27,IF($C13=3,料金元データ!D34,IF($C13=4,料金元データ!D41,IF($C13=5,料金元データ!D48,IF($C13=6,料金元データ!D55))))))*(1-$J$10),-1) -> 36450 | E13: =ROUNDDOWN(IF($C13=1,料金元データ!E20,IF($C13=2,料金元データ!E27,IF($C13=3,料金元データ!E34,IF($C13=4,料金元データ!E41,IF($C13=5,料金元データ!E48,IF($C13=6,料金元データ!E55))))))*(1-$J$10),-1) -> 44550 | F13: =ROUNDDOWN(IF($C13=1,料金元データ!F20,IF($C13=2,料金元データ!F27,IF($C13=3,料金元データ!F34,IF($C13=4,料金元データ!F41,IF($C13=5,料金元データ!F48,IF($C13=6,料金元データ!F55))))))*(1-$J$10),-1) -> 46800 | G13: =ROUNDDOWN(IF($C13=1,料金元データ!G20,IF($C13=2,料金元データ!G27,IF($C13=3,料金元データ!G34,IF($C13=4,料金元データ!G41,IF($C13=5,料金元データ!G48,IF($C13=6,料金元データ!G55))))))*(1-$J$10),-1) -> 49320 | H13: =ROUNDDOWN(IF($C13=1,料金元データ!H20,IF($C13=2,料金元データ!H27,IF($C13=3,料金元データ!H34,IF($C13=4,料金元データ!H41,IF($C13=5,料金元データ!H48,IF($C13=6,料金元データ!H55))))))*(1-$J$10),-1) -> 52200 | I13: =ROUNDDOWN(IF($C13=1,料金元データ!I20,IF($C13=2,料金元データ!I27,IF($C13=3,料金元データ!I34,IF($C13=4,料金元データ!I41,IF($C13=5,料金元データ!I48,IF($C13=6,料金元データ!I55))))))*(1-$J$10),-1) -> 56250 | J13: =ROUNDDOWN(IF($C13=1,料金元データ!J20,IF($C13=2,料金元データ!J27,IF($C13=3,料金元データ!J34,IF($C13=4,料金元データ!J41,IF($C13=5,料金元データ!J48,IF($C13=6,料金元データ!J55))))))*(1-$J$10),-1) -> 57600 | K13: =ROUNDDOWN(IF($C13=1,料金元データ!K20,IF($C13=2,料金元データ!K27,IF($C13=3,料金元データ!K34,IF($C13=4,料金元データ!K41,IF($C13=5,料金元データ!K48,IF($C13=6,料金元データ!K55))))))*(1-$J$10),-1) -> 59850 | ... AF13: =ROUNDDOWN(IF($C13=1,料金元データ!AF20,IF($C13=2,料金元データ!AF27,IF($C13=3,料金元データ!AF34,IF($C13=4,料金元データ!AF41,IF($C13=5,料金元データ!AF48,IF($C13=6,料金元データ!AF55))))))*(1-$J$10),-1) -> 0
B14: =カレンダー!B5 -> 0 | C14: 2 | D14: =ROUNDDOWN(IF($C14=1,料金元データ!D21,IF($C14=2,料金元データ!D28,IF($C14=3,料金元データ!D35,IF($C14=4,料金元データ!D42,IF($C14=5,料金元データ!D49,IF($C14=6,料金元データ!D56))))))*(1-$J$10),-1) -> 0 | E14: =ROUNDDOWN(IF($C14=1,料金元データ!E21,IF($C14=2,料金元データ!E28,IF($C14=3,料金元データ!E35,IF($C14=4,料金元データ!E42,IF($C14=5,料金元データ!E49,IF($C14=6,料金元データ!E56))))))*(1-$J$10),-1) -> 0 | F14: =ROUNDDOWN(IF($C14=1,料金元データ!F21,IF($C14=2,料金元データ!F28,IF($C14=3,料金元データ!F35,IF($C14=4,料金元データ!F42,IF($C14=5,料金元データ!F49,IF($C14=6,料金元データ!F56))))))*(1-$J$10),-1) -> 0 | G14: =ROUNDDOWN(IF($C14=1,料金元データ!G21,IF($C14=2,料金元データ!G28,IF($C14=3,料金元データ!G35,IF($C14=4,料金元データ!G42,IF($C14=5,料金元データ!G49,IF($C14=6,料金元データ!G56))))))*(1-$J$10),-1) -> 0 | H14: =ROUNDDOWN(IF($C14=1,料金元データ!H21,IF($C14=2,料金元データ!H28,IF($C14=3,料金元データ!H35,IF($C14=4,料金元データ!H42,IF($C14=5,料金元データ!H49,IF($C14=6,料金元データ!H56))))))*(1-$J$10),-1) -> 0 | I14: =ROUNDDOWN(IF($C14=1,料金元データ!I21,IF($C14=2,料金元データ!I28,IF($C14=3,料金元データ!I35,IF($C14=4,料金元データ!I42,IF($C14=5,料金元データ!I49,IF($C14=6,料金元データ!I56))))))*(1-$J$10),-1) -> 0 | J14: =ROUNDDOWN(IF($C14=1,料金元データ!J21,IF($C14=2,料金元データ!J28,IF($C14=3,料金元データ!J35,IF($C14=4,料金元データ!J42,IF($C14=5,料金元データ!J49,IF($C14=6,料金元データ!J56))))))*(1-$J$10),-1) -> 0 | K14: =ROUNDDOWN(IF($C14=1,料金元データ!K21,IF($C14=2,料金元データ!K28,IF($C14=3,料金元データ!K35,IF($C14=4,料金元データ!K42,IF($C14=5,料金元データ!K49,IF($C14=6,料金元データ!K56))))))*(1-$J$10),-1) -> 0 | ... AF14: =ROUNDDOWN(IF($C14=1,料金元データ!AF21,IF($C14=2,料金元データ!AF28,IF($C14=3,料金元データ!AF35,IF($C14=4,料金元データ!AF42,IF($C14=5,料金元データ!AF49,IF($C14=6,料金元データ!AF56))))))*(1-$J$10),-1) -> 0
B15: =カレンダー!B6 -> 0 | C15: 2 | D15: =ROUNDDOWN(IF($C15=1,料金元データ!D22,IF($C15=2,料金元データ!D29,IF($C15=3,料金元データ!D36,IF($C15=4,料金元データ!D43,IF($C15=5,料金元データ!D50,IF($C15=6,料金元データ!D57))))))*(1-$J$10),-1) -> 0 | E15: =ROUNDDOWN(IF($C15=1,料金元データ!E22,IF($C15=2,料金元データ!E29,IF($C15=3,料金元データ!E36,IF($C15=4,料金元データ!E43,IF($C15=5,料金元データ!E50,IF($C15=6,料金元データ!E57))))))*(1-$J$10),-1) -> 0 | F15: =ROUNDDOWN(IF($C15=1,料金元データ!F22,IF($C15=2,料金元データ!F29,IF($C15=3,料金元データ!F36,IF($C15=4,料金元データ!F43,IF($C15=5,料金元データ!F50,IF($C15=6,料金元データ!F57))))))*(1-$J$10),-1) -> 0 | G15: =ROUNDDOWN(IF($C15=1,料金元データ!G22,IF($C15=2,料金元データ!G29,IF($C15=3,料金元データ!G36,IF($C15=4,料金元データ!G43,IF($C15=5,料金元データ!G50,IF($C15=6,料金元データ!G57))))))*(1-$J$10),-1) -> 0 | H15: =ROUNDDOWN(IF($C15=1,料金元データ!H22,IF($C15=2,料金元データ!H29,IF($C15=3,料金元データ!H36,IF($C15=4,料金元データ!H43,IF($C15=5,料金元データ!H50,IF($C15=6,料金元データ!H57))))))*(1-$J$10),-1) -> 0 | I15: =ROUNDDOWN(IF($C15=1,料金元データ!I22,IF($C15=2,料金元データ!I29,IF($C15=3,料金元データ!I36,IF($C15=4,料金元データ!I43,IF($C15=5,料金元データ!I50,IF($C15=6,料金元データ!I57))))))*(1-$J$10),-1) -> 0 | J15: =ROUNDDOWN(IF($C15=1,料金元データ!J22,IF($C15=2,料金元データ!J29,IF($C15=3,料金元データ!J36,IF($C15=4,料金元データ!J43,IF($C15=5,料金元データ!J50,IF($C15=6,料金元データ!J57))))))*(1-$J$10),-1) -> 0 | K15: =ROUNDDOWN(IF($C15=1,料金元データ!K22,IF($C15=2,料金元データ!K29,IF($C15=3,料金元データ!K36,IF($C15=4,料金元データ!K43,IF($C15=5,料金元データ!K50,IF($C15=6,料金元データ!K57))))))*(1-$J$10),-1) -> 0 | ... AF15: =ROUNDDOWN(IF($C15=1,料金元データ!AF22,IF($C15=2,料金元データ!AF29,IF($C15=3,料金元データ!AF36,IF($C15=4,料金元データ!AF43,IF($C15=5,料金元データ!AF50,IF($C15=6,料金元データ!AF57))))))*(1-$J$10),-1) -> 0
B16: =カレンダー!B7 -> 0 | C16: 3 | D16: =ROUNDDOWN(IF($C16=1,料金元データ!D23,IF($C16=2,料金元データ!D30,IF($C16=3,料金元データ!D37,IF($C16=4,料金元データ!D44,IF($C16=5,料金元データ!D51,IF($C16=6,料金元データ!D58))))))*(1-$J$10),-1) -> 0 | E16: =ROUNDDOWN(IF($C16=1,料金元データ!E23,IF($C16=2,料金元データ!E30,IF($C16=3,料金元データ!E37,IF($C16=4,料金元データ!E44,IF($C16=5,料金元データ!E51,IF($C16=6,料金元データ!E58))))))*(1-$J$10),-1) -> 0 | F16: =ROUNDDOWN(IF($C16=1,料金元データ!F23,IF($C16=2,料金元データ!F30,IF($C16=3,料金元データ!F37,IF($C16=4,料金元データ!F44,IF($C16=5,料金元データ!F51,IF($C16=6,料金元データ!F58))))))*(1-$J$10),-1) -> 0 | G16: =ROUNDDOWN(IF($C16=1,料金元データ!G23,IF($C16=2,料金元データ!G30,IF($C16=3,料金元データ!G37,IF($C16=4,料金元データ!G44,IF($C16=5,料金元データ!G51,IF($C16=6,料金元データ!G58))))))*(1-$J$10),-1) -> 0 | H16: =ROUNDDOWN(IF($C16=1,料金元データ!H23,IF($C16=2,料金元データ!H30,IF($C16=3,料金元データ!H37,IF($C16=4,料金元データ!H44,IF($C16=5,料金元データ!H51,IF($C16=6,料金元データ!H58))))))*(1-$J$10),-1) -> 0 | I16: =ROUNDDOWN(IF($C16=1,料金元データ!I23,IF($C16=2,料金元データ!I30,IF($C16=3,料金元データ!I37,IF($C16=4,料金元データ!I44,IF($C16=5,料金元データ!I51,IF($C16=6,料金元データ!I58))))))*(1-$J$10),-1) -> 0 | J16: =ROUNDDOWN(IF($C16=1,料金元データ!J23,IF($C16=2,料金元データ!J30,IF($C16=3,料金元データ!J37,IF($C16=4,料金元データ!J44,IF($C16=5,料金元データ!J51,IF($C16=6,料金元データ!J58))))))*(1-$J$10),-1) -> 0 | K16: =ROUNDDOWN(IF($C16=1,料金元データ!K23,IF($C16=2,料金元データ!K30,IF($C16=3,料金元データ!K37,IF($C16=4,料金元データ!K44,IF($C16=5,料金元データ!K51,IF($C16=6,料金元データ!K58))))))*(1-$J$10),-1) -> 0 | ... AF16: =ROUNDDOWN(IF($C16=1,料金元データ!AF23,IF($C16=2,料金元データ!AF30,IF($C16=3,料金元データ!AF37,IF($C16=4,料金元データ!AF44,IF($C16=5,料金元データ!AF51,IF($C16=6,料金元データ!AF58))))))*(1-$J$10),-1) -> 0
B17: =カレンダー!B8 -> 0 | C17: 4 | D17: =ROUNDDOWN(IF($C17=1,料金元データ!D24,IF($C17=2,料金元データ!D31,IF($C17=3,料金元データ!D38,IF($C17=4,料金元データ!D45,IF($C17=5,料金元データ!D52,IF($C17=6,料金元データ!D59))))))*(1-$J$10),-1) -> 0 | E17: =ROUNDDOWN(IF($C17=1,料金元データ!E24,IF($C17=2,料金元データ!E31,IF($C17=3,料金元データ!E38,IF($C17=4,料金元データ!E45,IF($C17=5,料金元データ!E52,IF($C17=6,料金元データ!E59))))))*(1-$J$10),-1) -> 0 | F17: =ROUNDDOWN(IF($C17=1,料金元データ!F24,IF($C17=2,料金元データ!F31,IF($C17=3,料金元データ!F38,IF($C17=4,料金元データ!F45,IF($C17=5,料金元データ!F52,IF($C17=6,料金元データ!F59))))))*(1-$J$10),-1) -> 0 | G17: =ROUNDDOWN(IF($C17=1,料金元データ!G24,IF($C17=2,料金元データ!G31,IF($C17=3,料金元データ!G38,IF($C17=4,料金元データ!G45,IF($C17=5,料金元データ!G52,IF($C17=6,料金元データ!G59))))))*(1-$J$10),-1) -> 0 | H17: =ROUNDDOWN(IF($C17=1,料金元データ!H24,IF($C17=2,料金元データ!H31,IF($C17=3,料金元データ!H38,IF($C17=4,料金元データ!H45,IF($C17=5,料金元データ!H52,IF($C17=6,料金元データ!H59))))))*(1-$J$10),-1) -> 0 | I17: =ROUNDDOWN(IF($C17=1,料金元データ!I24,IF($C17=2,料金元データ!I31,IF($C17=3,料金元データ!I38,IF($C17=4,料金元データ!I45,IF($C17=5,料金元データ!I52,IF($C17=6,料金元データ!I59))))))*(1-$J$10),-1) -> 0 | J17: =ROUNDDOWN(IF($C17=1,料金元データ!J24,IF($C17=2,料金元データ!J31,IF($C17=3,料金元データ!J38,IF($C17=4,料金元データ!J45,IF($C17=5,料金元データ!J52,IF($C17=6,料金元データ!J59))))))*(1-$J$10),-1) -> 0 | K17: =ROUNDDOWN(IF($C17=1,料金元データ!K24,IF($C17=2,料金元データ!K31,IF($C17=3,料金元データ!K38,IF($C17=4,料金元データ!K45,IF($C17=5,料金元データ!K52,IF($C17=6,料金元データ!K59))))))*(1-$J$10),-1) -> 0 | ... AF17: =ROUNDDOWN(IF($C17=1,料金元データ!AF24,IF($C17=2,料金元データ!AF31,IF($C17=3,料金元データ!AF38,IF($C17=4,料金元データ!AF45,IF($C17=5,料金元データ!AF52,IF($C17=6,料金元データ!AF59))))))*(1-$J$10),-1) -> 0
C19: 在庫調整欄 | D19: =IFERROR(IF((D29-在庫!$B$1+1)<0,0,(D29-在庫!$B$1)+2),"") -> 0 | E19: =IFERROR(IF((E29-在庫!$B$1+1)<0,0,(E29-在庫!$B$1)+2),"") -> 0 | F19: =IFERROR(IF((F29-在庫!$B$1+1)<0,0,(F29-在庫!$B$1)+2),"") -> 0 | G19: =IFERROR(IF((G29-在庫!$B$1+1)<0,0,(G29-在庫!$B$1)+2),"") -> 0 | H19: =IFERROR(IF((H29-在庫!$B$1+1)<0,0,(H29-在庫!$B$1)+2),"") -> 0 | I19: =IFERROR(IF((I29-在庫!$B$1+1)<0,0,(I29-在庫!$B$1)+2),"") -> 0 | J19: =IFERROR(IF((J29-在庫!$B$1+1)<0,0,(J29-在庫!$B$1)+2),"") -> 0 | K19: =IFERROR(IF((K29-在庫!$B$1+1)<0,0,(K29-在庫!$B$1)+2),"") -> 0 | ... AH19: =IFERROR(IF((AH29-在庫!$B$1+1)<0,0,(AH29-在庫!$B$1)+2),"") -> 0
B20: =RIGHT(CELL("filename",A1),LEN(CELL("filename",A1))-FIND("]",CELL("filename",A1))) -> 2025年8月 | C20: 宿泊者数予測 | D20: =IFERROR(INDEX(カレンダーデータ!$I$4:$K$2000,MATCH(D$29,カレンダーデータ!$H$4:$H$2000,0),MATCH($C$20,カレンダーデータ!$I$3:$K$3,0)),"No Data") -> 74449 | E20: =IFERROR(INDEX(カレンダーデータ!$I$4:$K$2000,MATCH(E$29,カレンダーデータ!$H$4:$H$2000,0),MATCH($C$20,カレンダーデータ!$I$3:$K$3,0)),"No Data") -> 76981 | F20: =IFERROR(INDEX(カレンダーデータ!$I$4:$K$2000,MATCH(F$29,カレンダーデータ!$H$4:$H$2000,0),MATCH($C$20,カレンダーデータ!$I$3:$K$3,0)),"No Data") -> 76214 | G20: =IFERROR(INDEX(カレンダーデータ!$I$4:$K$2000,MATCH(G$29,カレンダーデータ!$H$4:$H$2000,0),MATCH($C$20,カレンダーデータ!$I$3:$K$3,0)),"No Data") -> 76626 | H20: =IFERROR(INDEX(カレンダーデータ!$I$4:$K$2000,MATCH(H$29,カレンダーデータ!$H$4:$H$2000,0),MATCH($C$20,カレンダーデータ!$I$3:$K$3,0)),"No Data") -> 71534 | I20: =IFERROR(INDEX(カレンダーデータ!$I$4:$K$2000,MATCH(I$29,カレンダーデータ!$H$4:$H$2000,0),MATCH($C$20,カレンダーデータ!$I$3:$K$3,0)),"No Data") -> 64854 | J20: =IFERROR(INDEX(カレンダーデータ!$I$4:$K$2000,MATCH(J$29,カレンダーデータ!$H$4:$H$2000,0),MATCH($C$20,カレンダーデータ!$I$3:$K$3,0)),"No Data") -> 62868 | K20: =IFERROR(INDEX(カレンダーデータ!$I$4:$K$2000,MATCH(K$29,カレンダーデータ!$H$4:$H$2000,0),MATCH($C$20,カレンダーデータ!$I$3:$K$3,0)),"No Data") -> 71070 | ... AH20: =IFERROR(INDEX(カレンダーデータ!$I$4:$K$2000,MATCH(AH$29,カレンダーデータ!$H$4:$H$2000,0),MATCH($C$20,カレンダーデータ!$I$3:$K$3,0)),"No Data") -> 78665
C21: 進捗 | D21: =IFERROR(INDEX(カレンダーデータ!$I$4:$K$2000,MATCH(D$29,カレンダーデータ!$H$4:$H$2000,0),MATCH($C$21,カレンダーデータ!$I$3:$K$3,0)),"No Data") -> 1.1173689 | E21: =IFERROR(INDEX(カレンダーデータ!$I$4:$K$2000,MATCH(E$29,カレンダーデータ!$H$4:$H$2000,0),MATCH($C$21,カレンダーデータ!$I$3:$K$3,0)),"No Data") -> 1.159299 | F21: =IFERROR(INDEX(カレンダーデータ!$I$4:$K$2000,MATCH(F$29,カレンダーデータ!$H$4:$H$2000,0),MATCH($C$21,カレンダーデータ!$I$3:$K$3,0)),"No Data") -> 1.1564017 | G21: =IFERROR(INDEX(カレンダーデータ!$I$4:$K$2000,MATCH(G$29,カレンダーデータ!$H$4:$H$2000,0),MATCH($C$21,カレンダーデータ!$I$3:$K$3,0)),"No Data") -> 1.2447472 | H21: =IFERROR(INDEX(カレンダーデータ!$I$4:$K$2000,MATCH(H$29,カレンダーデータ!$H$4:$H$2000,0),MATCH($C$21,カレンダーデータ!$I$3:$K$3,0)),"No Data") -> 1.2029944 | I21: =IFERROR(INDEX(カレンダーデータ!$I$4:$K$2000,MATCH(I$29,カレンダーデータ!$H$4:$H$2000,0),MATCH($C$21,カレンダーデータ!$I$3:$K$3,0)),"No Data") -> 1.2038733 | J21: =IFERROR(INDEX(カレンダーデータ!$I$4:$K$2000,MATCH(J$29,カレンダーデータ!$H$4:$H$2000,0),MATCH($C$21,カレンダーデータ!$I$3:$K$3,0)),"No Data") -> 1.181889 | K21: =IFERROR(INDEX(カレンダーデータ!$I$4:$K$2000,MATCH(K$29,カレンダーデータ!$H$4:$H$2000,0),MATCH($C$21,カレンダーデータ!$I$3:$K$3,0)),"No Data") -> 1.1626565 | ... AH21: =IFERROR(INDEX(カレンダーデータ!$I$4:$K$2000,MATCH(AH$29,カレンダーデータ!$H$4:$H$2000,0),MATCH($C$21,カレンダーデータ!$I$3:$K$3,0)),"No Data") -> 0.84388229
C22: 日本の祝日 | D22: =IFERROR(INDEX(カレンダーデータ!$C$4:$C$22,MATCH(D$29,カレンダーデータ!$B$4:$B$368,0),MATCH($C$22,カレンダーデータ!$C$3,0)),"") | E22: =IFERROR(INDEX(カレンダーデータ!$C$4:$C$22,MATCH(E$29,カレンダーデータ!$B$4:$B$368,0),MATCH($C$22,カレンダーデータ!$C$3,0)),"") | F22: =IFERROR(INDEX(カレンダーデータ!$C$4:$C$22,MATCH(F$29,カレンダーデータ!$B$4:$B$368,0),MATCH($C$22,カレンダーデータ!$C$3,0)),"") | G22: =IFERROR(INDEX(カレンダーデータ!$C$4:$C$22,MATCH(G$29,カレンダーデータ!$B$4:$B$368,0),MATCH($C$22,カレンダーデータ!$C$3,0)),"") | H22: =IFERROR(INDEX(カレンダーデータ!$C$4:$C$22,MATCH(H$29,カレンダーデータ!$B$4:$B$368,0),MATCH($C$22,カレンダーデータ!$C$3,0)),"") | I22: =IFERROR(INDEX(カレンダーデータ!$C$4:$C$22,MATCH(I$29,カレンダーデータ!$B$4:$B$368,0),MATCH($C$22,カレンダーデータ!$C$3,0)),"") | J22: =IFERROR(INDEX(カレンダーデータ!$C$4:$C$22,MATCH(J$29,カレンダーデータ!$B$4:$B$368,0),MATCH($C$22,カレンダーデータ!$C$3,0)),"") | K22: =IFERROR(INDEX(カレンダーデータ!$C$4:$C$22,MATCH(K$29,カレンダーデータ!$B$4:$B$368,0),MATCH($C$22,カレンダーデータ!$C$3,0)),"") | ... AH22: =IFERROR(INDEX(カレンダーデータ!$C$4:$C$22,MATCH(AH$29,カレンダーデータ!$B$4:$B$368,0),MATCH($C$22,カレンダーデータ!$C$3,0)),"")
C23: 海外の祝日 | D23: =IFERROR(INDEX(カレンダーデータ!$F$4:$F$368,MATCH(D$29,カレンダーデータ!$E$4:$E$368,0),MATCH($C$23,カレンダーデータ!$F$3,0)),"") | E23: =IFERROR(INDEX(カレンダーデータ!$F$4:$F$368,MATCH(E$29,カレンダーデータ!$E$4:$E$368,0),MATCH($C$23,カレンダーデータ!$F$3,0)),"") | F23: =IFERROR(INDEX(カレンダーデータ!$F$4:$F$368,MATCH(F$29,カレンダーデータ!$E$4:$E$368,0),MATCH($C$23,カレンダーデータ!$F$3,0)),"") | G23: =IFERROR(INDEX(カレンダーデータ!$F$4:$F$368,MATCH(G$29,カレンダーデータ!$E$4:$E$368,0),MATCH($C$23,カレンダーデータ!$F$3,0)),"") | H23: =IFERROR(INDEX(カレンダーデータ!$F$4:$F$368,MATCH(H$29,カレンダーデータ!$E$4:$E$368,0),MATCH($C$23,カレンダーデータ!$F$3,0)),"") | I23: =IFERROR(INDEX(カレンダーデータ!$F$4:$F$368,MATCH(I$29,カレンダーデータ!$E$4:$E$368,0),MATCH($C$23,カレンダーデータ!$F$3,0)),"") | J23: =IFERROR(INDEX(カレンダーデータ!$F$4:$F$368,MATCH(J$29,カレンダーデータ!$E$4:$E$368,0),MATCH($C$23,カレンダーデータ!$F$3,0)),"") | K23: =IFERROR(INDEX(カレンダーデータ!$F$4:$F$368,MATCH(K$29,カレンダーデータ!$E$4:$E$368,0),MATCH($C$23,カレンダーデータ!$F$3,0)),"") | ... AH23: =IFERROR(INDEX(カレンダーデータ!$F$4:$F$368,MATCH(AH$29,カレンダーデータ!$E$4:$E$368,0),MATCH($C$23,カレンダーデータ!$F$3,0)),"")
C24: 北部イベント① | D24: =IFERROR(IF(ISBLANK(INDEX(カレンダーデータ!$N$4:$R$368,MATCH(D$29,カレンダーデータ!$M$4:$M$368,0),MATCH($C24,カレンダーデータ!$N$3:$R$3,0))),"",INDEX(カレンダーデータ!$N$4:$R$368,MATCH(D$29,カレンダーデータ!$M$4:$M$368,0),MATCH($C24,カレンダーデータ!$N$3:$R$3,0))),"") | E24: =IFERROR(IF(ISBLANK(INDEX(カレンダーデータ!$N$4:$R$368,MATCH(E$29,カレンダーデータ!$M$4:$M$368,0),MATCH($C24,カレンダーデータ!$N$3:$R$3,0))),"",INDEX(カレンダーデータ!$N$4:$R$368,MATCH(E$29,カレンダーデータ!$M$4:$M$368,0),MATCH($C24,カレンダーデータ!$N$3:$R$3,0))),"") | F24: =IFERROR(IF(ISBLANK(INDEX(カレンダーデータ!$N$4:$R$368,MATCH(F$29,カレンダーデータ!$M$4:$M$368,0),MATCH($C24,カレンダーデータ!$N$3:$R$3,0))),"",INDEX(カレンダーデータ!$N$4:$R$368,MATCH(F$29,カレンダーデータ!$M$4:$M$368,0),MATCH($C24,カレンダーデータ!$N$3:$R$3,0))),"") | G24: =IFERROR(IF(ISBLANK(INDEX(カレンダーデータ!$N$4:$R$368,MATCH(G$29,カレンダーデータ!$M$4:$M$368,0),MATCH($C24,カレンダーデータ!$N$3:$R$3,0))),"",INDEX(カレンダーデータ!$N$4:$R$368,MATCH(G$29,カレンダーデータ!$M$4:$M$368,0),MATCH($C24,カレンダーデータ!$N$3:$R$3,0))),"") | H24: =IFERROR(IF(ISBLANK(INDEX(カレンダーデータ!$N$4:$R$368,MATCH(H$29,カレンダーデータ!$M$4:$M$368,0),MATCH($C24,カレンダーデータ!$N$3:$R$3,0))),"",INDEX(カレンダーデータ!$N$4:$R$368,MATCH(H$29,カレンダーデータ!$M$4:$M$368,0),MATCH($C24,カレンダーデータ!$N$3:$R$3,0))),"") | I24: =IFERROR(IF(ISBLANK(INDEX(カレンダーデータ!$N$4:$R$368,MATCH(I$29,カレンダーデータ!$M$4:$M$368,0),MATCH($C24,カレンダーデータ!$N$3:$R$3,0))),"",INDEX(カレンダーデータ!$N$4:$R$368,MATCH(I$29,カレンダーデータ!$M$4:$M$368,0),MATCH($C24,カレンダーデータ!$N$3:$R$3,0))),"") | J24: =IFERROR(IF(ISBLANK(INDEX(カレンダーデータ!$N$4:$R$368,MATCH(J$29,カレンダーデータ!$M$4:$M$368,0),MATCH($C24,カレンダーデータ!$N$3:$R$3,0))),"",INDEX(カレンダーデータ!$N$4:$R$368,MATCH(J$29,カレンダーデータ!$M$4:$M$368,0),MATCH($C24,カレンダーデータ!$N$3:$R$3,0))),"") | K24: =IFERROR(IF(ISBLANK(INDEX(カレンダーデータ!$N$4:$R$368,MATCH(K$29,カレンダーデータ!$M$4:$M$368,0),MATCH($C24,カレンダーデータ!$N$3:$R$3,0))),"",INDEX(カレンダーデータ!$N$4:$R$368,MATCH(K$29,カレンダーデータ!$M$4:$M$368,0),MATCH($C24,カレンダーデータ!$N$3:$R$3,0))),"") | ... AH24: =IFERROR(IF(ISBLANK(INDEX(カレンダーデータ!$N$4:$R$368,MATCH(AH$29,カレンダーデータ!$M$4:$M$368,0),MATCH($C24,カレンダーデータ!$N$3:$R$3,0))),"",INDEX(カレンダーデータ!$N$4:$R$368,MATCH(AH$29,カレンダーデータ!$M$4:$M$368,0),MATCH($C24,カレンダーデータ!$N$3:$R$3,0))),"")
C25: 北部イベント② | D25: =IFERROR(IF(ISBLANK(INDEX(カレンダーデータ!$N$4:$R$368,MATCH(D$29,カレンダーデータ!$M$4:$M$368,0),MATCH($C25,カレンダーデータ!$N$3:$R$3,0))),"",INDEX(カレンダーデータ!$N$4:$R$368,MATCH(D$29,カレンダーデータ!$M$4:$M$368,0),MATCH($C25,カレンダーデータ!$N$3:$R$3,0))),"") | E25: =IFERROR(IF(ISBLANK(INDEX(カレンダーデータ!$N$4:$R$368,MATCH(E$29,カレンダーデータ!$M$4:$M$368,0),MATCH($C25,カレンダーデータ!$N$3:$R$3,0))),"",INDEX(カレンダーデータ!$N$4:$R$368,MATCH(E$29,カレンダーデータ!$M$4:$M$368,0),MATCH($C25,カレンダーデータ!$N$3:$R$3,0))),"") | F25: =IFERROR(IF(ISBLANK(INDEX(カレンダーデータ!$N$4:$R$368,MATCH(F$29,カレンダーデータ!$M$4:$M$368,0),MATCH($C25,カレンダーデータ!$N$3:$R$3,0))),"",INDEX(カレンダーデータ!$N$4:$R$368,MATCH(F$29,カレンダーデータ!$M$4:$M$368,0),MATCH($C25,カレンダーデータ!$N$3:$R$3,0))),"") | G25: =IFERROR(IF(ISBLANK(INDEX(カレンダーデータ!$N$4:$R$368,MATCH(G$29,カレンダーデータ!$M$4:$M$368,0),MATCH($C25,カレンダーデータ!$N$3:$R$3,0))),"",INDEX(カレンダーデータ!$N$4:$R$368,MATCH(G$29,カレンダーデータ!$M$4:$M$368,0),MATCH($C25,カレンダーデータ!$N$3:$R$3,0))),"") | H25: =IFERROR(IF(ISBLANK(INDEX(カレンダーデータ!$N$4:$R$368,MATCH(H$29,カレンダーデータ!$M$4:$M$368,0),MATCH($C25,カレンダーデータ!$N$3:$R$3,0))),"",INDEX(カレンダーデータ!$N$4:$R$368,MATCH(H$29,カレンダーデータ!$M$4:$M$368,0),MATCH($C25,カレンダーデータ!$N$3:$R$3,0))),"") | I25: =IFERROR(IF(ISBLANK(INDEX(カレンダーデータ!$N$4:$R$368,MATCH(I$29,カレンダーデータ!$M$4:$M$368,0),MATCH($C25,カレンダーデータ!$N$3:$R$3,0))),"",INDEX(カレンダーデータ!$N$4:$R$368,MATCH(I$29,カレンダーデータ!$M$4:$M$368,0),MATCH($C25,カレンダーデータ!$N$3:$R$3,0))),"") | J25: =IFERROR(IF(ISBLANK(INDEX(カレンダーデータ!$N$4:$R$368,MATCH(J$29,カレンダーデータ!$M$4:$M$368,0),MATCH($C25,カレンダーデータ!$N$3:$R$3,0))),"",INDEX(カレンダーデータ!$N$4:$R$368,MATCH(J$29,カレンダーデータ!$M$4:$M$368,0),MATCH($C25,カレンダーデータ!$N$3:$R$3,0))),"") | K25: =IFERROR(IF(ISBLANK(INDEX(カレンダーデータ!$N$4:$R$368,MATCH(K$29,カレンダーデータ!$M$4:$M$368,0),MATCH($C25,カレンダーデータ!$N$3:$R$3,0))),"",INDEX(カレンダーデータ!$N$4:$R$368,MATCH(K$29,カレンダーデータ!$M$4:$M$368,0),MATCH($C25,カレンダーデータ!$N$3:$R$3,0))),"") | ... AH25: =IFERROR(IF(ISBLANK(INDEX(カレンダーデータ!$N$4:$R$368,MATCH(AH$29,カレンダーデータ!$M$4:$M$368,0),MATCH($C25,カレンダーデータ!$N$3:$R$3,0))),"",INDEX(カレンダーデータ!$N$4:$R$368,MATCH(AH$29,カレンダーデータ!$M$4:$M$368,0),MATCH($C25,カレンダーデータ!$N$3:$R$3,0))),"")
C26: 北部イベント③ | D26: =IFERROR(IF(ISBLANK(INDEX(カレンダーデータ!$N$4:$R$368,MATCH(D$29,カレンダーデータ!$M$4:$M$368,0),MATCH($C26,カレンダーデータ!$N$3:$R$3,0))),"",INDEX(カレンダーデータ!$N$4:$R$368,MATCH(D$29,カレンダーデータ!$M$4:$M$368,0),MATCH($C26,カレンダーデータ!$N$3:$R$3,0))),"") | E26: =IFERROR(IF(ISBLANK(INDEX(カレンダーデータ!$N$4:$R$368,MATCH(E$29,カレンダーデータ!$M$4:$M$368,0),MATCH($C26,カレンダーデータ!$N$3:$R$3,0))),"",INDEX(カレンダーデータ!$N$4:$R$368,MATCH(E$29,カレンダーデータ!$M$4:$M$368,0),MATCH($C26,カレンダーデータ!$N$3:$R$3,0))),"") | F26: =IFERROR(IF(ISBLANK(INDEX(カレンダーデータ!$N$4:$R$368,MATCH(F$29,カレンダーデータ!$M$4:$M$368,0),MATCH($C26,カレンダーデータ!$N$3:$R$3,0))),"",INDEX(カレンダーデータ!$N$4:$R$368,MATCH(F$29,カレンダーデータ!$M$4:$M$368,0),MATCH($C26,カレンダーデータ!$N$3:$R$3,0))),"") | G26: =IFERROR(IF(ISBLANK(INDEX(カレンダーデータ!$N$4:$R$368,MATCH(G$29,カレンダーデータ!$M$4:$M$368,0),MATCH($C26,カレンダーデータ!$N$3:$R$3,0))),"",INDEX(カレンダーデータ!$N$4:$R$368,MATCH(G$29,カレンダーデータ!$M$4:$M$368,0),MATCH($C26,カレンダーデータ!$N$3:$R$3,0))),"") | H26: =IFERROR(IF(ISBLANK(INDEX(カレンダーデータ!$N$4:$R$368,MATCH(H$29,カレンダーデータ!$M$4:$M$368,0),MATCH($C26,カレンダーデータ!$N$3:$R$3,0))),"",INDEX(カレンダーデータ!$N$4:$R$368,MATCH(H$29,カレンダーデータ!$M$4:$M$368,0),MATCH($C26,カレンダーデータ!$N$3:$R$3,0))),"") | I26: =IFERROR(IF(ISBLANK(INDEX(カレンダーデータ!$N$4:$R$368,MATCH(I$29,カレンダーデータ!$M$4:$M$368,0),MATCH($C26,カレンダーデータ!$N$3:$R$3,0))),"",INDEX(カレンダーデータ!$N$4:$R$368,MATCH(I$29,カレンダーデータ!$M$4:$M$368,0),MATCH($C26,カレンダーデータ!$N$3:$R$3,0))),"") | J26: =IFERROR(IF(ISBLANK(INDEX(カレンダーデータ!$N$4:$R$368,MATCH(J$29,カレンダーデータ!$M$4:$M$368,0),MATCH($C26,カレンダーデータ!$N$3:$R$3,0))),"",INDEX(カレンダーデータ!$N$4:$R$368,MATCH(J$29,カレンダーデータ!$M$4:$M$368,0),MATCH($C26,カレンダーデータ!$N$3:$R$3,0))),"") | K26: =IFERROR(IF(ISBLANK(INDEX(カレンダーデータ!$N$4:$R$368,MATCH(K$29,カレンダーデータ!$M$4:$M$368,0),MATCH($C26,カレンダーデータ!$N$3:$R$3,0))),"",INDEX(カレンダーデータ!$N$4:$R$368,MATCH(K$29,カレンダーデータ!$M$4:$M$368,0),MATCH($C26,カレンダーデータ!$N$3:$R$3,0))),"") | ... AH26: =IFERROR(IF(ISBLANK(INDEX(カレンダーデータ!$N$4:$R$368,MATCH(AH$29,カレンダーデータ!$M$4:$M$368,0),MATCH($C26,カレンダーデータ!$N$3:$R$3,0))),"",INDEX(カレンダーデータ!$N$4:$R$368,MATCH(AH$29,カレンダーデータ!$M$4:$M$368,0),MATCH($C26,カレンダーデータ!$N$3:$R$3,0))),"")
C27: 北部イベント④ | D27: =IFERROR(IF(ISBLANK(INDEX(カレンダーデータ!$N$4:$R$368,MATCH(D$29,カレンダーデータ!$M$4:$M$368,0),MATCH($C27,カレンダーデータ!$N$3:$R$3,0))),"",INDEX(カレンダーデータ!$N$4:$R$368,MATCH(D$29,カレンダーデータ!$M$4:$M$368,0),MATCH($C27,カレンダーデータ!$N$3:$R$3,0))),"") | E27: =IFERROR(IF(ISBLANK(INDEX(カレンダーデータ!$N$4:$R$368,MATCH(E$29,カレンダーデータ!$M$4:$M$368,0),MATCH($C27,カレンダーデータ!$N$3:$R$3,0))),"",INDEX(カレンダーデータ!$N$4:$R$368,MATCH(E$29,カレンダーデータ!$M$4:$M$368,0),MATCH($C27,カレンダーデータ!$N$3:$R$3,0))),"") | F27: =IFERROR(IF(ISBLANK(INDEX(カレンダーデータ!$N$4:$R$368,MATCH(F$29,カレンダーデータ!$M$4:$M$368,0),MATCH($C27,カレンダーデータ!$N$3:$R$3,0))),"",INDEX(カレンダーデータ!$N$4:$R$368,MATCH(F$29,カレンダーデータ!$M$4:$M$368,0),MATCH($C27,カレンダーデータ!$N$3:$R$3,0))),"") | G27: =IFERROR(IF(ISBLANK(INDEX(カレンダーデータ!$N$4:$R$368,MATCH(G$29,カレンダーデータ!$M$4:$M$368,0),MATCH($C27,カレンダーデータ!$N$3:$R$3,0))),"",INDEX(カレンダーデータ!$N$4:$R$368,MATCH(G$29,カレンダーデータ!$M$4:$M$368,0),MATCH($C27,カレンダーデータ!$N$3:$R$3,0))),"") | H27: =IFERROR(IF(ISBLANK(INDEX(カレンダーデータ!$N$4:$R$368,MATCH(H$29,カレンダーデータ!$M$4:$M$368,0),MATCH($C27,カレンダーデータ!$N$3:$R$3,0))),"",INDEX(カレンダーデータ!$N$4:$R$368,MATCH(H$29,カレンダーデータ!$M$4:$M$368,0),MATCH($C27,カレンダーデータ!$N$3:$R$3,0))),"") | I27: =IFERROR(IF(ISBLANK(INDEX(カレンダーデータ!$N$4:$R$368,MATCH(I$29,カレンダーデータ!$M$4:$M$368,0),MATCH($C27,カレンダーデータ!$N$3:$R$3,0))),"",INDEX(カレンダーデータ!$N$4:$R$368,MATCH(I$29,カレンダーデータ!$M$4:$M$368,0),MATCH($C27,カレンダーデータ!$N$3:$R$3,0))),"") | J27: =IFERROR(IF(ISBLANK(INDEX(カレンダーデータ!$N$4:$R$368,MATCH(J$29,カレンダーデータ!$M$4:$M$368,0),MATCH($C27,カレンダーデータ!$N$3:$R$3,0))),"",INDEX(カレンダーデータ!$N$4:$R$368,MATCH(J$29,カレンダーデータ!$M$4:$M$368,0),MATCH($C27,カレンダーデータ!$N$3:$R$3,0))),"") | K27: =IFERROR(IF(ISBLANK(INDEX(カレンダーデータ!$N$4:$R$368,MATCH(K$29,カレンダーデータ!$M$4:$M$368,0),MATCH($C27,カレンダーデータ!$N$3:$R$3,0))),"",INDEX(カレンダーデータ!$N$4:$R$368,MATCH(K$29,カレンダーデータ!$M$4:$M$368,0),MATCH($C27,カレンダーデータ!$N$3:$R$3,0))),"") | ... AH27: =IFERROR(IF(ISBLANK(INDEX(カレンダーデータ!$N$4:$R$368,MATCH(AH$29,カレンダーデータ!$M$4:$M$368,0),MATCH($C27,カレンダーデータ!$N$3:$R$3,0))),"",INDEX(カレンダーデータ!$N$4:$R$368,MATCH(AH$29,カレンダーデータ!$M$4:$M$368,0),MATCH($C27,カレンダーデータ!$N$3:$R$3,0))),"")
C28: 北部イベント⑤ | D28: =IFERROR(IF(ISBLANK(INDEX(カレンダーデータ!$N$4:$R$368,MATCH(D$29,カレンダーデータ!$M$4:$M$368,0),MATCH($C28,カレンダーデータ!$N$3:$R$3,0))),"",INDEX(カレンダーデータ!$N$4:$R$368,MATCH(D$29,カレンダーデータ!$M$4:$M$368,0),MATCH($C28,カレンダーデータ!$N$3:$R$3,0))),"") | E28: =IFERROR(IF(ISBLANK(INDEX(カレンダーデータ!$N$4:$R$368,MATCH(E$29,カレンダーデータ!$M$4:$M$368,0),MATCH($C28,カレンダーデータ!$N$3:$R$3,0))),"",INDEX(カレンダーデータ!$N$4:$R$368,MATCH(E$29,カレンダーデータ!$M$4:$M$368,0),MATCH($C28,カレンダーデータ!$N$3:$R$3,0))),"") | F28: =IFERROR(IF(ISBLANK(INDEX(カレンダーデータ!$N$4:$R$368,MATCH(F$29,カレンダーデータ!$M$4:$M$368,0),MATCH($C28,カレンダーデータ!$N$3:$R$3,0))),"",INDEX(カレンダーデータ!$N$4:$R$368,MATCH(F$29,カレンダーデータ!$M$4:$M$368,0),MATCH($C28,カレンダーデータ!$N$3:$R$3,0))),"") | G28: =IFERROR(IF(ISBLANK(INDEX(カレンダーデータ!$N$4:$R$368,MATCH(G$29,カレンダーデータ!$M$4:$M$368,0),MATCH($C28,カレンダーデータ!$N$3:$R$3,0))),"",INDEX(カレンダーデータ!$N$4:$R$368,MATCH(G$29,カレンダーデータ!$M$4:$M$368,0),MATCH($C28,カレンダーデータ!$N$3:$R$3,0))),"") | H28: =IFERROR(IF(ISBLANK(INDEX(カレンダーデータ!$N$4:$R$368,MATCH(H$29,カレンダーデータ!$M$4:$M$368,0),MATCH($C28,カレンダーデータ!$N$3:$R$3,0))),"",INDEX(カレンダーデータ!$N$4:$R$368,MATCH(H$29,カレンダーデータ!$M$4:$M$368,0),MATCH($C28,カレンダーデータ!$N$3:$R$3,0))),"") | I28: =IFERROR(IF(ISBLANK(INDEX(カレンダーデータ!$N$4:$R$368,MATCH(I$29,カレンダーデータ!$M$4:$M$368,0),MATCH($C28,カレンダーデータ!$N$3:$R$3,0))),"",INDEX(カレンダーデータ!$N$4:$R$368,MATCH(I$29,カレンダーデータ!$M$4:$M$368,0),MATCH($C28,カレンダーデータ!$N$3:$R$3,0))),"") | J28: =IFERROR(IF(ISBLANK(INDEX(カレンダーデータ!$N$4:$R$368,MATCH(J$29,カレンダーデータ!$M$4:$M$368,0),MATCH($C28,カレンダーデータ!$N$3:$R$3,0))),"",INDEX(カレンダーデータ!$N$4:$R$368,MATCH(J$29,カレンダーデータ!$M$4:$M$368,0),MATCH($C28,カレンダーデータ!$N$3:$R$3,0))),"") | K28: =IFERROR(IF(ISBLANK(INDEX(カレンダーデータ!$N$4:$R$368,MATCH(K$29,カレンダーデータ!$M$4:$M$368,0),MATCH($C28,カレンダーデータ!$N$3:$R$3,0))),"",INDEX(カレンダーデータ!$N$4:$R$368,MATCH(K$29,カレンダーデータ!$M$4:$M$368,0),MATCH($C28,カレンダーデータ!$N$3:$R$3,0))),"") | ... AH28: =IFERROR(IF(ISBLANK(INDEX(カレンダーデータ!$N$4:$R$368,MATCH(AH$29,カレンダーデータ!$M$4:$M$368,0),MATCH($C28,カレンダーデータ!$N$3:$R$3,0))),"",INDEX(カレンダーデータ!$N$4:$R$368,MATCH(AH$29,カレンダーデータ!$M$4:$M$368,0),MATCH($C28,カレンダーデータ!$N$3:$R$3,0))),"")
B29: ホテル名 | D29: =C1+1 -> 45870 | E29: =D29+1 -> 45871 | F29: =E29+1 -> 45872 | G29: =F29+1 -> 45873 | H29: =G29+1 -> 45874 | I29: =H29+1 -> 45875 | J29: =I29+1 -> 45876 | K29: =J29+1 -> 45877 | L29: =K29+1 -> 45878 | ... AH29: =AG29+1 -> 45900
A30: 2 | B30: =料金比較表!C11 -> アーマン スイート ヴィラ スムイデ | C30: 料金比較表(今週)【2名】 | D30: =IF($C$30=料金比較表!$C$1,(HLOOKUP('2025年8月'!D$29,料金比較表!$10:$20,'2025年8月'!$A30,FALSE)),IF($C$30=料金比較表!$C$2,(HLOOKUP('2025年8月'!D$29,料金比較表!$23:$33,'2025年8月'!$A30,FALSE)),IF($C$30=料金比較表!$C$3,(HLOOKUP('2025年8月'!D$29,料金比較表!$36:$46,'2025年8月'!$A30,FALSE)),IF($C$30=料金比較表!$C$4,(HLOOKUP('2025年8月'!D$29,料金比較表!$48:$60,'2025年8月'!$A30,FALSE)),IF($C$30=料金比較表!$C$5,(HLOOKUP('2025年8月'!D$29,料金比較表!$61:$71,'2025年8月'!$A30,FALSE)),IF($C$30=料金比較表!$C$6,(HLOOKUP('2025年8月'!D$29,料金比較表!$74:$84,'2025年8月'!$A30,FALSE)))))))) -> #N/A | E30: =IF($C$30=料金比較表!$C$1,(HLOOKUP('2025年8月'!E$29,料金比較表!$10:$20,'2025年8月'!$A30,FALSE)),IF($C$30=料金比較表!$C$2,(HLOOKUP('2025年8月'!E$29,料金比較表!$23:$33,'2025年8月'!$A30,FALSE)),IF($C$30=料金比較表!$C$3,(HLOOKUP('2025年8月'!E$29,料金比較表!$36:$46,'2025年8月'!$A30,FALSE)),IF($C$30=料金比較表!$C$4,(HLOOKUP('2025年8月'!E$29,料金比較表!$48:$60,'2025年8月'!$A30,FALSE)),IF($C$30=料金比較表!$C$5,(HLOOKUP('2025年8月'!E$29,料金比較表!$61:$71,'2025年8月'!$A30,FALSE)),IF($C$30=料金比較表!$C$6,(HLOOKUP('2025年8月'!E$29,料金比較表!$74:$84,'2025年8月'!$A30,FALSE)))))))) -> #N/A | F30: =IF($C$30=料金比較表!$C$1,(HLOOKUP('2025年8月'!F$29,料金比較表!$10:$20,'2025年8月'!$A30,FALSE)),IF($C$30=料金比較表!$C$2,(HLOOKUP('2025年8月'!F$29,料金比較表!$23:$33,'2025年8月'!$A30,FALSE)),IF($C$30=料金比較表!$C$3,(HLOOKUP('2025年8月'!F$29,料金比較表!$36:$46,'2025年8月'!$A30,FALSE)),IF($C$30=料金比較表!$C$4,(HLOOKUP('2025年8月'!F$29,料金比較表!$48:$60,'2025年8月'!$A30,FALSE)),IF($C$30=料金比較表!$C$5,(HLOOKUP('2025年8月'!F$29,料金比較表!$61:$71,'2025年8月'!$A30,FALSE)),IF($C$30=料金比較表!$C$6,(HLOOKUP('2025年8月'!F$29,料金比較表!$74:$84,'2025年8月'!$A30,FALSE)))))))) -> #N/A | G30: =IF($C$30=料金比較表!$C$1,(HLOOKUP('2025年8月'!G$29,料金比較表!$10:$20,'2025年8月'!$A30,FALSE)),IF($C$30=料金比較表!$C$2,(HLOOKUP('2025年8月'!G$29,料金比較表!$23:$33,'2025年8月'!$A30,FALSE)),IF($C$30=料金比較表!$C$3,(HLOOKUP('2025年8月'!G$29,料金比較表!$36:$46,'2025年8月'!$A30,FALSE)),IF($C$30=料金比較表!$C$4,(HLOOKUP('2025年8月'!G$29,料金比較表!$48:$60,'2025年8月'!$A30,FALSE)),IF($C$30=料金比較表!$C$5,(HLOOKUP('2025年8月'!G$29,料金比較表!$61:$71,'2025年8月'!$A30,FALSE)),IF($C$30=料金比較表!$C$6,(HLOOKUP('2025年8月'!G$29,料金比較表!$74:$84,'2025年8月'!$A30,FALSE)))))))) -> #N/A | H30: =IF($C$30=料金比較表!$C$1,(HLOOKUP('2025年8月'!H$29,料金比較表!$10:$20,'2025年8月'!$A30,FALSE)),IF($C$30=料金比較表!$C$2,(HLOOKUP('2025年8月'!H$29,料金比較表!$23:$33,'2025年8月'!$A30,FALSE)),IF($C$30=料金比較表!$C$3,(HLOOKUP('2025年8月'!H$29,料金比較表!$36:$46,'2025年8月'!$A30,FALSE)),IF($C$30=料金比較表!$C$4,(HLOOKUP('2025年8月'!H$29,料金比較表!$48:$60,'2025年8月'!$A30,FALSE)),IF($C$30=料金比較表!$C$5,(HLOOKUP('2025年8月'!H$29,料金比較表!$61:$71,'2025年8月'!$A30,FALSE)),IF($C$30=料金比較表!$C$6,(HLOOKUP('2025年8月'!H$29,料金比較表!$74:$84,'2025年8月'!$A30,FALSE)))))))) -> #N/A | I30: =IF($C$30=料金比較表!$C$1,(HLOOKUP('2025年8月'!I$29,料金比較表!$10:$20,'2025年8月'!$A30,FALSE)),IF($C$30=料金比較表!$C$2,(HLOOKUP('2025年8月'!I$29,料金比較表!$23:$33,'2025年8月'!$A30,FALSE)),IF($C$30=料金比較表!$C$3,(HLOOKUP('2025年8月'!I$29,料金比較表!$36:$46,'2025年8月'!$A30,FALSE)),IF($C$30=料金比較表!$C$4,(HLOOKUP('2025年8月'!I$29,料金比較表!$48:$60,'2025年8月'!$A30,FALSE)),IF($C$30=料金比較表!$C$5,(HLOOKUP('2025年8月'!I$29,料金比較表!$61:$71,'2025年8月'!$A30,FALSE)),IF($C$30=料金比較表!$C$6,(HLOOKUP('2025年8月'!I$29,料金比較表!$74:$84,'2025年8月'!$A30,FALSE)))))))) -> #N/A | J30: =IF($C$30=料金比較表!$C$1,(HLOOKUP('2025年8月'!J$29,料金比較表!$10:$20,'2025年8月'!$A30,FALSE)),IF($C$30=料金比較表!$C$2,(HLOOKUP('2025年8月'!J$29,料金比較表!$23:$33,'2025年8月'!$A30,FALSE)),IF($C$30=料金比較表!$C$3,(HLOOKUP('2025年8月'!J$29,料金比較表!$36:$46,'2025年8月'!$A30,FALSE)),IF($C$30=料金比較表!$C$4,(HLOOKUP('2025年8月'!J$29,料金比較表!$48:$60,'2025年8月'!$A30,FALSE)),IF($C$30=料金比較表!$C$5,(HLOOKUP('2025年8月'!J$29,料金比較表!$61:$71,'2025年8月'!$A30,FALSE)),IF($C$30=料金比較表!$C$6,(HLOOKUP('2025年8月'!J$29,料金比較表!$74:$84,'2025年8月'!$A30,FALSE)))))))) -> #N/A | K30: =IF($C$30=料金比較表!$C$1,(HLOOKUP('2025年8月'!K$29,料金比較表!$10:$20,'2025年8月'!$A30,FALSE)),IF($C$30=料金比較表!$C$2,(HLOOKUP('2025年8月'!K$29,料金比較表!$23:$33,'2025年8月'!$A30,FALSE)),IF($C$30=料金比較表!$C$3,(HLOOKUP('2025年8月'!K$29,料金比較表!$36:$46,'2025年8月'!$A30,FALSE)),IF($C$30=料金比較表!$C$4,(HLOOKUP('2025年8月'!K$29,料金比較表!$48:$60,'2025年8月'!$A30,FALSE)),IF($C$30=料金比較表!$C$5,(HLOOKUP('2025年8月'!K$29,料金比較表!$61:$71,'2025年8月'!$A30,FALSE)),IF($C$30=料金比較表!$C$6,(HLOOKUP('2025年8月'!K$29,料金比較表!$74:$84,'2025年8月'!$A30,FALSE)))))))) -> #N/A | ... AH30: =IF($C$30=料金比較表!$C$1,(HLOOKUP('2025年8月'!AH$29,料金比較表!$10:$20,'2025年8月'!$A30,FALSE)),IF($C$30=料金比較表!$C$2,(HLOOKUP('2025年8月'!AH$29,料金比較表!$23:$33,'2025年8月'!$A30,FALSE)),IF($C$30=料金比較表!$C$3,(HLOOKUP('2025年8月'!AH$29,料金比較表!$36:$46,'2025年8月'!$A30,FALSE)),IF($C$30=料金比較表!$C$4,(HLOOKUP('2025年8月'!AH$29,料金比較表!$48:$60,'2025年8月'!$A30,FALSE)),IF($C$30=料金比較表!$C$5,(HLOOKUP('2025年8月'!AH$29,料金比較表!$61:$71,'2025年8月'!$A30,FALSE)),IF($C$30=料金比較表!$C$6,(HLOOKUP('2025年8月'!AH$29,料金比較表!$74:$84,'2025年8月'!$A30,FALSE)))))))) -> #N/A
A31: =A30+1 -> 3 | B31: =料金比較表!C12 -> Ｏｎｅ Ｓｕｉｔｅ ＴＨＥ ＴＥＲＲＡＣＥ＜古宇利島＞ | D31: =IF($C$30=料金比較表!$C$1,(HLOOKUP('2025年8月'!D$29,料金比較表!$10:$20,'2025年8月'!$A31,FALSE)),IF($C$30=料金比較表!$C$2,(HLOOKUP('2025年8月'!D$29,料金比較表!$23:$33,'2025年8月'!$A31,FALSE)),IF($C$30=料金比較表!$C$3,(HLOOKUP('2025年8月'!D$29,料金比較表!$36:$46,'2025年8月'!$A31,FALSE)),IF($C$30=料金比較表!$C$4,(HLOOKUP('2025年8月'!D$29,料金比較表!$48:$60,'2025年8月'!$A31,FALSE)),IF($C$30=料金比較表!$C$5,(HLOOKUP('2025年8月'!D$29,料金比較表!$61:$71,'2025年8月'!$A31,FALSE)),IF($C$30=料金比較表!$C$6,(HLOOKUP('2025年8月'!D$29,料金比較表!$74:$84,'2025年8月'!$A31,FALSE)))))))) -> #N/A | E31: =IF($C$30=料金比較表!$C$1,(HLOOKUP('2025年8月'!E$29,料金比較表!$10:$20,'2025年8月'!$A31,FALSE)),IF($C$30=料金比較表!$C$2,(HLOOKUP('2025年8月'!E$29,料金比較表!$23:$33,'2025年8月'!$A31,FALSE)),IF($C$30=料金比較表!$C$3,(HLOOKUP('2025年8月'!E$29,料金比較表!$36:$46,'2025年8月'!$A31,FALSE)),IF($C$30=料金比較表!$C$4,(HLOOKUP('2025年8月'!E$29,料金比較表!$48:$60,'2025年8月'!$A31,FALSE)),IF($C$30=料金比較表!$C$5,(HLOOKUP('2025年8月'!E$29,料金比較表!$61:$71,'2025年8月'!$A31,FALSE)),IF($C$30=料金比較表!$C$6,(HLOOKUP('2025年8月'!E$29,料金比較表!$74:$84,'2025年8月'!$A31,FALSE)))))))) -> #N/A | F31: =IF($C$30=料金比較表!$C$1,(HLOOKUP('2025年8月'!F$29,料金比較表!$10:$20,'2025年8月'!$A31,FALSE)),IF($C$30=料金比較表!$C$2,(HLOOKUP('2025年8月'!F$29,料金比較表!$23:$33,'2025年8月'!$A31,FALSE)),IF($C$30=料金比較表!$C$3,(HLOOKUP('2025年8月'!F$29,料金比較表!$36:$46,'2025年8月'!$A31,FALSE)),IF($C$30=料金比較表!$C$4,(HLOOKUP('2025年8月'!F$29,料金比較表!$48:$60,'2025年8月'!$A31,FALSE)),IF($C$30=料金比較表!$C$5,(HLOOKUP('2025年8月'!F$29,料金比較表!$61:$71,'2025年8月'!$A31,FALSE)),IF($C$30=料金比較表!$C$6,(HLOOKUP('2025年8月'!F$29,料金比較表!$74:$84,'2025年8月'!$A31,FALSE)))))))) -> #N/A | G31: =IF($C$30=料金比較表!$C$1,(HLOOKUP('2025年8月'!G$29,料金比較表!$10:$20,'2025年8月'!$A31,FALSE)),IF($C$30=料金比較表!$C$2,(HLOOKUP('2025年8月'!G$29,料金比較表!$23:$33,'2025年8月'!$A31,FALSE)),IF($C$30=料金比較表!$C$3,(HLOOKUP('2025年8月'!G$29,料金比較表!$36:$46,'2025年8月'!$A31,FALSE)),IF($C$30=料金比較表!$C$4,(HLOOKUP('2025年8月'!G$29,料金比較表!$48:$60,'2025年8月'!$A31,FALSE)),IF($C$30=料金比較表!$C$5,(HLOOKUP('2025年8月'!G$29,料金比較表!$61:$71,'2025年8月'!$A31,FALSE)),IF($C$30=料金比較表!$C$6,(HLOOKUP('2025年8月'!G$29,料金比較表!$74:$84,'2025年8月'!$A31,FALSE)))))))) -> #N/A | H31: =IF($C$30=料金比較表!$C$1,(HLOOKUP('2025年8月'!H$29,料金比較表!$10:$20,'2025年8月'!$A31,FALSE)),IF($C$30=料金比較表!$C$2,(HLOOKUP('2025年8月'!H$29,料金比較表!$23:$33,'2025年8月'!$A31,FALSE)),IF($C$30=料金比較表!$C$3,(HLOOKUP('2025年8月'!H$29,料金比較表!$36:$46,'2025年8月'!$A31,FALSE)),IF($C$30=料金比較表!$C$4,(HLOOKUP('2025年8月'!H$29,料金比較表!$48:$60,'2025年8月'!$A31,FALSE)),IF($C$30=料金比較表!$C$5,(HLOOKUP('2025年8月'!H$29,料金比較表!$61:$71,'2025年8月'!$A31,FALSE)),IF($C$30=料金比較表!$C$6,(HLOOKUP('2025年8月'!H$29,料金比較表!$74:$84,'2025年8月'!$A31,FALSE)))))))) -> #N/A | I31: =IF($C$30=料金比較表!$C$1,(HLOOKUP('2025年8月'!I$29,料金比較表!$10:$20,'2025年8月'!$A31,FALSE)),IF($C$30=料金比較表!$C$2,(HLOOKUP('2025年8月'!I$29,料金比較表!$23:$33,'2025年8月'!$A31,FALSE)),IF($C$30=料金比較表!$C$3,(HLOOKUP('2025年8月'!I$29,料金比較表!$36:$46,'2025年8月'!$A31,FALSE)),IF($C$30=料金比較表!$C$4,(HLOOKUP('2025年8月'!I$29,料金比較表!$48:$60,'2025年8月'!$A31,FALSE)),IF($C$30=料金比較表!$C$5,(HLOOKUP('2025年8月'!I$29,料金比較表!$61:$71,'2025年8月'!$A31,FALSE)),IF($C$30=料金比較表!$C$6,(HLOOKUP('2025年8月'!I$29,料金比較表!$74:$84,'2025年8月'!$A31,FALSE)))))))) -> #N/A | J31: =IF($C$30=料金比較表!$C$1,(HLOOKUP('2025年8月'!J$29,料金比較表!$10:$20,'2025年8月'!$A31,FALSE)),IF($C$30=料金比較表!$C$2,(HLOOKUP('2025年8月'!J$29,料金比較表!$23:$33,'2025年8月'!$A31,FALSE)),IF($C$30=料金比較表!$C$3,(HLOOKUP('2025年8月'!J$29,料金比較表!$36:$46,'2025年8月'!$A31,FALSE)),IF($C$30=料金比較表!$C$4,(HLOOKUP('2025年8月'!J$29,料金比較表!$48:$60,'2025年8月'!$A31,FALSE)),IF($C$30=料金比較表!$C$5,(HLOOKUP('2025年8月'!J$29,料金比較表!$61:$71,'2025年8月'!$A31,FALSE)),IF($C$30=料金比較表!$C$6,(HLOOKUP('2025年8月'!J$29,料金比較表!$74:$84,'2025年8月'!$A31,FALSE)))))))) -> #N/A | K31: =IF($C$30=料金比較表!$C$1,(HLOOKUP('2025年8月'!K$29,料金比較表!$10:$20,'2025年8月'!$A31,FALSE)),IF($C$30=料金比較表!$C$2,(HLOOKUP('2025年8月'!K$29,料金比較表!$23:$33,'2025年8月'!$A31,FALSE)),IF($C$30=料金比較表!$C$3,(HLOOKUP('2025年8月'!K$29,料金比較表!$36:$46,'2025年8月'!$A31,FALSE)),IF($C$30=料金比較表!$C$4,(HLOOKUP('2025年8月'!K$29,料金比較表!$48:$60,'2025年8月'!$A31,FALSE)),IF($C$30=料金比較表!$C$5,(HLOOKUP('2025年8月'!K$29,料金比較表!$61:$71,'2025年8月'!$A31,FALSE)),IF($C$30=料金比較表!$C$6,(HLOOKUP('2025年8月'!K$29,料金比較表!$74:$84,'2025年8月'!$A31,FALSE)))))))) -> #N/A | ... AH31: =IF($C$30=料金比較表!$C$1,(HLOOKUP('2025年8月'!AH$29,料金比較表!$10:$20,'2025年8月'!$A31,FALSE)),IF($C$30=料金比較表!$C$2,(HLOOKUP('2025年8月'!AH$29,料金比較表!$23:$33,'2025年8月'!$A31,FALSE)),IF($C$30=料金比較表!$C$3,(HLOOKUP('2025年8月'!AH$29,料金比較表!$36:$46,'2025年8月'!$A31,FALSE)),IF($C$30=料金比較表!$C$4,(HLOOKUP('2025年8月'!AH$29,料金比較表!$48:$60,'2025年8月'!$A31,FALSE)),IF($C$30=料金比較表!$C$5,(HLOOKUP('2025年8月'!AH$29,料金比較表!$61:$71,'2025年8月'!$A31,FALSE)),IF($C$30=料金比較表!$C$6,(HLOOKUP('2025年8月'!AH$29,料金比較表!$74:$84,'2025年8月'!$A31,FALSE)))))))) -> #N/A
A32: =A31+1 -> 4 | B32: =料金比較表!C13 -> Ｏｎｅ Ｓｕｉｔｅ ＴＨＥ ＧＲＡＮＤ（ワンスイート ザ・グランド）＜古宇利島＞ | D32: =IF($C$30=料金比較表!$C$1,(HLOOKUP('2025年8月'!D$29,料金比較表!$10:$20,'2025年8月'!$A32,FALSE)),IF($C$30=料金比較表!$C$2,(HLOOKUP('2025年8月'!D$29,料金比較表!$23:$33,'2025年8月'!$A32,FALSE)),IF($C$30=料金比較表!$C$3,(HLOOKUP('2025年8月'!D$29,料金比較表!$36:$46,'2025年8月'!$A32,FALSE)),IF($C$30=料金比較表!$C$4,(HLOOKUP('2025年8月'!D$29,料金比較表!$48:$60,'2025年8月'!$A32,FALSE)),IF($C$30=料金比較表!$C$5,(HLOOKUP('2025年8月'!D$29,料金比較表!$61:$71,'2025年8月'!$A32,FALSE)),IF($C$30=料金比較表!$C$6,(HLOOKUP('2025年8月'!D$29,料金比較表!$74:$84,'2025年8月'!$A32,FALSE)))))))) -> #N/A | E32: =IF($C$30=料金比較表!$C$1,(HLOOKUP('2025年8月'!E$29,料金比較表!$10:$20,'2025年8月'!$A32,FALSE)),IF($C$30=料金比較表!$C$2,(HLOOKUP('2025年8月'!E$29,料金比較表!$23:$33,'2025年8月'!$A32,FALSE)),IF($C$30=料金比較表!$C$3,(HLOOKUP('2025年8月'!E$29,料金比較表!$36:$46,'2025年8月'!$A32,FALSE)),IF($C$30=料金比較表!$C$4,(HLOOKUP('2025年8月'!E$29,料金比較表!$48:$60,'2025年8月'!$A32,FALSE)),IF($C$30=料金比較表!$C$5,(HLOOKUP('2025年8月'!E$29,料金比較表!$61:$71,'2025年8月'!$A32,FALSE)),IF($C$30=料金比較表!$C$6,(HLOOKUP('2025年8月'!E$29,料金比較表!$74:$84,'2025年8月'!$A32,FALSE)))))))) -> #N/A | F32: =IF($C$30=料金比較表!$C$1,(HLOOKUP('2025年8月'!F$29,料金比較表!$10:$20,'2025年8月'!$A32,FALSE)),IF($C$30=料金比較表!$C$2,(HLOOKUP('2025年8月'!F$29,料金比較表!$23:$33,'2025年8月'!$A32,FALSE)),IF($C$30=料金比較表!$C$3,(HLOOKUP('2025年8月'!F$29,料金比較表!$36:$46,'2025年8月'!$A32,FALSE)),IF($C$30=料金比較表!$C$4,(HLOOKUP('2025年8月'!F$29,料金比較表!$48:$60,'2025年8月'!$A32,FALSE)),IF($C$30=料金比較表!$C$5,(HLOOKUP('2025年8月'!F$29,料金比較表!$61:$71,'2025年8月'!$A32,FALSE)),IF($C$30=料金比較表!$C$6,(HLOOKUP('2025年8月'!F$29,料金比較表!$74:$84,'2025年8月'!$A32,FALSE)))))))) -> #N/A | G32: =IF($C$30=料金比較表!$C$1,(HLOOKUP('2025年8月'!G$29,料金比較表!$10:$20,'2025年8月'!$A32,FALSE)),IF($C$30=料金比較表!$C$2,(HLOOKUP('2025年8月'!G$29,料金比較表!$23:$33,'2025年8月'!$A32,FALSE)),IF($C$30=料金比較表!$C$3,(HLOOKUP('2025年8月'!G$29,料金比較表!$36:$46,'2025年8月'!$A32,FALSE)),IF($C$30=料金比較表!$C$4,(HLOOKUP('2025年8月'!G$29,料金比較表!$48:$60,'2025年8月'!$A32,FALSE)),IF($C$30=料金比較表!$C$5,(HLOOKUP('2025年8月'!G$29,料金比較表!$61:$71,'2025年8月'!$A32,FALSE)),IF($C$30=料金比較表!$C$6,(HLOOKUP('2025年8月'!G$29,料金比較表!$74:$84,'2025年8月'!$A32,FALSE)))))))) -> #N/A | H32: =IF($C$30=料金比較表!$C$1,(HLOOKUP('2025年8月'!H$29,料金比較表!$10:$20,'2025年8月'!$A32,FALSE)),IF($C$30=料金比較表!$C$2,(HLOOKUP('2025年8月'!H$29,料金比較表!$23:$33,'2025年8月'!$A32,FALSE)),IF($C$30=料金比較表!$C$3,(HLOOKUP('2025年8月'!H$29,料金比較表!$36:$46,'2025年8月'!$A32,FALSE)),IF($C$30=料金比較表!$C$4,(HLOOKUP('2025年8月'!H$29,料金比較表!$48:$60,'2025年8月'!$A32,FALSE)),IF($C$30=料金比較表!$C$5,(HLOOKUP('2025年8月'!H$29,料金比較表!$61:$71,'2025年8月'!$A32,FALSE)),IF($C$30=料金比較表!$C$6,(HLOOKUP('2025年8月'!H$29,料金比較表!$74:$84,'2025年8月'!$A32,FALSE)))))))) -> #N/A | I32: =IF($C$30=料金比較表!$C$1,(HLOOKUP('2025年8月'!I$29,料金比較表!$10:$20,'2025年8月'!$A32,FALSE)),IF($C$30=料金比較表!$C$2,(HLOOKUP('2025年8月'!I$29,料金比較表!$23:$33,'2025年8月'!$A32,FALSE)),IF($C$30=料金比較表!$C$3,(HLOOKUP('2025年8月'!I$29,料金比較表!$36:$46,'2025年8月'!$A32,FALSE)),IF($C$30=料金比較表!$C$4,(HLOOKUP('2025年8月'!I$29,料金比較表!$48:$60,'2025年8月'!$A32,FALSE)),IF($C$30=料金比較表!$C$5,(HLOOKUP('2025年8月'!I$29,料金比較表!$61:$71,'2025年8月'!$A32,FALSE)),IF($C$30=料金比較表!$C$6,(HLOOKUP('2025年8月'!I$29,料金比較表!$74:$84,'2025年8月'!$A32,FALSE)))))))) -> #N/A | J32: =IF($C$30=料金比較表!$C$1,(HLOOKUP('2025年8月'!J$29,料金比較表!$10:$20,'2025年8月'!$A32,FALSE)),IF($C$30=料金比較表!$C$2,(HLOOKUP('2025年8月'!J$29,料金比較表!$23:$33,'2025年8月'!$A32,FALSE)),IF($C$30=料金比較表!$C$3,(HLOOKUP('2025年8月'!J$29,料金比較表!$36:$46,'2025年8月'!$A32,FALSE)),IF($C$30=料金比較表!$C$4,(HLOOKUP('2025年8月'!J$29,料金比較表!$48:$60,'2025年8月'!$A32,FALSE)),IF($C$30=料金比較表!$C$5,(HLOOKUP('2025年8月'!J$29,料金比較表!$61:$71,'2025年8月'!$A32,FALSE)),IF($C$30=料金比較表!$C$6,(HLOOKUP('2025年8月'!J$29,料金比較表!$74:$84,'2025年8月'!$A32,FALSE)))))))) -> #N/A | K32: =IF($C$30=料金比較表!$C$1,(HLOOKUP('2025年8月'!K$29,料金比較表!$10:$20,'2025年8月'!$A32,FALSE)),IF($C$30=料金比較表!$C$2,(HLOOKUP('2025年8月'!K$29,料金比較表!$23:$33,'2025年8月'!$A32,FALSE)),IF($C$30=料金比較表!$C$3,(HLOOKUP('2025年8月'!K$29,料金比較表!$36:$46,'2025年8月'!$A32,FALSE)),IF($C$30=料金比較表!$C$4,(HLOOKUP('2025年8月'!K$29,料金比較表!$48:$60,'2025年8月'!$A32,FALSE)),IF($C$30=料金比較表!$C$5,(HLOOKUP('2025年8月'!K$29,料金比較表!$61:$71,'2025年8月'!$A32,FALSE)),IF($C$30=料金比較表!$C$6,(HLOOKUP('2025年8月'!K$29,料金比較表!$74:$84,'2025年8月'!$A32,FALSE)))))))) -> #N/A | ... AH32: =IF($C$30=料金比較表!$C$1,(HLOOKUP('2025年8月'!AH$29,料金比較表!$10:$20,'2025年8月'!$A32,FALSE)),IF($C$30=料金比較表!$C$2,(HLOOKUP('2025年8月'!AH$29,料金比較表!$23:$33,'2025年8月'!$A32,FALSE)),IF($C$30=料金比較表!$C$3,(HLOOKUP('2025年8月'!AH$29,料金比較表!$36:$46,'2025年8月'!$A32,FALSE)),IF($C$30=料金比較表!$C$4,(HLOOKUP('2025年8月'!AH$29,料金比較表!$48:$60,'2025年8月'!$A32,FALSE)),IF($C$30=料金比較表!$C$5,(HLOOKUP('2025年8月'!AH$29,料金比較表!$61:$71,'2025年8月'!$A32,FALSE)),IF($C$30=料金比較表!$C$6,(HLOOKUP('2025年8月'!AH$29,料金比較表!$74:$84,'2025年8月'!$A32,FALSE)))))))) -> #N/A
A33: =A32+1 -> 5 | B33: =料金比較表!C14 -> Ｙｕｋｉ Ｓｕｉｔｅ Ｋｏｕｒｉｊｉｍａ＜古宇利島＞ | D33: =IF($C$30=料金比較表!$C$1,(HLOOKUP('2025年8月'!D$29,料金比較表!$10:$20,'2025年8月'!$A33,FALSE)),IF($C$30=料金比較表!$C$2,(HLOOKUP('2025年8月'!D$29,料金比較表!$23:$33,'2025年8月'!$A33,FALSE)),IF($C$30=料金比較表!$C$3,(HLOOKUP('2025年8月'!D$29,料金比較表!$36:$46,'2025年8月'!$A33,FALSE)),IF($C$30=料金比較表!$C$4,(HLOOKUP('2025年8月'!D$29,料金比較表!$48:$60,'2025年8月'!$A33,FALSE)),IF($C$30=料金比較表!$C$5,(HLOOKUP('2025年8月'!D$29,料金比較表!$61:$71,'2025年8月'!$A33,FALSE)),IF($C$30=料金比較表!$C$6,(HLOOKUP('2025年8月'!D$29,料金比較表!$74:$84,'2025年8月'!$A33,FALSE)))))))) -> #N/A | E33: =IF($C$30=料金比較表!$C$1,(HLOOKUP('2025年8月'!E$29,料金比較表!$10:$20,'2025年8月'!$A33,FALSE)),IF($C$30=料金比較表!$C$2,(HLOOKUP('2025年8月'!E$29,料金比較表!$23:$33,'2025年8月'!$A33,FALSE)),IF($C$30=料金比較表!$C$3,(HLOOKUP('2025年8月'!E$29,料金比較表!$36:$46,'2025年8月'!$A33,FALSE)),IF($C$30=料金比較表!$C$4,(HLOOKUP('2025年8月'!E$29,料金比較表!$48:$60,'2025年8月'!$A33,FALSE)),IF($C$30=料金比較表!$C$5,(HLOOKUP('2025年8月'!E$29,料金比較表!$61:$71,'2025年8月'!$A33,FALSE)),IF($C$30=料金比較表!$C$6,(HLOOKUP('2025年8月'!E$29,料金比較表!$74:$84,'2025年8月'!$A33,FALSE)))))))) -> #N/A | F33: =IF($C$30=料金比較表!$C$1,(HLOOKUP('2025年8月'!F$29,料金比較表!$10:$20,'2025年8月'!$A33,FALSE)),IF($C$30=料金比較表!$C$2,(HLOOKUP('2025年8月'!F$29,料金比較表!$23:$33,'2025年8月'!$A33,FALSE)),IF($C$30=料金比較表!$C$3,(HLOOKUP('2025年8月'!F$29,料金比較表!$36:$46,'2025年8月'!$A33,FALSE)),IF($C$30=料金比較表!$C$4,(HLOOKUP('2025年8月'!F$29,料金比較表!$48:$60,'2025年8月'!$A33,FALSE)),IF($C$30=料金比較表!$C$5,(HLOOKUP('2025年8月'!F$29,料金比較表!$61:$71,'2025年8月'!$A33,FALSE)),IF($C$30=料金比較表!$C$6,(HLOOKUP('2025年8月'!F$29,料金比較表!$74:$84,'2025年8月'!$A33,FALSE)))))))) -> #N/A | G33: =IF($C$30=料金比較表!$C$1,(HLOOKUP('2025年8月'!G$29,料金比較表!$10:$20,'2025年8月'!$A33,FALSE)),IF($C$30=料金比較表!$C$2,(HLOOKUP('2025年8月'!G$29,料金比較表!$23:$33,'2025年8月'!$A33,FALSE)),IF($C$30=料金比較表!$C$3,(HLOOKUP('2025年8月'!G$29,料金比較表!$36:$46,'2025年8月'!$A33,FALSE)),IF($C$30=料金比較表!$C$4,(HLOOKUP('2025年8月'!G$29,料金比較表!$48:$60,'2025年8月'!$A33,FALSE)),IF($C$30=料金比較表!$C$5,(HLOOKUP('2025年8月'!G$29,料金比較表!$61:$71,'2025年8月'!$A33,FALSE)),IF($C$30=料金比較表!$C$6,(HLOOKUP('2025年8月'!G$29,料金比較表!$74:$84,'2025年8月'!$A33,FALSE)))))))) -> #N/A | H33: =IF($C$30=料金比較表!$C$1,(HLOOKUP('2025年8月'!H$29,料金比較表!$10:$20,'2025年8月'!$A33,FALSE)),IF($C$30=料金比較表!$C$2,(HLOOKUP('2025年8月'!H$29,料金比較表!$23:$33,'2025年8月'!$A33,FALSE)),IF($C$30=料金比較表!$C$3,(HLOOKUP('2025年8月'!H$29,料金比較表!$36:$46,'2025年8月'!$A33,FALSE)),IF($C$30=料金比較表!$C$4,(HLOOKUP('2025年8月'!H$29,料金比較表!$48:$60,'2025年8月'!$A33,FALSE)),IF($C$30=料金比較表!$C$5,(HLOOKUP('2025年8月'!H$29,料金比較表!$61:$71,'2025年8月'!$A33,FALSE)),IF($C$30=料金比較表!$C$6,(HLOOKUP('2025年8月'!H$29,料金比較表!$74:$84,'2025年8月'!$A33,FALSE)))))))) -> #N/A | I33: =IF($C$30=料金比較表!$C$1,(HLOOKUP('2025年8月'!I$29,料金比較表!$10:$20,'2025年8月'!$A33,FALSE)),IF($C$30=料金比較表!$C$2,(HLOOKUP('2025年8月'!I$29,料金比較表!$23:$33,'2025年8月'!$A33,FALSE)),IF($C$30=料金比較表!$C$3,(HLOOKUP('2025年8月'!I$29,料金比較表!$36:$46,'2025年8月'!$A33,FALSE)),IF($C$30=料金比較表!$C$4,(HLOOKUP('2025年8月'!I$29,料金比較表!$48:$60,'2025年8月'!$A33,FALSE)),IF($C$30=料金比較表!$C$5,(HLOOKUP('2025年8月'!I$29,料金比較表!$61:$71,'2025年8月'!$A33,FALSE)),IF($C$30=料金比較表!$C$6,(HLOOKUP('2025年8月'!I$29,料金比較表!$74:$84,'2025年8月'!$A33,FALSE)))))))) -> #N/A | J33: =IF($C$30=料金比較表!$C$1,(HLOOKUP('2025年8月'!J$29,料金比較表!$10:$20,'2025年8月'!$A33,FALSE)),IF($C$30=料金比較表!$C$2,(HLOOKUP('2025年8月'!J$29,料金比較表!$23:$33,'2025年8月'!$A33,FALSE)),IF($C$30=料金比較表!$C$3,(HLOOKUP('2025年8月'!J$29,料金比較表!$36:$46,'2025年8月'!$A33,FALSE)),IF($C$30=料金比較表!$C$4,(HLOOKUP('2025年8月'!J$29,料金比較表!$48:$60,'2025年8月'!$A33,FALSE)),IF($C$30=料金比較表!$C$5,(HLOOKUP('2025年8月'!J$29,料金比較表!$61:$71,'2025年8月'!$A33,FALSE)),IF($C$30=料金比較表!$C$6,(HLOOKUP('2025年8月'!J$29,料金比較表!$74:$84,'2025年8月'!$A33,FALSE)))))))) -> #N/A | K33: =IF($C$30=料金比較表!$C$1,(HLOOKUP('2025年8月'!K$29,料金比較表!$10:$20,'2025年8月'!$A33,FALSE)),IF($C$30=料金比較表!$C$2,(HLOOKUP('2025年8月'!K$29,料金比較表!$23:$33,'2025年8月'!$A33,FALSE)),IF($C$30=料金比較表!$C$3,(HLOOKUP('2025年8月'!K$29,料金比較表!$36:$46,'2025年8月'!$A33,FALSE)),IF($C$30=料金比較表!$C$4,(HLOOKUP('2025年8月'!K$29,料金比較表!$48:$60,'2025年8月'!$A33,FALSE)),IF($C$30=料金比較表!$C$5,(HLOOKUP('2025年8月'!K$29,料金比較表!$61:$71,'2025年8月'!$A33,FALSE)),IF($C$30=料金比較表!$C$6,(HLOOKUP('2025年8月'!K$29,料金比較表!$74:$84,'2025年8月'!$A33,FALSE)))))))) -> #N/A | ... AH33: =IF($C$30=料金比較表!$C$1,(HLOOKUP('2025年8月'!AH$29,料金比較表!$10:$20,'2025年8月'!$A33,FALSE)),IF($C$30=料金比較表!$C$2,(HLOOKUP('2025年8月'!AH$29,料金比較表!$23:$33,'2025年8月'!$A33,FALSE)),IF($C$30=料金比較表!$C$3,(HLOOKUP('2025年8月'!AH$29,料金比較表!$36:$46,'2025年8月'!$A33,FALSE)),IF($C$30=料金比較表!$C$4,(HLOOKUP('2025年8月'!AH$29,料金比較表!$48:$60,'2025年8月'!$A33,FALSE)),IF($C$30=料金比較表!$C$5,(HLOOKUP('2025年8月'!AH$29,料金比較表!$61:$71,'2025年8月'!$A33,FALSE)),IF($C$30=料金比較表!$C$6,(HLOOKUP('2025年8月'!AH$29,料金比較表!$74:$84,'2025年8月'!$A33,FALSE)))))))) -> #N/A
A34: =A33+1 -> 6 | B34: =料金比較表!C15 -> ＢＡＴＯＮ ＳＵＩＴＥ 沖縄古宇利島 | D34: =IF($C$30=料金比較表!$C$1,(HLOOKUP('2025年8月'!D$29,料金比較表!$10:$20,'2025年8月'!$A34,FALSE)),IF($C$30=料金比較表!$C$2,(HLOOKUP('2025年8月'!D$29,料金比較表!$23:$33,'2025年8月'!$A34,FALSE)),IF($C$30=料金比較表!$C$3,(HLOOKUP('2025年8月'!D$29,料金比較表!$36:$46,'2025年8月'!$A34,FALSE)),IF($C$30=料金比較表!$C$4,(HLOOKUP('2025年8月'!D$29,料金比較表!$48:$60,'2025年8月'!$A34,FALSE)),IF($C$30=料金比較表!$C$5,(HLOOKUP('2025年8月'!D$29,料金比較表!$61:$71,'2025年8月'!$A34,FALSE)),IF($C$30=料金比較表!$C$6,(HLOOKUP('2025年8月'!D$29,料金比較表!$74:$84,'2025年8月'!$A34,FALSE)))))))) -> #N/A | E34: =IF($C$30=料金比較表!$C$1,(HLOOKUP('2025年8月'!E$29,料金比較表!$10:$20,'2025年8月'!$A34,FALSE)),IF($C$30=料金比較表!$C$2,(HLOOKUP('2025年8月'!E$29,料金比較表!$23:$33,'2025年8月'!$A34,FALSE)),IF($C$30=料金比較表!$C$3,(HLOOKUP('2025年8月'!E$29,料金比較表!$36:$46,'2025年8月'!$A34,FALSE)),IF($C$30=料金比較表!$C$4,(HLOOKUP('2025年8月'!E$29,料金比較表!$48:$60,'2025年8月'!$A34,FALSE)),IF($C$30=料金比較表!$C$5,(HLOOKUP('2025年8月'!E$29,料金比較表!$61:$71,'2025年8月'!$A34,FALSE)),IF($C$30=料金比較表!$C$6,(HLOOKUP('2025年8月'!E$29,料金比較表!$74:$84,'2025年8月'!$A34,FALSE)))))))) -> #N/A | F34: =IF($C$30=料金比較表!$C$1,(HLOOKUP('2025年8月'!F$29,料金比較表!$10:$20,'2025年8月'!$A34,FALSE)),IF($C$30=料金比較表!$C$2,(HLOOKUP('2025年8月'!F$29,料金比較表!$23:$33,'2025年8月'!$A34,FALSE)),IF($C$30=料金比較表!$C$3,(HLOOKUP('2025年8月'!F$29,料金比較表!$36:$46,'2025年8月'!$A34,FALSE)),IF($C$30=料金比較表!$C$4,(HLOOKUP('2025年8月'!F$29,料金比較表!$48:$60,'2025年8月'!$A34,FALSE)),IF($C$30=料金比較表!$C$5,(HLOOKUP('2025年8月'!F$29,料金比較表!$61:$71,'2025年8月'!$A34,FALSE)),IF($C$30=料金比較表!$C$6,(HLOOKUP('2025年8月'!F$29,料金比較表!$74:$84,'2025年8月'!$A34,FALSE)))))))) -> #N/A | G34: =IF($C$30=料金比較表!$C$1,(HLOOKUP('2025年8月'!G$29,料金比較表!$10:$20,'2025年8月'!$A34,FALSE)),IF($C$30=料金比較表!$C$2,(HLOOKUP('2025年8月'!G$29,料金比較表!$23:$33,'2025年8月'!$A34,FALSE)),IF($C$30=料金比較表!$C$3,(HLOOKUP('2025年8月'!G$29,料金比較表!$36:$46,'2025年8月'!$A34,FALSE)),IF($C$30=料金比較表!$C$4,(HLOOKUP('2025年8月'!G$29,料金比較表!$48:$60,'2025年8月'!$A34,FALSE)),IF($C$30=料金比較表!$C$5,(HLOOKUP('2025年8月'!G$29,料金比較表!$61:$71,'2025年8月'!$A34,FALSE)),IF($C$30=料金比較表!$C$6,(HLOOKUP('2025年8月'!G$29,料金比較表!$74:$84,'2025年8月'!$A34,FALSE)))))))) -> #N/A | H34: =IF($C$30=料金比較表!$C$1,(HLOOKUP('2025年8月'!H$29,料金比較表!$10:$20,'2025年8月'!$A34,FALSE)),IF($C$30=料金比較表!$C$2,(HLOOKUP('2025年8月'!H$29,料金比較表!$23:$33,'2025年8月'!$A34,FALSE)),IF($C$30=料金比較表!$C$3,(HLOOKUP('2025年8月'!H$29,料金比較表!$36:$46,'2025年8月'!$A34,FALSE)),IF($C$30=料金比較表!$C$4,(HLOOKUP('2025年8月'!H$29,料金比較表!$48:$60,'2025年8月'!$A34,FALSE)),IF($C$30=料金比較表!$C$5,(HLOOKUP('2025年8月'!H$29,料金比較表!$61:$71,'2025年8月'!$A34,FALSE)),IF($C$30=料金比較表!$C$6,(HLOOKUP('2025年8月'!H$29,料金比較表!$74:$84,'2025年8月'!$A34,FALSE)))))))) -> #N/A | I34: =IF($C$30=料金比較表!$C$1,(HLOOKUP('2025年8月'!I$29,料金比較表!$10:$20,'2025年8月'!$A34,FALSE)),IF($C$30=料金比較表!$C$2,(HLOOKUP('2025年8月'!I$29,料金比較表!$23:$33,'2025年8月'!$A34,FALSE)),IF($C$30=料金比較表!$C$3,(HLOOKUP('2025年8月'!I$29,料金比較表!$36:$46,'2025年8月'!$A34,FALSE)),IF($C$30=料金比較表!$C$4,(HLOOKUP('2025年8月'!I$29,料金比較表!$48:$60,'2025年8月'!$A34,FALSE)),IF($C$30=料金比較表!$C$5,(HLOOKUP('2025年8月'!I$29,料金比較表!$61:$71,'2025年8月'!$A34,FALSE)),IF($C$30=料金比較表!$C$6,(HLOOKUP('2025年8月'!I$29,料金比較表!$74:$84,'2025年8月'!$A34,FALSE)))))))) -> #N/A | J34: =IF($C$30=料金比較表!$C$1,(HLOOKUP('2025年8月'!J$29,料金比較表!$10:$20,'2025年8月'!$A34,FALSE)),IF($C$30=料金比較表!$C$2,(HLOOKUP('2025年8月'!J$29,料金比較表!$23:$33,'2025年8月'!$A34,FALSE)),IF($C$30=料金比較表!$C$3,(HLOOKUP('2025年8月'!J$29,料金比較表!$36:$46,'2025年8月'!$A34,FALSE)),IF($C$30=料金比較表!$C$4,(HLOOKUP('2025年8月'!J$29,料金比較表!$48:$60,'2025年8月'!$A34,FALSE)),IF($C$30=料金比較表!$C$5,(HLOOKUP('2025年8月'!J$29,料金比較表!$61:$71,'2025年8月'!$A34,FALSE)),IF($C$30=料金比較表!$C$6,(HLOOKUP('2025年8月'!J$29,料金比較表!$74:$84,'2025年8月'!$A34,FALSE)))))))) -> #N/A | K34: =IF($C$30=料金比較表!$C$1,(HLOOKUP('2025年8月'!K$29,料金比較表!$10:$20,'2025年8月'!$A34,FALSE)),IF($C$30=料金比較表!$C$2,(HLOOKUP('2025年8月'!K$29,料金比較表!$23:$33,'2025年8月'!$A34,FALSE)),IF($C$30=料金比較表!$C$3,(HLOOKUP('2025年8月'!K$29,料金比較表!$36:$46,'2025年8月'!$A34,FALSE)),IF($C$30=料金比較表!$C$4,(HLOOKUP('2025年8月'!K$29,料金比較表!$48:$60,'2025年8月'!$A34,FALSE)),IF($C$30=料金比較表!$C$5,(HLOOKUP('2025年8月'!K$29,料金比較表!$61:$71,'2025年8月'!$A34,FALSE)),IF($C$30=料金比較表!$C$6,(HLOOKUP('2025年8月'!K$29,料金比較表!$74:$84,'2025年8月'!$A34,FALSE)))))))) -> #N/A | ... AH34: =IF($C$30=料金比較表!$C$1,(HLOOKUP('2025年8月'!AH$29,料金比較表!$10:$20,'2025年8月'!$A34,FALSE)),IF($C$30=料金比較表!$C$2,(HLOOKUP('2025年8月'!AH$29,料金比較表!$23:$33,'2025年8月'!$A34,FALSE)),IF($C$30=料金比較表!$C$3,(HLOOKUP('2025年8月'!AH$29,料金比較表!$36:$46,'2025年8月'!$A34,FALSE)),IF($C$30=料金比較表!$C$4,(HLOOKUP('2025年8月'!AH$29,料金比較表!$48:$60,'2025年8月'!$A34,FALSE)),IF($C$30=料金比較表!$C$5,(HLOOKUP('2025年8月'!AH$29,料金比較表!$61:$71,'2025年8月'!$A34,FALSE)),IF($C$30=料金比較表!$C$6,(HLOOKUP('2025年8月'!AH$29,料金比較表!$74:$84,'2025年8月'!$A34,FALSE)))))))) -> #N/A
A35: =A34+1 -> 7 | B35: =料金比較表!C16 -> プールヴィラ 今泊 ｂｙ コルディオプレミアム | D35: =IF($C$30=料金比較表!$C$1,(HLOOKUP('2025年8月'!D$29,料金比較表!$10:$20,'2025年8月'!$A35,FALSE)),IF($C$30=料金比較表!$C$2,(HLOOKUP('2025年8月'!D$29,料金比較表!$23:$33,'2025年8月'!$A35,FALSE)),IF($C$30=料金比較表!$C$3,(HLOOKUP('2025年8月'!D$29,料金比較表!$36:$46,'2025年8月'!$A35,FALSE)),IF($C$30=料金比較表!$C$4,(HLOOKUP('2025年8月'!D$29,料金比較表!$48:$60,'2025年8月'!$A35,FALSE)),IF($C$30=料金比較表!$C$5,(HLOOKUP('2025年8月'!D$29,料金比較表!$61:$71,'2025年8月'!$A35,FALSE)),IF($C$30=料金比較表!$C$6,(HLOOKUP('2025年8月'!D$29,料金比較表!$74:$84,'2025年8月'!$A35,FALSE)))))))) -> #N/A | E35: =IF($C$30=料金比較表!$C$1,(HLOOKUP('2025年8月'!E$29,料金比較表!$10:$20,'2025年8月'!$A35,FALSE)),IF($C$30=料金比較表!$C$2,(HLOOKUP('2025年8月'!E$29,料金比較表!$23:$33,'2025年8月'!$A35,FALSE)),IF($C$30=料金比較表!$C$3,(HLOOKUP('2025年8月'!E$29,料金比較表!$36:$46,'2025年8月'!$A35,FALSE)),IF($C$30=料金比較表!$C$4,(HLOOKUP('2025年8月'!E$29,料金比較表!$48:$60,'2025年8月'!$A35,FALSE)),IF($C$30=料金比較表!$C$5,(HLOOKUP('2025年8月'!E$29,料金比較表!$61:$71,'2025年8月'!$A35,FALSE)),IF($C$30=料金比較表!$C$6,(HLOOKUP('2025年8月'!E$29,料金比較表!$74:$84,'2025年8月'!$A35,FALSE)))))))) -> #N/A | F35: =IF($C$30=料金比較表!$C$1,(HLOOKUP('2025年8月'!F$29,料金比較表!$10:$20,'2025年8月'!$A35,FALSE)),IF($C$30=料金比較表!$C$2,(HLOOKUP('2025年8月'!F$29,料金比較表!$23:$33,'2025年8月'!$A35,FALSE)),IF($C$30=料金比較表!$C$3,(HLOOKUP('2025年8月'!F$29,料金比較表!$36:$46,'2025年8月'!$A35,FALSE)),IF($C$30=料金比較表!$C$4,(HLOOKUP('2025年8月'!F$29,料金比較表!$48:$60,'2025年8月'!$A35,FALSE)),IF($C$30=料金比較表!$C$5,(HLOOKUP('2025年8月'!F$29,料金比較表!$61:$71,'2025年8月'!$A35,FALSE)),IF($C$30=料金比較表!$C$6,(HLOOKUP('2025年8月'!F$29,料金比較表!$74:$84,'2025年8月'!$A35,FALSE)))))))) -> #N/A | G35: =IF($C$30=料金比較表!$C$1,(HLOOKUP('2025年8月'!G$29,料金比較表!$10:$20,'2025年8月'!$A35,FALSE)),IF($C$30=料金比較表!$C$2,(HLOOKUP('2025年8月'!G$29,料金比較表!$23:$33,'2025年8月'!$A35,FALSE)),IF($C$30=料金比較表!$C$3,(HLOOKUP('2025年8月'!G$29,料金比較表!$36:$46,'2025年8月'!$A35,FALSE)),IF($C$30=料金比較表!$C$4,(HLOOKUP('2025年8月'!G$29,料金比較表!$48:$60,'2025年8月'!$A35,FALSE)),IF($C$30=料金比較表!$C$5,(HLOOKUP('2025年8月'!G$29,料金比較表!$61:$71,'2025年8月'!$A35,FALSE)),IF($C$30=料金比較表!$C$6,(HLOOKUP('2025年8月'!G$29,料金比較表!$74:$84,'2025年8月'!$A35,FALSE)))))))) -> #N/A | H35: =IF($C$30=料金比較表!$C$1,(HLOOKUP('2025年8月'!H$29,料金比較表!$10:$20,'2025年8月'!$A35,FALSE)),IF($C$30=料金比較表!$C$2,(HLOOKUP('2025年8月'!H$29,料金比較表!$23:$33,'2025年8月'!$A35,FALSE)),IF($C$30=料金比較表!$C$3,(HLOOKUP('2025年8月'!H$29,料金比較表!$36:$46,'2025年8月'!$A35,FALSE)),IF($C$30=料金比較表!$C$4,(HLOOKUP('2025年8月'!H$29,料金比較表!$48:$60,'2025年8月'!$A35,FALSE)),IF($C$30=料金比較表!$C$5,(HLOOKUP('2025年8月'!H$29,料金比較表!$61:$71,'2025年8月'!$A35,FALSE)),IF($C$30=料金比較表!$C$6,(HLOOKUP('2025年8月'!H$29,料金比較表!$74:$84,'2025年8月'!$A35,FALSE)))))))) -> #N/A | I35: =IF($C$30=料金比較表!$C$1,(HLOOKUP('2025年8月'!I$29,料金比較表!$10:$20,'2025年8月'!$A35,FALSE)),IF($C$30=料金比較表!$C$2,(HLOOKUP('2025年8月'!I$29,料金比較表!$23:$33,'2025年8月'!$A35,FALSE)),IF($C$30=料金比較表!$C$3,(HLOOKUP('2025年8月'!I$29,料金比較表!$36:$46,'2025年8月'!$A35,FALSE)),IF($C$30=料金比較表!$C$4,(HLOOKUP('2025年8月'!I$29,料金比較表!$48:$60,'2025年8月'!$A35,FALSE)),IF($C$30=料金比較表!$C$5,(HLOOKUP('2025年8月'!I$29,料金比較表!$61:$71,'2025年8月'!$A35,FALSE)),IF($C$30=料金比較表!$C$6,(HLOOKUP('2025年8月'!I$29,料金比較表!$74:$84,'2025年8月'!$A35,FALSE)))))))) -> #N/A | J35: =IF($C$30=料金比較表!$C$1,(HLOOKUP('2025年8月'!J$29,料金比較表!$10:$20,'2025年8月'!$A35,FALSE)),IF($C$30=料金比較表!$C$2,(HLOOKUP('2025年8月'!J$29,料金比較表!$23:$33,'2025年8月'!$A35,FALSE)),IF($C$30=料金比較表!$C$3,(HLOOKUP('2025年8月'!J$29,料金比較表!$36:$46,'2025年8月'!$A35,FALSE)),IF($C$30=料金比較表!$C$4,(HLOOKUP('2025年8月'!J$29,料金比較表!$48:$60,'2025年8月'!$A35,FALSE)),IF($C$30=料金比較表!$C$5,(HLOOKUP('2025年8月'!J$29,料金比較表!$61:$71,'2025年8月'!$A35,FALSE)),IF($C$30=料金比較表!$C$6,(HLOOKUP('2025年8月'!J$29,料金比較表!$74:$84,'2025年8月'!$A35,FALSE)))))))) -> #N/A | K35: =IF($C$30=料金比較表!$C$1,(HLOOKUP('2025年8月'!K$29,料金比較表!$10:$20,'2025年8月'!$A35,FALSE)),IF($C$30=料金比較表!$C$2,(HLOOKUP('2025年8月'!K$29,料金比較表!$23:$33,'2025年8月'!$A35,FALSE)),IF($C$30=料金比較表!$C$3,(HLOOKUP('2025年8月'!K$29,料金比較表!$36:$46,'2025年8月'!$A35,FALSE)),IF($C$30=料金比較表!$C$4,(HLOOKUP('2025年8月'!K$29,料金比較表!$48:$60,'2025年8月'!$A35,FALSE)),IF($C$30=料金比較表!$C$5,(HLOOKUP('2025年8月'!K$29,料金比較表!$61:$71,'2025年8月'!$A35,FALSE)),IF($C$30=料金比較表!$C$6,(HLOOKUP('2025年8月'!K$29,料金比較表!$74:$84,'2025年8月'!$A35,FALSE)))))))) -> #N/A | ... AH35: =IF($C$30=料金比較表!$C$1,(HLOOKUP('2025年8月'!AH$29,料金比較表!$10:$20,'2025年8月'!$A35,FALSE)),IF($C$30=料金比較表!$C$2,(HLOOKUP('2025年8月'!AH$29,料金比較表!$23:$33,'2025年8月'!$A35,FALSE)),IF($C$30=料金比較表!$C$3,(HLOOKUP('2025年8月'!AH$29,料金比較表!$36:$46,'2025年8月'!$A35,FALSE)),IF($C$30=料金比較表!$C$4,(HLOOKUP('2025年8月'!AH$29,料金比較表!$48:$60,'2025年8月'!$A35,FALSE)),IF($C$30=料金比較表!$C$5,(HLOOKUP('2025年8月'!AH$29,料金比較表!$61:$71,'2025年8月'!$A35,FALSE)),IF($C$30=料金比較表!$C$6,(HLOOKUP('2025年8月'!AH$29,料金比較表!$74:$84,'2025年8月'!$A35,FALSE)))))))) -> #N/A
A36: =A35+1 -> 8 | B36: =料金比較表!C17 -> プールヴィラ 屋我地島 ｂｙ コルディオプレミアム | D36: =IF($C$30=料金比較表!$C$1,(HLOOKUP('2025年8月'!D$29,料金比較表!$10:$20,'2025年8月'!$A36,FALSE)),IF($C$30=料金比較表!$C$2,(HLOOKUP('2025年8月'!D$29,料金比較表!$23:$33,'2025年8月'!$A36,FALSE)),IF($C$30=料金比較表!$C$3,(HLOOKUP('2025年8月'!D$29,料金比較表!$36:$46,'2025年8月'!$A36,FALSE)),IF($C$30=料金比較表!$C$4,(HLOOKUP('2025年8月'!D$29,料金比較表!$48:$60,'2025年8月'!$A36,FALSE)),IF($C$30=料金比較表!$C$5,(HLOOKUP('2025年8月'!D$29,料金比較表!$61:$71,'2025年8月'!$A36,FALSE)),IF($C$30=料金比較表!$C$6,(HLOOKUP('2025年8月'!D$29,料金比較表!$74:$84,'2025年8月'!$A36,FALSE)))))))) -> #N/A | E36: =IF($C$30=料金比較表!$C$1,(HLOOKUP('2025年8月'!E$29,料金比較表!$10:$20,'2025年8月'!$A36,FALSE)),IF($C$30=料金比較表!$C$2,(HLOOKUP('2025年8月'!E$29,料金比較表!$23:$33,'2025年8月'!$A36,FALSE)),IF($C$30=料金比較表!$C$3,(HLOOKUP('2025年8月'!E$29,料金比較表!$36:$46,'2025年8月'!$A36,FALSE)),IF($C$30=料金比較表!$C$4,(HLOOKUP('2025年8月'!E$29,料金比較表!$48:$60,'2025年8月'!$A36,FALSE)),IF($C$30=料金比較表!$C$5,(HLOOKUP('2025年8月'!E$29,料金比較表!$61:$71,'2025年8月'!$A36,FALSE)),IF($C$30=料金比較表!$C$6,(HLOOKUP('2025年8月'!E$29,料金比較表!$74:$84,'2025年8月'!$A36,FALSE)))))))) -> #N/A | F36: =IF($C$30=料金比較表!$C$1,(HLOOKUP('2025年8月'!F$29,料金比較表!$10:$20,'2025年8月'!$A36,FALSE)),IF($C$30=料金比較表!$C$2,(HLOOKUP('2025年8月'!F$29,料金比較表!$23:$33,'2025年8月'!$A36,FALSE)),IF($C$30=料金比較表!$C$3,(HLOOKUP('2025年8月'!F$29,料金比較表!$36:$46,'2025年8月'!$A36,FALSE)),IF($C$30=料金比較表!$C$4,(HLOOKUP('2025年8月'!F$29,料金比較表!$48:$60,'2025年8月'!$A36,FALSE)),IF($C$30=料金比較表!$C$5,(HLOOKUP('2025年8月'!F$29,料金比較表!$61:$71,'2025年8月'!$A36,FALSE)),IF($C$30=料金比較表!$C$6,(HLOOKUP('2025年8月'!F$29,料金比較表!$74:$84,'2025年8月'!$A36,FALSE)))))))) -> #N/A | G36: =IF($C$30=料金比較表!$C$1,(HLOOKUP('2025年8月'!G$29,料金比較表!$10:$20,'2025年8月'!$A36,FALSE)),IF($C$30=料金比較表!$C$2,(HLOOKUP('2025年8月'!G$29,料金比較表!$23:$33,'2025年8月'!$A36,FALSE)),IF($C$30=料金比較表!$C$3,(HLOOKUP('2025年8月'!G$29,料金比較表!$36:$46,'2025年8月'!$A36,FALSE)),IF($C$30=料金比較表!$C$4,(HLOOKUP('2025年8月'!G$29,料金比較表!$48:$60,'2025年8月'!$A36,FALSE)),IF($C$30=料金比較表!$C$5,(HLOOKUP('2025年8月'!G$29,料金比較表!$61:$71,'2025年8月'!$A36,FALSE)),IF($C$30=料金比較表!$C$6,(HLOOKUP('2025年8月'!G$29,料金比較表!$74:$84,'2025年8月'!$A36,FALSE)))))))) -> #N/A | H36: =IF($C$30=料金比較表!$C$1,(HLOOKUP('2025年8月'!H$29,料金比較表!$10:$20,'2025年8月'!$A36,FALSE)),IF($C$30=料金比較表!$C$2,(HLOOKUP('2025年8月'!H$29,料金比較表!$23:$33,'2025年8月'!$A36,FALSE)),IF($C$30=料金比較表!$C$3,(HLOOKUP('2025年8月'!H$29,料金比較表!$36:$46,'2025年8月'!$A36,FALSE)),IF($C$30=料金比較表!$C$4,(HLOOKUP('2025年8月'!H$29,料金比較表!$48:$60,'2025年8月'!$A36,FALSE)),IF($C$30=料金比較表!$C$5,(HLOOKUP('2025年8月'!H$29,料金比較表!$61:$71,'2025年8月'!$A36,FALSE)),IF($C$30=料金比較表!$C$6,(HLOOKUP('2025年8月'!H$29,料金比較表!$74:$84,'2025年8月'!$A36,FALSE)))))))) -> #N/A | I36: =IF($C$30=料金比較表!$C$1,(HLOOKUP('2025年8月'!I$29,料金比較表!$10:$20,'2025年8月'!$A36,FALSE)),IF($C$30=料金比較表!$C$2,(HLOOKUP('2025年8月'!I$29,料金比較表!$23:$33,'2025年8月'!$A36,FALSE)),IF($C$30=料金比較表!$C$3,(HLOOKUP('2025年8月'!I$29,料金比較表!$36:$46,'2025年8月'!$A36,FALSE)),IF($C$30=料金比較表!$C$4,(HLOOKUP('2025年8月'!I$29,料金比較表!$48:$60,'2025年8月'!$A36,FALSE)),IF($C$30=料金比較表!$C$5,(HLOOKUP('2025年8月'!I$29,料金比較表!$61:$71,'2025年8月'!$A36,FALSE)),IF($C$30=料金比較表!$C$6,(HLOOKUP('2025年8月'!I$29,料金比較表!$74:$84,'2025年8月'!$A36,FALSE)))))))) -> #N/A | J36: =IF($C$30=料金比較表!$C$1,(HLOOKUP('2025年8月'!J$29,料金比較表!$10:$20,'2025年8月'!$A36,FALSE)),IF($C$30=料金比較表!$C$2,(HLOOKUP('2025年8月'!J$29,料金比較表!$23:$33,'2025年8月'!$A36,FALSE)),IF($C$30=料金比較表!$C$3,(HLOOKUP('2025年8月'!J$29,料金比較表!$36:$46,'2025年8月'!$A36,FALSE)),IF($C$30=料金比較表!$C$4,(HLOOKUP('2025年8月'!J$29,料金比較表!$48:$60,'2025年8月'!$A36,FALSE)),IF($C$30=料金比較表!$C$5,(HLOOKUP('2025年8月'!J$29,料金比較表!$61:$71,'2025年8月'!$A36,FALSE)),IF($C$30=料金比較表!$C$6,(HLOOKUP('2025年8月'!J$29,料金比較表!$74:$84,'2025年8月'!$A36,FALSE)))))))) -> #N/A | K36: =IF($C$30=料金比較表!$C$1,(HLOOKUP('2025年8月'!K$29,料金比較表!$10:$20,'2025年8月'!$A36,FALSE)),IF($C$30=料金比較表!$C$2,(HLOOKUP('2025年8月'!K$29,料金比較表!$23:$33,'2025年8月'!$A36,FALSE)),IF($C$30=料金比較表!$C$3,(HLOOKUP('2025年8月'!K$29,料金比較表!$36:$46,'2025年8月'!$A36,FALSE)),IF($C$30=料金比較表!$C$4,(HLOOKUP('2025年8月'!K$29,料金比較表!$48:$60,'2025年8月'!$A36,FALSE)),IF($C$30=料金比較表!$C$5,(HLOOKUP('2025年8月'!K$29,料金比較表!$61:$71,'2025年8月'!$A36,FALSE)),IF($C$30=料金比較表!$C$6,(HLOOKUP('2025年8月'!K$29,料金比較表!$74:$84,'2025年8月'!$A36,FALSE)))))))) -> #N/A | ... AH36: =IF($C$30=料金比較表!$C$1,(HLOOKUP('2025年8月'!AH$29,料金比較表!$10:$20,'2025年8月'!$A36,FALSE)),IF($C$30=料金比較表!$C$2,(HLOOKUP('2025年8月'!AH$29,料金比較表!$23:$33,'2025年8月'!$A36,FALSE)),IF($C$30=料金比較表!$C$3,(HLOOKUP('2025年8月'!AH$29,料金比較表!$36:$46,'2025年8月'!$A36,FALSE)),IF($C$30=料金比較表!$C$4,(HLOOKUP('2025年8月'!AH$29,料金比較表!$48:$60,'2025年8月'!$A36,FALSE)),IF($C$30=料金比較表!$C$5,(HLOOKUP('2025年8月'!AH$29,料金比較表!$61:$71,'2025年8月'!$A36,FALSE)),IF($C$30=料金比較表!$C$6,(HLOOKUP('2025年8月'!AH$29,料金比較表!$74:$84,'2025年8月'!$A36,FALSE)))))))) -> #N/A
A37: =A36+1 -> 9 | B37: =料金比較表!C18 -> 0 | D37: =IF($C$30=料金比較表!$C$1,(HLOOKUP('2025年8月'!D$29,料金比較表!$10:$20,'2025年8月'!$A37,FALSE)),IF($C$30=料金比較表!$C$2,(HLOOKUP('2025年8月'!D$29,料金比較表!$23:$33,'2025年8月'!$A37,FALSE)),IF($C$30=料金比較表!$C$3,(HLOOKUP('2025年8月'!D$29,料金比較表!$36:$46,'2025年8月'!$A37,FALSE)),IF($C$30=料金比較表!$C$4,(HLOOKUP('2025年8月'!D$29,料金比較表!$48:$60,'2025年8月'!$A37,FALSE)),IF($C$30=料金比較表!$C$5,(HLOOKUP('2025年8月'!D$29,料金比較表!$61:$71,'2025年8月'!$A37,FALSE)),IF($C$30=料金比較表!$C$6,(HLOOKUP('2025年8月'!D$29,料金比較表!$74:$84,'2025年8月'!$A37,FALSE)))))))) -> #N/A | E37: =IF($C$30=料金比較表!$C$1,(HLOOKUP('2025年8月'!E$29,料金比較表!$10:$20,'2025年8月'!$A37,FALSE)),IF($C$30=料金比較表!$C$2,(HLOOKUP('2025年8月'!E$29,料金比較表!$23:$33,'2025年8月'!$A37,FALSE)),IF($C$30=料金比較表!$C$3,(HLOOKUP('2025年8月'!E$29,料金比較表!$36:$46,'2025年8月'!$A37,FALSE)),IF($C$30=料金比較表!$C$4,(HLOOKUP('2025年8月'!E$29,料金比較表!$48:$60,'2025年8月'!$A37,FALSE)),IF($C$30=料金比較表!$C$5,(HLOOKUP('2025年8月'!E$29,料金比較表!$61:$71,'2025年8月'!$A37,FALSE)),IF($C$30=料金比較表!$C$6,(HLOOKUP('2025年8月'!E$29,料金比較表!$74:$84,'2025年8月'!$A37,FALSE)))))))) -> #N/A | F37: =IF($C$30=料金比較表!$C$1,(HLOOKUP('2025年8月'!F$29,料金比較表!$10:$20,'2025年8月'!$A37,FALSE)),IF($C$30=料金比較表!$C$2,(HLOOKUP('2025年8月'!F$29,料金比較表!$23:$33,'2025年8月'!$A37,FALSE)),IF($C$30=料金比較表!$C$3,(HLOOKUP('2025年8月'!F$29,料金比較表!$36:$46,'2025年8月'!$A37,FALSE)),IF($C$30=料金比較表!$C$4,(HLOOKUP('2025年8月'!F$29,料金比較表!$48:$60,'2025年8月'!$A37,FALSE)),IF($C$30=料金比較表!$C$5,(HLOOKUP('2025年8月'!F$29,料金比較表!$61:$71,'2025年8月'!$A37,FALSE)),IF($C$30=料金比較表!$C$6,(HLOOKUP('2025年8月'!F$29,料金比較表!$74:$84,'2025年8月'!$A37,FALSE)))))))) -> #N/A | G37: =IF($C$30=料金比較表!$C$1,(HLOOKUP('2025年8月'!G$29,料金比較表!$10:$20,'2025年8月'!$A37,FALSE)),IF($C$30=料金比較表!$C$2,(HLOOKUP('2025年8月'!G$29,料金比較表!$23:$33,'2025年8月'!$A37,FALSE)),IF($C$30=料金比較表!$C$3,(HLOOKUP('2025年8月'!G$29,料金比較表!$36:$46,'2025年8月'!$A37,FALSE)),IF($C$30=料金比較表!$C$4,(HLOOKUP('2025年8月'!G$29,料金比較表!$48:$60,'2025年8月'!$A37,FALSE)),IF($C$30=料金比較表!$C$5,(HLOOKUP('2025年8月'!G$29,料金比較表!$61:$71,'2025年8月'!$A37,FALSE)),IF($C$30=料金比較表!$C$6,(HLOOKUP('2025年8月'!G$29,料金比較表!$74:$84,'2025年8月'!$A37,FALSE)))))))) -> #N/A | H37: =IF($C$30=料金比較表!$C$1,(HLOOKUP('2025年8月'!H$29,料金比較表!$10:$20,'2025年8月'!$A37,FALSE)),IF($C$30=料金比較表!$C$2,(HLOOKUP('2025年8月'!H$29,料金比較表!$23:$33,'2025年8月'!$A37,FALSE)),IF($C$30=料金比較表!$C$3,(HLOOKUP('2025年8月'!H$29,料金比較表!$36:$46,'2025年8月'!$A37,FALSE)),IF($C$30=料金比較表!$C$4,(HLOOKUP('2025年8月'!H$29,料金比較表!$48:$60,'2025年8月'!$A37,FALSE)),IF($C$30=料金比較表!$C$5,(HLOOKUP('2025年8月'!H$29,料金比較表!$61:$71,'2025年8月'!$A37,FALSE)),IF($C$30=料金比較表!$C$6,(HLOOKUP('2025年8月'!H$29,料金比較表!$74:$84,'2025年8月'!$A37,FALSE)))))))) -> #N/A | I37: =IF($C$30=料金比較表!$C$1,(HLOOKUP('2025年8月'!I$29,料金比較表!$10:$20,'2025年8月'!$A37,FALSE)),IF($C$30=料金比較表!$C$2,(HLOOKUP('2025年8月'!I$29,料金比較表!$23:$33,'2025年8月'!$A37,FALSE)),IF($C$30=料金比較表!$C$3,(HLOOKUP('2025年8月'!I$29,料金比較表!$36:$46,'2025年8月'!$A37,FALSE)),IF($C$30=料金比較表!$C$4,(HLOOKUP('2025年8月'!I$29,料金比較表!$48:$60,'2025年8月'!$A37,FALSE)),IF($C$30=料金比較表!$C$5,(HLOOKUP('2025年8月'!I$29,料金比較表!$61:$71,'2025年8月'!$A37,FALSE)),IF($C$30=料金比較表!$C$6,(HLOOKUP('2025年8月'!I$29,料金比較表!$74:$84,'2025年8月'!$A37,FALSE)))))))) -> #N/A | J37: =IF($C$30=料金比較表!$C$1,(HLOOKUP('2025年8月'!J$29,料金比較表!$10:$20,'2025年8月'!$A37,FALSE)),IF($C$30=料金比較表!$C$2,(HLOOKUP('2025年8月'!J$29,料金比較表!$23:$33,'2025年8月'!$A37,FALSE)),IF($C$30=料金比較表!$C$3,(HLOOKUP('2025年8月'!J$29,料金比較表!$36:$46,'2025年8月'!$A37,FALSE)),IF($C$30=料金比較表!$C$4,(HLOOKUP('2025年8月'!J$29,料金比較表!$48:$60,'2025年8月'!$A37,FALSE)),IF($C$30=料金比較表!$C$5,(HLOOKUP('2025年8月'!J$29,料金比較表!$61:$71,'2025年8月'!$A37,FALSE)),IF($C$30=料金比較表!$C$6,(HLOOKUP('2025年8月'!J$29,料金比較表!$74:$84,'2025年8月'!$A37,FALSE)))))))) -> #N/A | K37: =IF($C$30=料金比較表!$C$1,(HLOOKUP('2025年8月'!K$29,料金比較表!$10:$20,'2025年8月'!$A37,FALSE)),IF($C$30=料金比較表!$C$2,(HLOOKUP('2025年8月'!K$29,料金比較表!$23:$33,'2025年8月'!$A37,FALSE)),IF($C$30=料金比較表!$C$3,(HLOOKUP('2025年8月'!K$29,料金比較表!$36:$46,'2025年8月'!$A37,FALSE)),IF($C$30=料金比較表!$C$4,(HLOOKUP('2025年8月'!K$29,料金比較表!$48:$60,'2025年8月'!$A37,FALSE)),IF($C$30=料金比較表!$C$5,(HLOOKUP('2025年8月'!K$29,料金比較表!$61:$71,'2025年8月'!$A37,FALSE)),IF($C$30=料金比較表!$C$6,(HLOOKUP('2025年8月'!K$29,料金比較表!$74:$84,'2025年8月'!$A37,FALSE)))))))) -> #N/A | ... AH37: =IF($C$30=料金比較表!$C$1,(HLOOKUP('2025年8月'!AH$29,料金比較表!$10:$20,'2025年8月'!$A37,FALSE)),IF($C$30=料金比較表!$C$2,(HLOOKUP('2025年8月'!AH$29,料金比較表!$23:$33,'2025年8月'!$A37,FALSE)),IF($C$30=料金比較表!$C$3,(HLOOKUP('2025年8月'!AH$29,料金比較表!$36:$46,'2025年8月'!$A37,FALSE)),IF($C$30=料金比較表!$C$4,(HLOOKUP('2025年8月'!AH$29,料金比較表!$48:$60,'2025年8月'!$A37,FALSE)),IF($C$30=料金比較表!$C$5,(HLOOKUP('2025年8月'!AH$29,料金比較表!$61:$71,'2025年8月'!$A37,FALSE)),IF($C$30=料金比較表!$C$6,(HLOOKUP('2025年8月'!AH$29,料金比較表!$74:$84,'2025年8月'!$A37,FALSE)))))))) -> #N/A
A38: =A37+1 -> 10 | B38: =料金比較表!C19 -> プールヴィラ 古宇利島 ｂｙ コルディオスマートリゾート | C38: 現最安値 | D38: =IF($C$30=料金比較表!$C$1,(HLOOKUP('2025年8月'!D$29,料金比較表!$10:$20,'2025年8月'!$A38,FALSE)),IF($C$30=料金比較表!$C$2,(HLOOKUP('2025年8月'!D$29,料金比較表!$23:$33,'2025年8月'!$A38,FALSE)),IF($C$30=料金比較表!$C$3,(HLOOKUP('2025年8月'!D$29,料金比較表!$36:$46,'2025年8月'!$A38,FALSE)),IF($C$30=料金比較表!$C$4,(HLOOKUP('2025年8月'!D$29,料金比較表!$48:$60,'2025年8月'!$A38,FALSE)),IF($C$30=料金比較表!$C$5,(HLOOKUP('2025年8月'!D$29,料金比較表!$61:$71,'2025年8月'!$A38,FALSE)),IF($C$30=料金比較表!$C$6,(HLOOKUP('2025年8月'!D$29,料金比較表!$74:$84,'2025年8月'!$A38,FALSE)))))))) -> #N/A | E38: =IF($C$30=料金比較表!$C$1,(HLOOKUP('2025年8月'!E$29,料金比較表!$10:$20,'2025年8月'!$A38,FALSE)),IF($C$30=料金比較表!$C$2,(HLOOKUP('2025年8月'!E$29,料金比較表!$23:$33,'2025年8月'!$A38,FALSE)),IF($C$30=料金比較表!$C$3,(HLOOKUP('2025年8月'!E$29,料金比較表!$36:$46,'2025年8月'!$A38,FALSE)),IF($C$30=料金比較表!$C$4,(HLOOKUP('2025年8月'!E$29,料金比較表!$48:$60,'2025年8月'!$A38,FALSE)),IF($C$30=料金比較表!$C$5,(HLOOKUP('2025年8月'!E$29,料金比較表!$61:$71,'2025年8月'!$A38,FALSE)),IF($C$30=料金比較表!$C$6,(HLOOKUP('2025年8月'!E$29,料金比較表!$74:$84,'2025年8月'!$A38,FALSE)))))))) -> #N/A | F38: =IF($C$30=料金比較表!$C$1,(HLOOKUP('2025年8月'!F$29,料金比較表!$10:$20,'2025年8月'!$A38,FALSE)),IF($C$30=料金比較表!$C$2,(HLOOKUP('2025年8月'!F$29,料金比較表!$23:$33,'2025年8月'!$A38,FALSE)),IF($C$30=料金比較表!$C$3,(HLOOKUP('2025年8月'!F$29,料金比較表!$36:$46,'2025年8月'!$A38,FALSE)),IF($C$30=料金比較表!$C$4,(HLOOKUP('2025年8月'!F$29,料金比較表!$48:$60,'2025年8月'!$A38,FALSE)),IF($C$30=料金比較表!$C$5,(HLOOKUP('2025年8月'!F$29,料金比較表!$61:$71,'2025年8月'!$A38,FALSE)),IF($C$30=料金比較表!$C$6,(HLOOKUP('2025年8月'!F$29,料金比較表!$74:$84,'2025年8月'!$A38,FALSE)))))))) -> #N/A | G38: =IF($C$30=料金比較表!$C$1,(HLOOKUP('2025年8月'!G$29,料金比較表!$10:$20,'2025年8月'!$A38,FALSE)),IF($C$30=料金比較表!$C$2,(HLOOKUP('2025年8月'!G$29,料金比較表!$23:$33,'2025年8月'!$A38,FALSE)),IF($C$30=料金比較表!$C$3,(HLOOKUP('2025年8月'!G$29,料金比較表!$36:$46,'2025年8月'!$A38,FALSE)),IF($C$30=料金比較表!$C$4,(HLOOKUP('2025年8月'!G$29,料金比較表!$48:$60,'2025年8月'!$A38,FALSE)),IF($C$30=料金比較表!$C$5,(HLOOKUP('2025年8月'!G$29,料金比較表!$61:$71,'2025年8月'!$A38,FALSE)),IF($C$30=料金比較表!$C$6,(HLOOKUP('2025年8月'!G$29,料金比較表!$74:$84,'2025年8月'!$A38,FALSE)))))))) -> #N/A | H38: =IF($C$30=料金比較表!$C$1,(HLOOKUP('2025年8月'!H$29,料金比較表!$10:$20,'2025年8月'!$A38,FALSE)),IF($C$30=料金比較表!$C$2,(HLOOKUP('2025年8月'!H$29,料金比較表!$23:$33,'2025年8月'!$A38,FALSE)),IF($C$30=料金比較表!$C$3,(HLOOKUP('2025年8月'!H$29,料金比較表!$36:$46,'2025年8月'!$A38,FALSE)),IF($C$30=料金比較表!$C$4,(HLOOKUP('2025年8月'!H$29,料金比較表!$48:$60,'2025年8月'!$A38,FALSE)),IF($C$30=料金比較表!$C$5,(HLOOKUP('2025年8月'!H$29,料金比較表!$61:$71,'2025年8月'!$A38,FALSE)),IF($C$30=料金比較表!$C$6,(HLOOKUP('2025年8月'!H$29,料金比較表!$74:$84,'2025年8月'!$A38,FALSE)))))))) -> #N/A | I38: =IF($C$30=料金比較表!$C$1,(HLOOKUP('2025年8月'!I$29,料金比較表!$10:$20,'2025年8月'!$A38,FALSE)),IF($C$30=料金比較表!$C$2,(HLOOKUP('2025年8月'!I$29,料金比較表!$23:$33,'2025年8月'!$A38,FALSE)),IF($C$30=料金比較表!$C$3,(HLOOKUP('2025年8月'!I$29,料金比較表!$36:$46,'2025年8月'!$A38,FALSE)),IF($C$30=料金比較表!$C$4,(HLOOKUP('2025年8月'!I$29,料金比較表!$48:$60,'2025年8月'!$A38,FALSE)),IF($C$30=料金比較表!$C$5,(HLOOKUP('2025年8月'!I$29,料金比較表!$61:$71,'2025年8月'!$A38,FALSE)),IF($C$30=料金比較表!$C$6,(HLOOKUP('2025年8月'!I$29,料金比較表!$74:$84,'2025年8月'!$A38,FALSE)))))))) -> #N/A | J38: =IF($C$30=料金比較表!$C$1,(HLOOKUP('2025年8月'!J$29,料金比較表!$10:$20,'2025年8月'!$A38,FALSE)),IF($C$30=料金比較表!$C$2,(HLOOKUP('2025年8月'!J$29,料金比較表!$23:$33,'2025年8月'!$A38,FALSE)),IF($C$30=料金比較表!$C$3,(HLOOKUP('2025年8月'!J$29,料金比較表!$36:$46,'2025年8月'!$A38,FALSE)),IF($C$30=料金比較表!$C$4,(HLOOKUP('2025年8月'!J$29,料金比較表!$48:$60,'2025年8月'!$A38,FALSE)),IF($C$30=料金比較表!$C$5,(HLOOKUP('2025年8月'!J$29,料金比較表!$61:$71,'2025年8月'!$A38,FALSE)),IF($C$30=料金比較表!$C$6,(HLOOKUP('2025年8月'!J$29,料金比較表!$74:$84,'2025年8月'!$A38,FALSE)))))))) -> #N/A | K38: =IF($C$30=料金比較表!$C$1,(HLOOKUP('2025年8月'!K$29,料金比較表!$10:$20,'2025年8月'!$A38,FALSE)),IF($C$30=料金比較表!$C$2,(HLOOKUP('2025年8月'!K$29,料金比較表!$23:$33,'2025年8月'!$A38,FALSE)),IF($C$30=料金比較表!$C$3,(HLOOKUP('2025年8月'!K$29,料金比較表!$36:$46,'2025年8月'!$A38,FALSE)),IF($C$30=料金比較表!$C$4,(HLOOKUP('2025年8月'!K$29,料金比較表!$48:$60,'2025年8月'!$A38,FALSE)),IF($C$30=料金比較表!$C$5,(HLOOKUP('2025年8月'!K$29,料金比較表!$61:$71,'2025年8月'!$A38,FALSE)),IF($C$30=料金比較表!$C$6,(HLOOKUP('2025年8月'!K$29,料金比較表!$74:$84,'2025年8月'!$A38,FALSE)))))))) -> #N/A | ... AH38: =IF($C$30=料金比較表!$C$1,(HLOOKUP('2025年8月'!AH$29,料金比較表!$10:$20,'2025年8月'!$A38,FALSE)),IF($C$30=料金比較表!$C$2,(HLOOKUP('2025年8月'!AH$29,料金比較表!$23:$33,'2025年8月'!$A38,FALSE)),IF($C$30=料金比較表!$C$3,(HLOOKUP('2025年8月'!AH$29,料金比較表!$36:$46,'2025年8月'!$A38,FALSE)),IF($C$30=料金比較表!$C$4,(HLOOKUP('2025年8月'!AH$29,料金比較表!$48:$60,'2025年8月'!$A38,FALSE)),IF($C$30=料金比較表!$C$5,(HLOOKUP('2025年8月'!AH$29,料金比較表!$61:$71,'2025年8月'!$A38,FALSE)),IF($C$30=料金比較表!$C$6,(HLOOKUP('2025年8月'!AH$29,料金比較表!$74:$84,'2025年8月'!$A38,FALSE)))))))) -> #N/A
B39: =B38 -> プールヴィラ 古宇利島 ｂｙ コルディオスマートリゾート | C39: =$B$3&"(単泊)" -> ラグジュアリープールヴィラ(単泊) | I39: V | J39: V | K39: T | L39: V | M39: V | N39: X | O39: T | P39: Q | Q39: Q | R39: Q | S39: S | T39: S | U39: P | V39: T | W39: Q | X39: T | Y39: M | Z39: R | AA39: W | AB39: M | AC39: N | AD39: S | AE39: P | AF39: P | AG39: S | AH39: K
C40: =$F$1 -> WEB割 | D40: =IFERROR(IF(D64=0,"Close",(IFERROR(HLOOKUP(D39,$D$2:$BC$3,2,FALSE),""))),"") | E40: =IFERROR(IF(E64=0,"Close",(IFERROR(HLOOKUP(E39,$D$2:$BC$3,2,FALSE),""))),"") | F40: =IFERROR(IF(F64=0,"Close",(IFERROR(HLOOKUP(F39,$D$2:$BC$3,2,FALSE),""))),"") | G40: =IFERROR(IF(G64=0,"Close",(IFERROR(HLOOKUP(G39,$D$2:$BC$3,2,FALSE),""))),"") | H40: =IFERROR(IF(H64=0,"Close",(IFERROR(HLOOKUP(H39,$D$2:$BC$3,2,FALSE),""))),"") | I40: =IFERROR(IF(I64=0,"Close",(IFERROR(HLOOKUP(I39,$D$2:$BC$3,2,FALSE),""))),"") -> 117000 | J40: =IFERROR(IF(J64=0,"Close",(IFERROR(HLOOKUP(J39,$D$2:$BC$3,2,FALSE),""))),"") -> 117000 | K40: =IFERROR(IF(K64=0,"Close",(IFERROR(HLOOKUP(K39,$D$2:$BC$3,2,FALSE),""))),"") -> 95000 | ... AH40: =IFERROR(IF(AH64=0,"Close",(IFERROR(HLOOKUP(AH39,$D$2:$BC$3,2,FALSE),""))),"") -> 64500
C41: =$B$3&"(連泊)" -> ラグジュアリープールヴィラ(連泊) | D41: =IF(ISBLANK(D$39),"",D$39) | E41: =IF(ISBLANK(E$39),"",E$39) | F41: =IF(ISBLANK(F$39),"",F$39) | G41: =IF(ISBLANK(G$39),"",G$39) | H41: =IF(ISBLANK(H$39),"",H$39) | I41: =IF(ISBLANK(I$39),"",I$39) -> V | J41: =IF(ISBLANK(J$39),"",J$39) -> V | K41: =IF(ISBLANK(K$39),"",K$39) -> T | ... AH41: =IF(ISBLANK(AH$39),"",AH$39) -> K
C42: =$F$10 -> 連泊 | D42: =IFERROR(IF(D64=0,"Close",(IFERROR(HLOOKUP(D41,$D$11:$BC$12,2,FALSE),""))),"") | E42: =IFERROR(IF(E64=0,"Close",(IFERROR(HLOOKUP(E41,$D$11:$BC$12,2,FALSE),""))),"") | F42: =IFERROR(IF(F64=0,"Close",(IFERROR(HLOOKUP(F41,$D$11:$BC$12,2,FALSE),""))),"") | G42: =IFERROR(IF(G64=0,"Close",(IFERROR(HLOOKUP(G41,$D$11:$BC$12,2,FALSE),""))),"") | H42: =IFERROR(IF(H64=0,"Close",(IFERROR(HLOOKUP(H41,$D$11:$BC$12,2,FALSE),""))),"") | I42: =IFERROR(IF(I64=0,"Close",(IFERROR(HLOOKUP(I41,$D$11:$BC$12,2,FALSE),""))),"") -> 105300 | J42: =IFERROR(IF(J64=0,"Close",(IFERROR(HLOOKUP(J41,$D$11:$BC$12,2,FALSE),""))),"") -> 105300 | K42: =IFERROR(IF(K64=0,"Close",(IFERROR(HLOOKUP(K41,$D$11:$BC$12,2,FALSE),""))),"") -> 85500 | ... AH42: =IFERROR(IF(AH64=0,"Close",(IFERROR(HLOOKUP(AH41,$D$11:$BC$12,2,FALSE),""))),"") -> 58050
C43: =$B$4&"(単泊)" -> with SAUNA(単泊) | D43: =IF(ISBLANK(D$39),"",D$39) | E43: =IF(ISBLANK(E$39),"",E$39) | F43: =IF(ISBLANK(F$39),"",F$39) | G43: =IF(ISBLANK(G$39),"",G$39) | H43: =IF(ISBLANK(H$39),"",H$39) | I43: =IF(ISBLANK(I$39),"",I$39) -> V | J43: =IF(ISBLANK(J$39),"",J$39) -> V | K43: =IF(ISBLANK(K$39),"",K$39) -> T | ... AH43: =IF(ISBLANK(AH$39),"",AH$39) -> K
C44: =$F$1 -> WEB割 | D44: =IFERROR(IF(D65=0,"Close",(IFERROR(HLOOKUP(D43,$D$2:$BC$4,3,FALSE),""))),"") | E44: =IFERROR(IF(E65=0,"Close",(IFERROR(HLOOKUP(E43,$D$2:$BC$4,3,FALSE),""))),"") | F44: =IFERROR(IF(F65=0,"Close",(IFERROR(HLOOKUP(F43,$D$2:$BC$4,3,FALSE),""))),"") | G44: =IFERROR(IF(G65=0,"Close",(IFERROR(HLOOKUP(G43,$D$2:$BC$4,3,FALSE),""))),"") | H44: =IFERROR(IF(H65=0,"Close",(IFERROR(HLOOKUP(H43,$D$2:$BC$4,3,FALSE),""))),"") | I44: =IFERROR(IF(I65=0,"Close",(IFERROR(HLOOKUP(I43,$D$2:$BC$4,3,FALSE),""))),"") -> 127000 | J44: =IFERROR(IF(J65=0,"Close",(IFERROR(HLOOKUP(J43,$D$2:$BC$4,3,FALSE),""))),"") -> 127000 | K44: =IFERROR(IF(K65=0,"Close",(IFERROR(HLOOKUP(K43,$D$2:$BC$4,3,FALSE),""))),"") -> 105000 | ... AH44: =IFERROR(IF(AH65=0,"Close",(IFERROR(HLOOKUP(AH43,$D$2:$BC$4,3,FALSE),""))),"") -> 74500
C45: =$B$4&"(連泊)" -> with SAUNA(連泊) | D45: =IF(ISBLANK(D$41),"",D$41) | E45: =IF(ISBLANK(E$41),"",E$41) | F45: =IF(ISBLANK(F$41),"",F$41) | G45: =IF(ISBLANK(G$41),"",G$41) | H45: =IF(ISBLANK(H$41),"",H$41) | I45: =IF(ISBLANK(I$41),"",I$41) -> V | J45: =IF(ISBLANK(J$41),"",J$41) -> V | K45: =IF(ISBLANK(K$41),"",K$41) -> T | ... AH45: =IF(ISBLANK(AH$41),"",AH$41) -> K
